Workbook
Name Slicer_Mandatory_BY_Version: #N/A
Name Slicer_Mandatory_BY_Version1: #N/A

Sheet Sheet2
A1: Wave1 - Simple Pages
A2: Wave2 - Modarate Pages
A3: Wave3 - Complex Pages

Sheet Sheet1

Sheet Additional comment MFG & QA
A1: Product | B1: Module | C1: Comment | D1: Total Features
A2: Manufacturing | B2: Manufacturing | C2: Included in Mfg Wave | D2: 38
A3: Manufacturing | B3: Smart Operations | C3: Excluded from Mfg Wave, since this is an entirely new offering | D3: 36
A4: Manufacturing | B4: Kanban | C4: Included in Mfg Wave | D4: 3
A5: Manufacturing | B5: Flow Manufacturing | C5: Excluded from Mfg Wave, since this is an entirely new offering | D5: 7
A6: Manufacturing | B6: Supply Chain Orchestration | C6: Included in Mfg Wave | D6: 5
A7: Quality Management | B7: Quality Inspection Management | C7: Included in QA Wave | D7: 11
C10: Product | D10: Manufacturing
C11: Module | D11: Manufacturing, Kanban, Supply Chain Orchestration
C12: Row Labels | D12: Count of Redwood Features
C13: Wave1 - Simple Pages | D13: 20
C14: Wave2 - Modarate Pages | D14: 14
C15: Wave3 - Complex Pages | D15: 12
C16: Grand Total | D16: 46
C23: Product | D23: Quality Management
C24: Module | D24: Quality Management
C25: Row Labels | D25: Count of Redwood Features
C26: Wave1 - Simple Pages | D26: 11
C27: Grand Total | D27: 11

Sheet Feature By Release
A3: Count of S.no | B3: Column Labels
A4: Row Labels | B4: 22B | C4: 22C | D4: 22D | E4: 23A | F4: 23B | G4: 23C | H4: 23D | I4: 24A | J4: 24B | K4: 24C | L4: 24D | M4: 25A | N4: 25B | O4: 25C | P4: 25D | Q4: 26A | R4: Grand Total
A5: Inventory Management | I5: 1 | J5: 2 | K5: 7 | L5: 17 | M5: 43 | N5: 77 | O5: 31 | P5: 34 | Q5: 32 | R5: 244
A6: Maintenance | M6: 4 | N6: 5 | O6: 14 | P6: 8 | Q6: 14 | R6: 45
A7: Manufacturing | J7: 3 | K7: 7 | L7: 14 | M7: 24 | N7: 19 | O7: 11 | P7: 6 | Q7: 14 | R7: 98
A8: Order Management | F8: 1 | G8: 3 | K8: 2 | L8: 8 | M8: 12 | N8: 19 | O8: 12 | P8: 16 | Q8: 21 | R8: 94
A9: Procurement | B9: 1 | C9: 2 | D9: 5 | E9: 4 | F9: 5 | G9: 4 | H9: 7 | J9: 7 | K9: 9 | L9: 17 | M9: 25 | N9: 40 | O9: 66 | P9: 61 | Q9: 68 | R9: 321
A10: Product Hub | J10: 6 | K10: 1 | L10: 8 | N10: 3 | R10: 18
A11: Product Lifecycle Management | J11: 1 | K11: 1 | P11: 12 | Q11: 20 | R11: 34
A12: Quality Management | J12: 1 | K12: 3 | M12: 1 | N12: 2 | O12: 1 | P12: 3 | Q12: 1 | R12: 12
A13: SCM Common Components | K13: 1 | N13: 1 | P13: 3 | R13: 5
A14: Supply Chain Collaboration | J14: 4 | K14: 3 | L14: 4 | N14: 1 | R14: 12
A15: Supply Chain Orchestration | K15: 3 | M15: 1 | N15: 1 | O15: 6 | P15: 18 | Q15: 9 | R15: 38
A16: Supply Chain Planning | J16: 7 | K16: 14 | L16: 14 | M16: 6 | N16: 43 | O16: 42 | P16: 48 | Q16: 64 | R16: 238
A17: Grand Total | B17: 1 | C17: 2 | D17: 5 | E17: 4 | F17: 6 | G17: 7 | H17: 7 | I17: 1 | J17: 31 | K17: 51 | L17: 82 | M17: 116 | N17: 211 | O17: 183 | P17: 209 | Q17: 243 | R17: 1159

Sheet Feature by Mandatory
A3: Count of S.no | B3: Column Labels
A4: Row Labels | B4: 25A | C4: 25B | D4: 25C | E4: 25D | F4: 26A | G4: 26B | H4: 26C | I4: 26D | J4: 27A | K4: (blank) | L4: Grand Total
A5: Inventory Management | B5: 2 | C5: 92 | D5: 45 | E5: 47 | F5: 30 | G5: 12 | I5: 1 | J5: 15 | L5: 244
A6: Maintenance | F6: 6 | G6: 1 | H6: 31 | I6: 7 | L6: 45
A7: Manufacturing | B7: 2 | C7: 10 | D7: 4 | E7: 12 | F7: 66 | G7: 1 | H7: 3 | L7: 98
A8: Order Management | B8: 1 | C8: 3 | D8: 5 | E8: 5 | F8: 10 | G8: 67 | J8: 3 | L8: 94
A9: Procurement | C9: 5 | D9: 78 | E9: 37 | F9: 76 | G9: 112 | H9: 3 | J9: 10 | L9: 321
A10: Product Hub | C10: 3 | D10: 2 | E10: 4 | F10: 4 | G10: 2 | H10: 3 | L10: 18
A11: Product Lifecycle Management | E11: 7 | F11: 6 | G11: 6 | I11: 13 | K11: 2 | L11: 34
A12: Quality Management | C12: 1 | E12: 6 | F12: 3 | G12: 2 | L12: 12
A13: SCM Common Components | D13: 1 | E13: 2 | F13: 1 | H13: 1 | L13: 5
A14: Supply Chain Collaboration | C14: 3 | E14: 1 | F14: 3 | G14: 2 | H14: 3 | L14: 12
A15: Supply Chain Orchestration | D15: 5 | E15: 9 | F15: 8 | G15: 12 | I15: 1 | J15: 3 | L15: 38
A16: Supply Chain Planning | F16: 1 | G16: 237 | L16: 238
A17: Grand Total | B17: 5 | C17: 117 | D17: 140 | E17: 130 | F17: 214 | G17: 454 | H17: 44 | I17: 22 | J17: 31 | K17: 2 | L17: 1159

Sheet Feature By Wave
A3: Count of S.no | B3: Column Labels
A4: Row Labels | B4: Wave1 - Simple Pages | C4: Wave2 - Modarate Pages | D4: Wave3 - Complex Pages | E4: (blank) | F4: Grand Total
A5: Inventory Management | B5: 118 | C5: 108 | D5: 18 | F5: 244
A6: Maintenance | B6: 17 | C6: 16 | D6: 12 | F6: 45
A7: Manufacturing | B7: 15 | C7: 52 | D7: 31 | F7: 98
A8: Order Management | B8: 32 | C8: 34 | D8: 28 | F8: 94
A9: Procurement | B9: 216 | C9: 97 | D9: 8 | F9: 321
A10: Product Hub | B10: 9 | C10: 7 | D10: 2 | F10: 18
A11: Product Lifecycle Management | B11: 13 | C11: 9 | D11: 11 | E11: 1 | F11: 34
A12: Quality Management | B12: 12 | F12: 12
A13: SCM Common Components | B13: 2 | C13: 3 | F13: 5
A14: Supply Chain Collaboration | B14: 10 | C14: 1 | D14: 1 | F14: 12
A15: Supply Chain Orchestration | B15: 19 | C15: 16 | D15: 3 | F15: 38
A16: Supply Chain Planning | B16: 77 | C16: 119 | D16: 42 | F16: 238
A17: Grand Total | B17: 540 | C17: 462 | D17: 156 | E17: 1 | F17: 1159

Sheet 1.11 - Final Features List
A1: S.no | B1: Product | C1: Module | D1: Feature Names | E1: Update Version | F1: Mandate Version | G1: Wave | H1: CSS Mandate Version | I1: Privilage Name | J1: Profile Options Value | K1: Additional Info | L1: Action Required | M1: Availability of PPT | N1: SME | O1: UI Page Names | P1: Remarks
A2: 1 | B2: Inventory Management | C2: Mobile Inventory | D2: Redwood: Create an Interorganization Transfer Using a Mobile Device | E2: 24D | F2: 25B | G2: Wave1 - Simple Pages | H2: 26B | I2: Create Interorganization Transfer Using Responsive Inventory Duty (ORA_INV_CREATE_INTERORG_TRANSFER_PWA_DUTY). | L2: Role Setup | M2: Y | N2: G, Pravalika | O2: Inventory Management (Mobile)
A3: 2 | B3: Inventory Management | C3: Mobile Inventory | D3: Redwood: View the Inventory Management (New) Tile as Inventory Management (Mobile) | E3: 24D | F3: 25B | G3: Wave1 - Simple Pages | H3: 26B | L3: Auto Enabled | N3: G, Pravalika | O3: Inventory Management (Mobile)
A4: 3 | B4: Inventory Management | C4: Mobile Inventory | D4: Redwood: Inspect Received Goods Using a Mobile Device | E4: 24D | F4: 25B | G4: Wave1 - Simple Pages | H4: 26B | I4: New: Inspect goods using the responsive receiving application (ORA_RCV_INSPECT_GOODS_PWA_DUTY) | J4: Manage Inventory Profile Options > ORA_INV_MOBILE_INVENTORY_MANAGEMENT_REDWOOD_ENABLED = Yes | K4: 1. Activate Sandbox to enable the Inventory Management (New) 2. Run the "ESS job to create index definition and perform Initial Ingest to OSCS" Refer: https://docs.oracle.com/en/cloud/saas/readiness/scm/24b/inv24b/24B-inventory-wn-f31373.htm | L4: Profile Option | N4: G, Pravalika | O4: Inventory Management (Mobile)
A5: 4 | B5: Inventory Management | C5: Mobile Inventory | D5: Redwood: View Lot Attributes in Mobile Inventory Transactions | E5: 24D | F5: 25B | G5: Wave1 - Simple Pages | H5: 26B | L5: Auto Enabled | N5: G, Pravalika | O5: Inventory Management (Mobile)
A6: 5 | B6: Inventory Management | C6: Cost Management | D6: Redwood: View Rollup Costs Using a New User Experience | E6: 25A | F6: 25B | G6: Wave1 - Simple Pages | H6: 26A | I6: Users who are assigned a configured job role that contains the following privilege can access this feature: View Rolled Up Costs (CST_REVIEW_ROLLEDUP_COSTS) | J6: On the Manage Administrator Profile Values page, search for and select the ORA_CST_VIEW_ROLLEDUP_COSTS_REDWOOD_ENABLED profile option code. In the Profile Values section, set the Site level to Yes. The default value is No. Click Save and Close. Changes in the profile value will affect users the next time they sign in. Yes = enables the feature No = disables the feature | L6: Role Setup+Profile option | M6: Y | N6: Krishnan, Karthikeyan | O6: Cost Accounting Work Area
A7: 6 | B7: Inventory Management | C7: Cost Management | D7: Redwood: Create and Update Cost Scenarios Using a New User Experience | E7: 25A | F7: 25B | G7: Wave2 - Modarate Pages | H7: 26A | I7: Users who are assigned a configured job role that contains the following privilege can access this feature: Manage Cost Planning Scenario Definition (CST_MANAGE_SCENARIO) | J7: On the Manage Administrator Profile Values page, search for and select the ORA_CST_PLANNING_SCENARIOS_REDWOOD_ENABLED profile option code. In the Profile Values section, set the Site level to Yes. The default value is No. Click Save and Close. Changes in the profile value will affect users the next time they sign in. Yes = enables the feature No = disables the feature | L7: Role Setup+Profile option | M7: Y | N7: Krishnan, Karthikeyan | O7: Cost Accounting Work Area
A8: 7 | B8: Inventory Management | C8: Cost Management | D8: Redwood: Review Standard Costs Import Exceptions Using a New User Experience | E8: 25A | F8: 25B | G8: Wave1 - Simple Pages | H8: 26A | I8: Users who are assigned a configured job role that contains the following privilege can access this feature: Estimate Costs (CST_ESTIMATE_COSTS) | J8: On the Manage Administrator Profile Values page, search for and select the ORA_CST_STD_COST_IMPORT_EXCEPTIONS_REDWOOD_ENABLED profile option code. In the Profile Values section, set the Site level to Yes. The default value is No. Click Save and Close. Changes in the profile value will affect users the next time they sign in. Yes = enables the feature No = disables the feature | L8: Role Setup+Profile option | M8: Y | N8: Krishnan, Karthikeyan | O8: Cost Accounting Work Area
A9: 8 | B9: Inventory Management | C9: Receiving | D9: Redwood: Manage Inbound Shipments and Create ASN or ASBN Using a Redwood Page | E9: 24D | F9: 25C | G9: Wave1 - Simple Pages | H9: 26A | I9: 1. Manage Inbound Shipment Using Responsive Receiving (RCV_MANAGE_INBOUND_SHIPMENT_PWA) 2. Manage Inbound Shipment as Supplier Using Responsive Receiving (RCV_MANAGE_INBOUND_SHIPMENT_AS_SUPPLIER_PWA) 3. Create Advance Shipment Notice Using Responsive Receiving (RCV_CREATE_ADVANCE_SHIPMENT_NOTICE_PWA) 4. Create Advance Shipment Notice as Supplier Using Responsive Receiving (RCV_CREATE_ADVANCE_SHIPMENT_NOTICE_AS_SUPPLIER_PWA) | J9: Manage Receiving Profile Options > 1. ORA_RCV_INBOUND_SHIPMENTS_REDWOOD_ENABLED = Yes 2. ORA_RCV_ADVANCE_SHIPMENT_NOTICE_REDWOOD_ENABLED = Yes 3. ORA_RCV_INBOUND_SHIPMENTS_SUPPLIER_PORTAL_REDWOOD_ENABLED = Yes 4. ORA_RCV_ADVANCE_SHIPMENT_NOTICE_SUPPLIER_PORTAL_REDWOOD_ENABLED = Yes | K9: 1. Activate Sandbox to enable the Inventory Management (New) 2. Run the "ESS job to create index definition and perform Initial Ingest to OSCS" Refer: https://docs.oracle.com/en/cloud/saas/readiness/scm/24b/inv24b/24B-inventory-wn-f31373.htm | L9: Profile Option | M9: Y | N9: G, Pravalika | O9: Receipts
A10: 9 | B10: Inventory Management | C10: Receiving | D10: Redwood: View Receipts and Receipt Returns in Supplier Portal Using a Redwood Page | E10: 24D | F10: 25C | G10: Wave1 - Simple Pages | H10: 26A | I10: View Receiving Receipt and Receipt Return as Supplier (RCV_VIEW_RECEIVING_RECEIPT_AND_RECEIPT_RETURN_AS_SUPPLIER_PRIV) | J10: Manage Receiving Profile Options task > ORA_RCV_RECEIPTS_RETURNS_SUPPLIER_PORTAL_REDWOOD_ENABLED = Yes | L10: Profile Option | M10: Y | N10: G, Pravalika | O10: Supplier Portal
A11: 10 | B11: Inventory Management | C11: Cost Management | D11: Create and Edit Overhead Rates Using Redwood Pages | E11: 24C | F11: 26B | G11: Wave2 - Modarate Pages | H11: 26A | I11: Users who are assigned a configured job role that contains the following privilege can access this feature: Manage Resource and Overhead Rate Plans (CST_MANAGE_RATE_PLANS) | J11: On the Manage Administrator Profile Values page, search for and select the ORA_CST_RESOURCE_RATES_REDWOOD_ENABLED profile option code. In the Profile Values section, set the Site level to Yes. The default value is No. Yes = enables the feature No = disables the feature | L11: Role Setup+Profile option | N11: Krishnan, Karthikeyan | O11: Overhead Rates
A12: 11 | B12: Inventory Management | C12: Fiscal Document Capture | D12: Manage Tolerances Using the Redwood Experience | E12: 24C | F12: 26B | G12: Wave2 - Modarate Pages | H12: 26B | I12: Set Up Fiscal Document Tolerances (CMF_FISCAL_DOC_TOLERANCES) Manage Fiscal Document Tolerances by Web Service (CMF_FISCAL_DOC_TOLERANCE_WEB_SERVICE) | J12: On the Manage Administrator Profile Values page, enable the new ORA_CMF_TOLERANCE_RULES_REDWOOD_ENABLED profile option at Site or Product or User level. Select Yes for the Redwood page for Fiscal Document Tolerance Rules Enabled option. | L12: Role Setup+Profile option | N12: G, Pravalika | O12: Fiscal Document Tolerance Rules
A13: 12 | B13: Supply Chain Orchestration | C13: Supply Chain Orchestration | D13: Manage Documentation and Accounting Rule in Redwood Pages | E13: 24C | F13: 26B | G13: Wave1 - Simple Pages | H13: 26D | I13: Maintain Documentation and Accounting Rules (FOS_MAINTAIN_TRADE_AND_ACCOUNTING_RULES) Manage Documentation and Accounting Rules (FOS_MANAGE_TRADE_AND_ACCOUNTING_RULES) View Documentation and Accounting Rules (FOS_VIEW_TRADE_AND_ACCOUNTING_RULES) | J13: ORA_FOS_TRADE_ACCOUNTING_RULES_REDWOOD_ENABLED | L13: Role Setup+Profile option | M13: Y | N13: Sumalatha, A | O13: Documentation and Accounting Rules
A14: 13 | B14: Supply Chain Orchestration | C14: Supply Chain Orchestration | D14: Manage Transfer Pricing Rule in Redwood Pages | E14: 24C | F14: 26B | G14: Wave1 - Simple Pages | H14: 26D | I14: Maintain Transfer Pricing Rules (FOS_MAINTAIN_TRANSFER_PRICING_RULES) Manage Transfer Pricing Rules (FOS_MANAGE_TRANSFER_PRICING_RULES) View Transfer Pricing Rules (FOS_VIEW_TRANSFER_PRICING_RULES) | J14: ORA_FOS_TRANSFER_PRICING_RULES_REDWOOD_ENABLED | L14: Role Setup+Profile option | M14: Y | N14: Sumalatha, A | O14: Financial Orchestration Work Area
A15: 14 | B15: Inventory Management | C15: Cost Management | D15: Create and Update Resource Rates Using Redwood Pages | E15: 24B | F15: 26B | G15: Wave2 - Modarate Pages | H15: 26A | I15: Users who are assigned a configured job role that contains the following privilege can access this feature: Manage Resource and Overhead Rate Plans (CST_MANAGE_RATE_PLANS) | J15: On the Manage Administrator Profile Values page, search for and select the ORA_CST_RESOURCE_RATES_REDWOOD_ENABLED profile option code. In the Profile Values section, set the Site level to Yes. The default value is No. Yes = enables the feature No = disables the feature | L15: Role Setup+Profile option | N15: Krishnan, Karthikeyan | O15: Resource Rates
A16: 15 | B16: Inventory Management | C16: Cost Management | D16: Redwood: View Scenario Exceptions Using a New User Experience | E16: 25A | F16: 25B | G16: Wave1 - Simple Pages | H16: 26A | I16: Users who are assigned a configured job role that contains the following privilege can access this feature: View Scenario Exceptions (CST_MANAGE_SCENRIO_EXCEPTIONS) | J16: On the Manage Administrator Profile Values page, search for and select the ORA_CST_SCENARIO_EXCEPTIONS_REDWOOD_ENABLED profile option code. In the Profile Values section, set the Site level to Yes. The default value is No. Click Save and Close. Changes in the profile value will affect users the next time they sign in. Yes = enables the feature No = disables the feature | L16: Role Setup+Profile option | M16: Y | N16: Krishnan, Karthikeyan | O16: Cost Accounting Work Area
A17: 16 | B17: Manufacturing | C17: Manufacturing | D17: Search for, Create, and Edit a Standard Item Work Definition Using the Redwood User Experience | E17: 24B | F17: 26B | G17: Wave1 - Simple Pages | H17: 26A | J17: ORA_WIS_WORK_DEFINITIONS_REDWOOD_ENABLED | L17: Role Setup+Profile option | M17: Y | N17: Muthu Kumar Madhavan | O17: Manage Work Definitions Page
A18: 17 | B18: Order Management | C18: Channel Revenue Management | D18: Redwood: Define Product Eligibility Based on Item Categories for Customer Rebate Programs | E18: 24D | F18: 25A | G18: Wave3 - Complex Pages | H18: 26C | I18: Manage Customer Programs (CJM_MANAGE_CUSTOMER_PROGRAMS_PRIV) | K18: Use the Opt In UI to enable this feature. | L18: OPT IN+Role Setup | N18: Arepally, Susmitha | O18: Customer Programs UI (Customer rebate programs)
A19: 18 | B19: Order Management | C19: Channel Revenue Management | D19: Redwood: Exclude Multiple Items or Item Categories in Product Eligibility Rules | E19: 24D | F19: 25C | G19: Wave3 - Complex Pages | H19: 26C | I19: Manage Customer Programs (CJM_MANAGE_CUSTOMER_PROGRAMS_PRIV) | K19: Use the Opt In UI to enable this feature. | L19: OPT IN+Role Setup | N19: Arepally, Susmitha | O19: Customer Programs UI (Customer rebate programs and Customer volume programs).
A20: 19 | B20: Order Management | C20: Channel Revenue Management | D20: Redwood: Manage Manual Accrual Adjustments for Customer Rebate Programs | E20: 24D | F20: 26B | G20: Wave3 - Complex Pages | H20: 26C | I20: Manage Customer Manual Adjustments (CJM_MANAGE_CUSTOMER_MANUAL_ADJUSTMENTS_PRIV), View Customer Manual Adjustments (CJM_VIEW_CUSTOMER_MANUAL_ADJUSTMENTS_PRIV) | K20: Use the Opt In UI to enable this feature. | L20: OPT IN+Role Setup | N20: Arepally, Susmitha | O20: Customer Programs /Adjustments
A21: 20 | B21: Order Management | C21: Pricing | D21: Redwood: Apply Pricing Promotions According to Pricing Strategies and Payment Terms | E21: 24D | F21: 26B | G21: Wave3 - Complex Pages | H21: 26C | I21: Manage Draft Pricing Promotions (QP_MANAGE_DRAFT_PRICING_PROMOTIONS) Manage Pricing Promotions (QP_MANAGE_PRICING_PROMOTIONS) View Pricing Promotions (QP_VIEW_PRICING_PROMOTIONS) Activate Pricing Promotions (QP_ APPROVE_PRICING_PROMOTIONS) Manage Dynamic Rules (QP_MANAGE_DYNAMIC_RULES) | K21: This is a new feature not available on classic UI | L21: OPT IN | M21: Y | N21: Arepally, Susmitha | O21: Pricing Promotion Work Area
A22: 21 | B22: Order Management | C22: Pricing | D22: Redwood: Copy and Delete Pricing Promotions | E22: 24D | F22: 26B | G22: Wave3 - Complex Pages | H22: 26C | I22: Manage Promotions (QP_MANAGE_PROMOTIONS) | K22: This is a new feature not available on classic UI | L22: OPT IN | M22: Y | N22: Arepally, Susmitha | O22: Pricing Promotion Work Area
A23: 22 | B23: Order Management | C23: Pricing | D23: Redwood: Define Tiered Adjustments on Rate Plan Charges | E23: 24D | F23: 26B | G23: Wave3 - Complex Pages | H23: 26C | I23: Manage Price Lists (QP_MANAGE_PRICE_LISTS) Manage In-Progress Price Lists (QP_MANAGE_IN_PROGRESS_PRICE_LISTS) View Price Lists (QP_VIEW_PRICE_LISTS) Approve Price Lists QP_APPROVE_PRICE_LISTS | K23: This is a new feature not available on classic UI | L23: OPT IN+Role Setup | M23: Y | N23: Arepally, Susmitha | O23: Price List Work Area , New Recurring Charge ,Tier Adjustments
A24: 23 | B24: Order Management | C24: Pricing | D24: Create Pricing Promotions for Sales Orders Using Redwood Pages | E24: 24C | F24: 26A | G24: Wave3 - Complex Pages | H24: 26C | I24: Manage Draft Pricing Promotions (QP_MANAGE_DRAFT_PRICING_PROMOTIONS) Manage Pricing Promotions (QP_MANAGE_PRICING_PROMOTIONS) View Pricing Promotions (QP_VIEW_PRICING_PROMOTIONS) Activate Pricing Promotions (QP_ APPROVE_PRICING_PROMOTIONS) Manage Dynamic Rules (QP_MANAGE_DYNAMIC_RULES) | K24: This is a new feature not available on classic UI | L24: OPT IN+Role Setup | M24: Y | N24: Arepally, Susmitha | O24: Pricing Promotion Work Area
A25: 24 | B25: Order Management | C25: Channel Revenue Management | D25: Add Notes for Customer Programs and Claims in Redwood Pages | E25: 23C | F25: 25B | G25: Wave3 - Complex Pages | H25: 26C | I25: Manage Customer Programs (CJM_MANAGE_CUSTOMER_PROGRAMS_PRIV) Manage Customer Claims (CJM_MANAGE_CUSTOMER_CLAIMS_PRIV) View Only Activity (ZMM_VIEW_ONLY_ACTIVITY_PRIV) | K25: Use the Opt In UI to enable this feature. | L25: OPT IN+Role Setup | N25: Arepally, Susmitha | O25: Customer Program / Claim
A26: 25 | B26: Order Management | C26: Channel Revenue Management | D26: Improve Usability of Claim Pages in Redwood | E26: 23C | F26: 25B | G26: Wave3 - Complex Pages | H26: 26C | I26: Manage Customer Claims (CJM_MANAGE_CUSTOMER_CLAIMS_PRIV) Create Customer Claims (CJM_CREATE_CUSTOMER_CLAIMS_PRIV) View Customer Claims (CJM_VIEW_CUSTOMER_CLAIMS_PRIV) | K26: Use the Opt In UI to enable this feature. | L26: OPT IN+Role Setup | N26: Arepally, Susmitha | O26: Customer Claims Work Area
A27: 26 | B27: Order Management | C27: Channel Revenue Management | D27: Update and Settle Multiple Claims Using Redwood Pages | E27: 23C | F27: 25B | G27: Wave3 - Complex Pages | H27: 26C | I27: Manage Customer Claims (CJM_MANAGE_CUSTOMER_CLAIMS_PRIV) View Only Activity (ZMM_VIEW_ONLY_ACTIVITY_PRIV) | K27: Use the Opt In UI to enable this feature. | L27: OPT IN+Role Setup | N27: Arepally, Susmitha | O27: Customer Claims Work Area
A28: 27 | B28: Order Management | C28: Channel Revenue Management | D28: Manage Deduction Claims Using Redwood Pages | E28: 23B | F28: 26A | G28: Wave3 - Complex Pages | H28: 25C | I28: No additional roles needed to access redwood pages if you already have access to Deductions and Settlement in 23B. Add reference data set access to existing Channel Claim Manager users, in addition to their existing business unit data access. | K28: Use the Opt In UI to enable this feature. | L28: OPT IN+Role Setup | N28: Arepally, Susmitha | O28: Customer Claims Work Area
A29: 28 | B29: Procurement | C29: Sourcing | D29: Redwood: Respond to Simple Negotiations in Supplier Portal | E29: 24D | F29: 26A | G29: Wave1 - Simple Pages | H29: 26B | I29: Create Supplier Negotiation Response (PON_CREATE_SUPPLIER_NEGOTIATION_RESPONSE_PRIV) Edit Supplier Negotiation Response (PON_EDIT_SUPPLIER_NEGOTIATION_RESPONSE_PRIV) | L29: Log Service Request | M29: Y | N29: DESHPANDE, NILESH | O29: Supplier Portal Negotiations Work Area
A30: 29 | B30: Procurement | C30: Sourcing | D30: Redwood: Use Enhanced Negotiation Search in Supplier Portal | E30: 24D | F30: 26A | G30: Wave1 - Simple Pages | H30: 26B | I30: View Supplier Negotiation as Supplier (PON_VIEW_SUPPLIER_NEGOTIATION_SUPPLIER_FACING_PRIV) | L30: OPT IN | M30: Y | N30: DESHPANDE, NILESH | O30: Supplier Portal Negotiations Work Area
A31: 30 | B31: Procurement | C31: Sourcing | D31: Redwood: Use New Buyer Experience for Negotiation Messages | E31: 24D | F31: 25C | G31: Wave1 - Simple Pages | H31: 26B | I31: View Supplier Negotiation Online Message (PON_VIEW_ONLINE_MESSAGE_PRIV) Create Supplier Negotiation Online Message (PON_CREATE_ONLINE_MESSAGE_PRIV) Reply Supplier Negotiation Online Message (PON_REPLY_ONLINE_MESSAGE_PRIV) | L31: OPT IN+ Profile Option | M31: Y | N31: DESHPANDE, NILESH | O31: Negotiation Messages
A32: 31 | B32: Procurement | C32: Sourcing | D32: Redwood: Use New Supplier Experience for Negotiation Messages | E32: 24D | F32: 26A | G32: Wave1 - Simple Pages | H32: 26B | I32: View Supplier Negotiation Online Message as Supplier (PON_VIEW_ONLINE_MESSAGE_SUPPLIER_FACING_PRIV) Create Supplier Negotiation Online Message as Supplier (PON_CREATE_ONLINE_MESSAGE_SUPPLIER_FACING_PRIV) Reply Supplier Negotiation Online Message as Supplier (PON_REPLY_ONLINE_MESSAGE_SUPPLIER_FACING_PRIV) | L32: OPT IN | M32: Y | N32: DESHPANDE, NILESH | O32: Negotiation Messages
A33: 32 | B33: Procurement | C33: Supplier Model | D33: Redwood: Next Generation User Experience for Supplier Registration | E33: 24D | F33: 25C | G33: Wave1 - Simple Pages | H33: 25C | L33: OPT IN | M33: Y | N33: DESHPANDE, NILESH | O33: Supplier Registration UI
A34: 33 | B34: Procurement | C34: Supplier Qualification Management | D34: Redwood: Use Questionnaires in Internal Supplier Registration | E34: 24D | F34: 25C | G34: Wave2 - Modarate Pages | I34: POZ_SUBMIT_SUPPLIER_REGISTRATION_PRIV | K34: Opt in : Redwood: Next Generation User Experience for Supplier Registration | L34: OPT IN+Role Setup | M34: Y | N34: DESHPANDE, NILESH | O34: Supplier Registration UI
A35: 34 | B35: Procurement | C35: Common Procurement | D35: Extend Procurement Redwood Application Pages Using Visual Builder Studio | E35: 24C | F35: 25C | G35: Wave3 - Complex Pages | H35: 25C | L35: Visual Builder | N35: DESHPANDE, NILESH | O35: Visual Builder
A36: 35 | B36: Product Hub | C36: Product Development | D36: Redwood: Secure Manufacturers Using Access Control Lists | E36: 24D | F36: 26A | G36: Wave3 - Complex Pages | H36: 26C | I36: To configure manufacturer conditions using a filtered list: Use REST Service - Identity Integration (ASE_REST_SERVICE_ACCESS_IDENTITY_INTEGRATION_PRIV) Use Atom Feed - Employees Workspace (PER_ATOM_WORKSPACE_ACCESS_EMPLOYEES_PRIV) Manage HCM Lists (HRC_MANAGE_HCM_LISTS_PRIV) Human Capital Management Application Administrator (ORA_HRC_HUMAN_CAPITAL_MANAGEMENT_APPLICATION_ADMINISTRATOR_JOB) To configure teams, permission sets, and conditions: Monitor Product Development (ACA_MONITOR_PRODUCT_DEVELOPMENT_PRIV) Configure Access Control Teams, Permission Sets, and Conditions (EGP_ACCESS_CONTROL_TEAMS_PRIV) Use REST Service - Identity Integration (ASE_REST_SERVICE_ACCESS_IDENTITY_INTEGRATION_PRIV) Use Atom Feed - Employees Workspace (PER_ATOM_WORKSPACE_ACCESS_EMPLOYEES_PRIV) Manage HCM Lists (HRC_MANAGE_HCM_LISTS_PRIV) Manage HCM Rules (HRC_MANAGE_HCM_RULES_PRIV) Run Scheduled Processes (HEY_RUN_SCHEDULED_PROCESSES_PRIV) Manage Scheduled Processes(FND_MANAGE_SCHEDULED_PROCESSES_PRIV) To access the secured manufacturer data: Create Manufacturer (EGP_CREATE_MANUFACTURER_PRIV) View Manufacturers (EGP_VIEW_MANUFACTURER_PRIV) Manage Manufacturers (EGP_MANAGE_MANUFACTURER_PRIV) To access journeys setup and configure the roles in role hierarchy: Manage Journey (ORA_PER_MANAGE_JOURNEY_TEMPLATE) Manage Guided Journeys (ORA_PER_MANAGE_GUIDED_JOURNEYS) Use REST Service - Guided Journeys Read Only (ORA_PER_REST_SERVICE_ACCESS_GUIDED_JOURNEYS_RO) Use REST Service - Journey Categories List of Values (ORA_PER_REST_SERVICE_ACCESS_JOURNEY_CATEGORIES_LOV) To access business rules: Administer Sandbox (FND_ADMINISTER_SANDBOX_PRIV) | K36: Mandate version is not specified hence considering the mandate version as per Roadmap for PLM module which is 26B. | L36: OPT IN | M36: Y | N36: Sujay Parab | O36: Product Management Work Area
A37: 36 | B37: Product Hub | C37: Product Lifecycle Management | D37: Redwood: Create and Manage Personalized Views in Product Management Search | E37: 24D | F37: 26A | G37: Wave1 - Simple Pages | H37: 26C | I37: View Product Management Search (EGP_VIEW_PRODUCT_MGT_SEARCH_PRIV) Get Search View REST (EGP_GET_SEARCH_VIEW_REST_PRIV) GET Product Management Index REST (EGP_GET_PM_INDEX_REST_PRIV) Manage Search View REST (EGP_MANAGE_SEARCH_VIEW_REST_PRIV) | K37: Mandate version is not specified hence considering the mandate version as per Roadmap for PLM module which is 26B. | L37: Role Setup+Profile option | M37: Y | N37: Sujay Parab | O37: Product Information Management Work Area-->Search Products
A38: 37 | B38: Product Hub | C38: Product Lifecycle Management | D38: Redwood: Search Workflow Approvals | E38: 24D | F38: 25C | G38: Wave1 - Simple Pages | H38: 26C | I38: Users with view only access to changes require the following privileges: Access Product Management Change Search (EGO_VIEW_PRODUCT_MANAGEMENT_CHANGE_SEARCH) Get Search View REST (EGP_GET_SEARCH_VIEW_REST_PRIV) GET Product Management Index REST (EGP_GET_PM_INDEX_REST_PRIV) You should have Monitor Product Management Workflow Objects (ACA_MONITOR_PRODUCT_MANAGEMENT_WORFLOW_OBJECTS_PRIV) and one of the following privileges: For change orders: View Change Order (ACA_VIEW_CHANGE_ORDERS_PRIV) or Manage Change Orders (ACA_MANAGE_CHANGE_ORDERS_PRIV) For change requests: View Change Request (ACA_VIEW_CHANGE_REQUESTS_PRIV) Manage Change Requests (ACA_MANAGE_CHANGE_REQUESTS_PRIV) For problem reports: View Problem Report (ACA_VIEW_PROBLEM_REPORTS_PRIV) Manage Problem Report (ACA_MANAGE_PROBLEM_REPORT_PRIV) For corrective and preventive actions: View Corrective Action (ACA_VIEW_CORRECTIVE_ACTIONS_PRIV) Manage Corrective Action (ACA_MANAGE_CORRECTIVE_ACTION_PRIV) To configure the index: Manage Product Management Index (EGP_MANAGE_PM_INDEXES_PRIV) Manage Scheduled Job Definition (FND_MANAGE_SCHEDULED_JOB_DEFINITION_PRIV) Grant Search Framework Manager Permissions (FND_SEARCH_FWK_MGR_PRIV) To rebuild the index: Rebuild Product Management Indexes (EGO_REBUILD_PRODUCT_MGT_INDEXES_PRIV) To create search views: Manage Product Management View (EGP_MANAGE_PM_VIEWS_PRIV) Manage Scheduled Job Definition (FND_MANAGE_SCHEDULED_JOB_DEFINITION_PRIV) Grant Search Framework Manager Permissions (FND_SEARCH_FWK_MGR_PRIV) Access Product Development Configurations Using a REST Service (ACA_GET_PD_CONFIGURATIONS_REST_PRIV) Manage Search View REST (EGP_MANAGE_SEARCH_VIEW_REST_PRIV) Get View Available Attribute REST (EGP_VIEW_AVAIL_ATTR_REST_PRIV) | K38: Mandate version is not specified hence considering the mandate version as per Roadmap for PLM module which is 26B. | L38: Role Setup+Profile option | M38: Y | N38: Sujay Parab | O38: Product Information Management Work Area-->Search Products
A39: 38 | B39: Product Hub | C39: Product Lifecycle Management | D39: Redwood: Search Workflow History | E39: 24D | F39: 25C | G39: Wave1 - Simple Pages | H39: 26C | I39: Users with view only access to changes require the following privileges: Access Product Management Change Search (EGO_VIEW_PRODUCT_MANAGEMENT_CHANGE_SEARCH) View Change History (EGO_VIEW_CHANGE_HISTORY_PRIV) Get Search View REST (EGP_GET_SEARCH_VIEW_REST_PRIV) GET Product Management Index REST (EGP_GET_PM_INDEX_REST_PRIV) You should have Monitor Product Management Workflow Objects (ACA_MONITOR_PRODUCT_MANAGEMENT_WORFLOW_OBJECTS_PRIV) and one of the following privileges: For change orders: View Change Order (ACA_VIEW_CHANGE_ORDERS_PRIV) or Manage Change Orders (ACA_MANAGE_CHANGE_ORDERS_PRIV) For change requests: View Change Request (ACA_VIEW_CHANGE_REQUESTS_PRIV) Manage Change Requests (ACA_MANAGE_CHANGE_REQUESTS_PRIV) For problem reports: View Problem Report (ACA_VIEW_PROBLEM_REPORTS_PRIV) Manage Problem Report (ACA_MANAGE_PROBLEM_REPORT_PRIV) For corrective and preventive actions: View Corrective Action (ACA_VIEW_CORRECTIVE_ACTIONS_PRIV) Manage Corrective Action (ACA_MANAGE_CORRECTIVE_ACTION_PRIV) To configure the index: Manage Product Management Index (EGP_MANAGE_PM_INDEXES_PRIV) Manage Scheduled Job Definition (FND_MANAGE_SCHEDULED_JOB_DEFINITION_PRIV) Grant Search Framework Manager Permissions (FND_SEARCH_FWK_MGR_PRIV) To rebuild the index: Rebuild Product Management Indexes (EGO_REBUILD_PRODUCT_MGT_INDEXES_PRIV) To create search views: Manage Product Management View (EGP_MANAGE_PM_VIEWS_PRIV) Manage Scheduled Job Definition (FND_MANAGE_SCHEDULED_JOB_DEFINITION_PRIV) Grant Search Framework Manager Permissions (FND_SEARCH_FWK_MGR_PRIV) Access Product Development Configurations Using a REST Service (ACA_GET_PD_CONFIGURATIONS_REST_PRIV) Manage Search View REST (EGP_MANAGE_SEARCH_VIEW_REST_PRIV) Get View Available Attribute REST (EGP_VIEW_AVAIL_ATTR_REST_PRIV) | K39: Mandate version is not specified hence considering the mandate version as per Roadmap for PLM module which is 26B. | L39: Role Setup+Profile option | M39: Y | N39: Sujay Parab | O39: Product Information Management Work Area-->Search Products
A40: 39 | B40: Product Hub | C40: Product Development | D40: Create, Edit, and Extend Manufacturers Using a Redwood Page | E40: 24B | F40: 25B | G40: Wave2 - Modarate Pages | H40: 26C | I40: To search for manufacturers using a Redwood page: Get Search View REST(EGP_GET_SEARCH_VIEW_REST_PRIV) To view only manufacturers: View Manufacturer (EGP_VIEW_MANUFACTURER_PRIV) To edit manufacturers: Manage Manufacturer (EGP_MANAGE_MANUFACTURER_PRIV) To create manufacturers: Create Manufacturer (EGP_CREATE_MANUFACTURER_PRIV) Manage Manufacturer (EGP_MANAGE_MANUFACTURER_PRIV) | J40: EGP_MANUFACTURER_REDWOOD_ENABLED | K40: Mandate version is not specified hence considering the mandate version as per Roadmap for PLM module which is 26B. | L40: Role Setup+Profile option | M40: Y | N40: Sujay Parab | O40: Product Development Work Area-->Manufacturers
A41: 40 | B41: Product Hub | C41: Product Development & Product Hub Common | D41: Access Side Panel View of Item Data from Search Results Using a Redwood Page | E41: 24B | F41: 25D | G41: Wave1 - Simple Pages | H41: 26C | I41: To view the item search: View Product Management Search (EGP_VIEW_PRODUCT_MGT_SEARCH) View Item (EGP_VIEW_ITEM) Get Search View REST (EGP_GET_SEARCH_VIEW_REST_PRIV) Data Security: View Item Basic To view the item AML in Redwood: Manage Trading Partner Item (EGP_MANAGE_TRADING_PARTNER_ITEM_PRIV) View Trading Partner Item (EGP_VIEW_TRANDING_PARTNER_ITEM_PRIV) View Manufacturers (EGP_VIEW_MANUFACTURER_PRIV) Get Trading Partner Item Relationship Rest (EGI_GET_TPI_REL_REST_PRIV) To view the item pending changes in Redwood: Manage Change Orders (ACA_MANAGE_CHANGE_ORDERS_PRIV) Manage Change Requests (ACA_MANAGE_CHANGE_REQUESTS_PRIV) View Change Order (ACA_VIEW_CHANGE_ORDERS_PRIV) View Change Request (ACA_VIEW_CHANGE_REQUESTS_PRIV) Data Security: View Item Change Order (EGO_ENGINEERING_CHANGES_B) To view the quality issues, quality actions, problem reports and corrective actions: Manage Problem Report (ACA_MANAGE_PROBLEM_REPORT_PRIV) View Problem Report (ACA_VIEW_PROBLEM_REPORTS_PRIV) Manage Corrective Action (ACA_MANAGE_CORRECTIVE_ACTION_PRIV) View Corrective Action (ACA_VIEW_CORRECTIVE_ACTIONS_PRIV) Manage Quality Issue (ENQ_MANAGE_QUALITY_ISSUE_PRIV) View Quality Issue (ENQ_VIEW_QUALITY_ISSUE_PRIV) Manage Quality Action (ENQ_MANAGE_QUALITY_ACTION_PRIV) View Quality Action (ENQ_VIEW_QUALITY_ACTION_PRIV) | K41: Mandate version is not specified hence considering the mandate version as per Roadmap for PLM module which is 26B. | L41: Role Setup+Profile option | M41: Y | N41: Sujay Parab | O41: Product Management Work Area-->Search Items
A42: 41 | B42: Product Hub | C42: Product Development & Product Hub Common | D42: Access Side Panel View of Structure Component Data Using a Redwood Page | E42: 24B | F42: 25D | G42: Wave2 - Modarate Pages | H42: 26C | I42: To view the item structure in Redwood: View Product Management Search (EGP_VIEW_PRODUCT_MGT_SEARCH) View Item (EGP_VIEW_ITEM) Create Item Structure (EGP_CREATE_ITEM_STRUCTURE_PRIV) Get Search View REST (EGP_GET_SEARCH_VIEW_REST_PRIV) Data Security: View Item Basic To configure the index: Manage Product Management Index (EGP_MANAGE_PM_INDEXES) Manage Scheduled Job Definition (FND_MANAGE_SCHEDULED_JOB_DEFINITION_PRIV) Grant Search Framework Manager Permissions (FND_SEARCH_FWK_MGR_PRIV) Get Item Index Available Attributes REST (EGP_GET_PM_ITEM_AVAIL_REST_PRIV) To rebuild the index: Rebuild Product Management Indexes (EGO_REBUILD_PRODUCT_MGT_INDEXES) To create the structure view: Manage Product Management View (EGP_MANAGE_PM_VIEWS) Manage Scheduled Job Definition (FND_MANAGE_SCHEDULED_JOB_DEFINITION_PRIV) Grant Search Framework Manager Permissions (FND_SEARCH_FWK_MGR_PRIV) Access Product Development Configurations Using a REST Service (ACA_GET_PD_CONFIGURATIONS_REST_PRIV) Manage Search View REST (EGP_MANAGE_SEARCH_VIEW_REST_PRIV) Get View Available Attribute REST (EGP_VIEW_AVAIL_ATTR_REST_PRIV) To view the quality issues, quality actions, problem report, and corrective action in the side panel: Manage Problem Report (ACA_MANAGE_PROBLEM_REPORT_PRIV) Manage Corrective Action (ACA_MANAGE_CORRECTIVE_ACTION_PRIV) Manage Quality Issue (ENQ_MANAGE_QUALITY_ISSUE_PRIV) Manage Quality Action (ENQ_MANAGE_QUALITY_ACTION_PRIV) | K42: Mandate version is not specified hence considering the mandate version as per Roadmap for PLM module which is 26B. | L42: Role Setup+Profile option | M42: Y | N42: Sujay Parab | O42: Product Management Search page
A43: 42 | B43: Quality Management | C43: Quality Inspection Management | D43: Manage Inspection Levels using the Redwood Experience | E43: 24C | F43: 26A | G43: Wave1 - Simple Pages | H43: 26C | I43: View Product Management Search (EGP_VIEW_PRODUCT_MGT_SEARCH_PRIV) Get Search View Rest (EGP_GET_SEARCH_VIEW_REST_PRIV) GET Product Management Index REST (EGP_GET_PM_INDEX_REST_PRIV) | J43: ORA_QA_INSPECTION_LEVEL_REDWOOD_ENABLED | L43: Role Setup+Profile option | M43: Y | N43: Muthu Kumar Madhavan | O43: Quality Management, Inspectoin Levels Page
A44: 43 | B44: Quality Management | C44: Quality Inspection Management | D44: Manage Inspection Plans using the Redwood Experience | E44: 24C | F44: 26A | G44: Wave1 - Simple Pages | H44: 26C | I44: Manage Item Source System (EGI_MANAGE_ITEM_SOURCE_SYSTEM_PRIV) | J44: ORA_QA_INSPECTION_PLAN_REDWOOD_ENABLED | L44: Role Setup+Profile option | M44: Y | N44: Muthu Kumar Madhavan | O44: Quality Management, Inspection Plans Page
A45: 44 | B45: Quality Management | C45: Quality Inspection Management | D45: Perform Quality Inspections using the Redwood Experience | E45: 24C | F45: 25B | G45: Wave1 - Simple Pages | H45: 26C | I45: Manage Item Delete Group (EGP_MANAGE_ITEM_DELETE_GROUP_PRIV) Access Item Structure Data Using a REST Service (EGP_GET_ITEM_STRUCTURE_REST_PRIV) Access Change Order Using a REST Service (ACA_GET_CHANGE_REST_PRIV) Manage Delete Group Rest (EGP_DG_REST_PRIV) GET Product Management Index REST (EGP_GET_PM_INDEX_REST_PRIV) Get Search View REST (EGP_GET_SEARCH_VIEW_REST_PRIV) Grant Search Framework Manager Permissions (FND_SEARCH_FWK_MGR_PRIV) View Product Management Search (EGP_VIEW_PRODUCT_MGT_SEARCH_PRIV) | J45: ORA_QA_INSPECTIONS_REDWOOD_ENABLED | L45: Role Setup+Profile option | M45: Y | N45: Muthu Kumar Madhavan | O45: Quality Management, New Inspection
A46: 45 | B46: Quality Management | C46: Quality Inspection Management | D46: Manage Inspection Characteristics in Redwood Pages | E46: 24B | F46: 26B | G46: Wave1 - Simple Pages | H46: 26C | I46: To search for manufacturers using a Redwood page: Get Search View REST(EGP_GET_SEARCH_VIEW_REST_PRIV) To view only manufacturers: View Manufacturer (EGP_VIEW_MANUFACTURER_PRIV) To edit manufacturers: Manage Manufacturer (EGP_MANAGE_MANUFACTURER_PRIV) To create manufacturers: Create Manufacturer (EGP_CREATE_MANUFACTURER_PRIV) Manage Manufacturer (EGP_MANAGE_MANUFACTURER_PRIV) | J46: ORA_QA_CHARACTERISTIC_REDWOOD_ENABLED | L46: Role Setup+Profile option | M46: Y | N46: Muthu Kumar Madhavan | O46: Quality Management, Create Inspection Characteristecs
A47: 46 | B47: SCM Common Components | C47: SCM Common Components | D47: Create Guided Journeys for Redwood Pages | E47: 24C | F47: 26A | G47: Wave1 - Simple Pages | H47: 26B | I47: Manage Publication Maps (EGI_MANAGE_PUBLICATION_MAPS_PRIV) Manage Publishable Attributes REST (EGI_MANAGE_PUBLISHABLE_ATTR_REST_PRIV) Manage Publication Maps REST (EGI_MANAGE_PUBLICATION_MAPS_REST_PRIV) | L47: Visual Builder | N47: Pravalika G | O47: Guided Journeys UI
A48: 47 | B48: Inventory Management | C48: Cost Management | D48: Redwood: Create and Update Standard Costs Using a New User Experience | E48: 25A | F48: 25B | G48: Wave2 - Modarate Pages | H48: 26A | I48: To search for manufacturers using a Redwood page: Get Search View REST(EGP_GET_SEARCH_VIEW_REST_PRIV) To view manufacturers: View Manufacturer (EGP_VIEW_MANUFACTURER_PRIV) To edit manufacturers: Manage Manufacturer (EGP_MANAGE_MANUFACTURER_PRIV) To create manufacturers: Create Manufacturer (EGP_CREATE_MANUFACTURER_PRIV) Manage Manufacturer (EGP_MANAGE_MANUFACTURER_PRIV) | J48: On the Manage Administrator Profile Values page, search for and select the ORA_CST_STANDARD_COSTS_REDWOOD_ENABLED profile option code. In the Profile Values section, set the Site level to Yes. The default value is No. Click Save and Close. Changes in the profile value will affect users the next time they sign in. Yes = enables the feature No = disables the feature | L48: Role Setup+Profile option | M48: Y | N48: Krishnan, Karthikeyan | O48: Cost Accounting Work Area
A49: 48 | B49: Inventory Management | C49: Cost Management | D49: Redwood: Compare Standard Costs Using a New User Experience | E49: 25A | F49: 25B | G49: Wave2 - Modarate Pages | H49: 26A | I49: Access Clipboard (ACA_ACCESS_CLIPBOARD_PRIV) | J49: On the Manage Administrator Profile Values page, search for and select the ORA_CST_COMPARE_STD_COSTS_REDWOOD_ENABLED profile option code. In the Profile Values section, set the Site level to Yes. The default value is No. Click Save and Close. Changes in the profile value will affect users the next time they sign in. Yes = enables the feature No = disables the feature | L49: Role Setup+Profile option | M49: Y | N49: Krishnan, Karthikeyan | O49: Cost Accounting Work Area
A50: 49 | B50: Supply Chain Collaboration | C50: Supply Chain Collaboration | D50: Manage Supplier On-Hand Quantities Using a Redwood Page | E50: 24C | F50: 26A | G50: Wave1 - Simple Pages | H50: 26C | I50: To view the item structure on the Redwood page: View Product Management Search (EGP_VIEW_PRODUCT_MGT_SEARCH) View Item (EGP_VIEW_ITEM) Create Item Structure (EGP_CREATE_ITEM_STRUCTURE_PRIV) Get Search View REST (EGP_GET_SEARCH_VIEW_REST_PRIV) Data Security: View Item Basic Access Item Structure Data Using a REST Service (EGP_GET_ITEM_STRUCTURE_REST_PRIV) Access Structure Attributes for Indexing Using REST (EGP_GET_PM_STRUCTURE_AVAIL_REST_PRIV) | L50: OPT IN+Role Setup | M50: Y | N50: Veeranarayana Swamy | O50: Supplier On-Hand Quantities
A51: 50 | B51: Supply Chain Collaboration | C51: Supply Chain Collaboration | D51: Manage Supply Collaboration Network Using a Redwood Page | E51: 24C | F51: 25D | G51: Wave1 - Simple Pages | H51: 26C | I51: You should have Monitor Product Management Workflow Objects (ACA_MONITOR_PRODUCT_MANAGEMENT_WORFLOW_OBJECTS_PRIV) and one of the following privileges: For change orders: View Change Order (ACA_VIEW_CHANGE_ORDERS_PRIV) or Manage Change Orders (ACA_MANAGE_CHANGE_ORDERS_PRIV) For change requests: View Change Request (ACA_VIEW_CHANGE_REQUESTS_PRIV) or Manage Change Requests (ACA_MANAGE_CHANGE_REQUESTS_PRIV) For problem reports: View Problem Report (ACA_VIEW_PROBLEM_REPORTS_PRIV) or Manage Problem Report (ACA_MANAGE_PROBLEM_REPORT_PRIV) For corrective and preventive actions: View Corrective Action (ACA_VIEW_CORRECTIVE_ACTIONS_PRIV) or Manage Corrective Action (ACA_MANAGE_CORRECTIVE_ACTION_PRIV) | L51: OPT IN+Role Setup | N51: Venkat | O51: Supply Collaboration Network
A52: 51 | B52: Supply Chain Collaboration | C52: Supply Chain Collaboration | D52: Manage Upload Supply Data Using a Redwood Page | E52: 24C | F52: 26A | G52: Wave1 - Simple Pages | H52: 26C | I52: You should have Monitor Product Management Workflow Objects (ACA_MONITOR_PRODUCT_MANAGEMENT_WORFLOW_OBJECTS_PRIV) and one of the following privileges: For change orders: View Change Order (ACA_VIEW_CHANGE_ORDERS_PRIV) or Manage Change Orders (ACA_MANAGE_CHANGE_ORDERS_PRIV) For change requests: View Change Request (ACA_VIEW_CHANGE_REQUESTS_PRIV) or Manage Change Requests (ACA_MANAGE_CHANGE_REQUESTS_PRIV) For problem reports: View Problem Report (ACA_VIEW_PROBLEM_REPORTS_PRIV) or Manage Problem Report (ACA_MANAGE_PROBLEM_REPORT_PRIV) For corrective and preventive actions: View Corrective Action (ACA_VIEW_CORRECTIVE_ACTIONS_PRIV) or Manage Corrective Action (ACA_MANAGE_CORRECTIVE_ACTION_PRIV) Users who are assigned a configured job role that contains these privileges can access assigned notifications: For Item Change Orders: EGO_VIEW_ITEM_CHANGE_ORDER_PRIV For New Item Request: EGO_VIEW_NEW_ITEM_REQUEST_PRIV | L52: OPT IN+Role Setup | N52: Venkat | O52: Upload Supply Data
A53: 52 | B53: Supply Chain Collaboration | C53: Supply Chain Collaboration | D53: Manage Collaboration Planners Using a Redwood Page | E53: 24B | F53: 25B | G53: Wave1 - Simple Pages | H53: 26C | I53: Landing Page (ORA_EGP_LANDING_PAGE_DUTY) contains: View Item Redwood (ORA_EGP_REDWOOD_VIEW_ITEM_DUTY) Product Search (ORA_EGI_PRODUCT_SEARCH_DUTY) Access Object Tag Set Repository (ACA_ACCESS_OBJECT_TAG_SETS_PRIV) Access Object Tags Repository (ACA_ACCESS_OBJECT_TAGS_PRIV) Access Product Management Landing Page (EGP_ACCESS_LANDING_PAGE_PRIV) Manage Landing Page Layout (EGP_MANAGE_LANDING_PAGE_LAYOUT_PRIV) Access Clipboard (ACA_ACCESS_CLIPBOARD_PRIV) Access HCM Common Components (HRC_ACCESS_HCM_COMMON_COMPONENTS_PRIV) Manage Search Consumer Applications Rest (EGP_MANAGE_SEARCH_CONS_REST_PRIV) | L53: OPT IN+Role Setup | N53: Venkat | O53: Collaboration Planners
A54: 53 | B54: Supply Chain Collaboration | C54: Supply Chain Collaboration | D54: Manage Collaboration Plans Using a Redwood Page | E54: 24B | F54: 25B | G54: Wave1 - Simple Pages | H54: 26C | L54: OPT IN+Role Setup | N54: Venkat | O54: Collaboration Plans
A55: 54 | B55: Supply Chain Collaboration | C55: Supply Chain Collaboration | D55: Manage VMI Analysts Using a Redwood Page | E55: 24B | F55: 25B | G55: Wave1 - Simple Pages | H55: 26C | I55: View Item Redwood Items (EGP_VIEW_REDWOOD_ITEM_PRIV) View Item Redwood Attachments (EGP_VIEW_REDWOOD_ITEM_ATTACHMENT_PRIV) View Item Redwood Associations (EGP_VIEW_REDWOOD_ITEM_ASSOCIATION_PRIV) View Item Redwood Structures (EGP_VIEW_REDWOOD_ITEM_STRUCTURE_PRIV) View Item Redwood Changes (EGP_VIEW_REDWOOD_ITEM_CHANGE_PRIV) View Item Redwood Item Categories (EGP_VIEW_REDWOOD_ITEM_CATEGORIES_PRIV) View Item Redwood Relationships (EGP_VIEW_REDWOOD_ITEM_RELATIONSHIP_PRIV) View Item Redwood Quality (EGP_VIEW_REDWOOD_ITEM_QUALITY_PRIV) Supply Chain Common View Web Service (ORA_RCS_SCM_COMMON_VIEW_WEB_SERVICE_DUTY) Enter Trading Community Organization Information (HZ_ENTER_TRADING_COMMUNITY_ORGANIZATION_INFORMATION_PRIV) Get Failure Condition Event Codes (MNT_GET_FAILURE_CONDITION_EVENT_CODE_BY_SERVICE_PRIV) Get Item Attribute Control REST (EGP_ITEM_ATTRIBUTE_CONTROL_READ_PRIV) Get Item Lifecycle Phases Read Rest (EGP_ITEM_LIFECYCLE_PHASES_READ_REST_PRIV) Get Item Status REST (EGP_ITEM_STATUSES_READ_PRIV) Get New Item Request Rest (EGI_NEW_ITEM_REQUEST_REST_PRIV) Get Template REST (EGP_TEMPLATE_READ_PRIV) Manage Material Planner (MSP_MANAGE_MATERIAL_PLANNER_PRIV) Manage Subscription Setup (OSS_MANAGE_SUBSCRIPTION_SETUP_PRIV) Remove Trading Community Organization (HZ_REMOVE_TRADING_COMMUNITY_ORGANIZATION_PRIV) Set Up Receivables Payment Terms (AR_SET_UP_RECEIVABLES_PAYMENT_TERM_PRIV) Update Trading Community Organization (HZ_UPDATE_TRADING_COMMUNITY_ORGANIZATION_PRIV) Verify Tax Configuration (ZX_VERIFY_TAX_CONFIGURATION_PRIV) View Procurement Buyers List of Values using REST Service (PO_VIEW_BUYER_LOV_REST_SERVICE_PRIV) View Purchasing Hazard Classes List of Values using REST Service (PO_VIEW_HAZARD_CLASSES_LOV_REST_SERVICE_PRIV) View Purchasing UN Numbers List of Values using REST Service (PO_VIEW_UNNUMBER_LOV_REST_SERVICE_PRIV) View Trading Community Organization (HZ_VIEW_TRADING_COMMUNITY_ORGANIZATION_PRIV) View Trading Community Person (HZ_VIEW_TRADING_COMMUNITY_PERSON_PRIV) Manage Item Redwood Items (EGP_MANAGE_REDWOOD_ITEM_PRIV) Manage Item Redwood Attachments (EGP_MANAGE_REDWOOD_ITEM_ATTACHMENT_PRIV) Manage Item Redwood Associations (EGP_MANAGE_REDWOOD_ITEM_ASSOCIATION_PRIV) Manage Item Redwood Item Categories (EGP_MANAGE_REDWOOD_ITEM_CATEGORY_PRIV) Manage Item Redwood Relationships (EGP_MANAGE_REDWOOD_ITEM_RELATIONSHIP_PRIV) Manage Item Redwood Structures (EGP_MANAGE_REDWOOD_ITEM_STRUCTURE_PRIV) Get New Item Request Rest (EGI_NEW_ITEM_REQUEST_REST_PRIV) Manage Item Status REST (EGP_ITEM_STATUSES_PRIV) | L55: OPT IN+Role Setup | N55: Venkat | O55: VMI Analytics
A56: 55 | B56: Supply Chain Collaboration | C56: Supply Chain Collaboration | D56: Specify Aggregation Schedule Using a Redwood Page | E56: 24B | F56: 26A | G56: Wave1 - Simple Pages | H56: 26C | I56: To access the item on Redwood page: View Item Redwood Items (EGP_VIEW_REDWOOD_ITEM_PRIV) Manage Item Redwood Items (EGP_MANAGE_REDWOOD_ITEM_PRIV) To create, manage, or view the item structure on the Redwood page: Create Item Structure (EGP_CREATE_ITEM_STRUCTURE_PRIV) Manage Item Redwood Structures (EGP_MANAGE_REDWOOD_ITEM_STRUCTURE_PRIV) View Item Redwood Structures (EGP_VIEW_REDWOOD_ITEM_STRUCTURE_PRIV To manage change order on Redwood page: Manage Change Orders (ACA_MANAGE_CHANGE_ORDERS_PRIV) | L56: OPT IN+Role Setup | N56: Venkat | O56: Select Aggregation Schedule
A57: 56 | B57: Inventory Management | C57: Inventory Management | D57: Manage Subinventories and Locators on Redesigned Pages | E57: 24A | F57: 26A | G57: Wave2 - Modarate Pages | H57: 26A | J57: Get Item Rest (EGP_GET_ITEM_REST_PRIV) Manage Inventory Status (INV_MANAGE_INVENTORY_STATUS_PRIV) Manage Subinventory and Locator (INV_MANAGE_SUBINVENTORY_AND_LOCATOR_PRIV) Manage Unit of Measure Usage (INV_MANAGE_UNIT_OF_MEASURE_USAGE_PRIV) View Inventory On-Hand Balance Web Service (INV_VIEW_INVENTORY_ONHAND_BALANCE_WEB_SERVICE_PRIV) View Subinventory and Locator List of Values by Web Service (INV_VIEW_SUBINVENTORY_LOCATOR_LOV_WEB_SERVICE_PRIV) View Inventory Organizations List of Values by Web Service (RCS_VIEW_INV_ORG_LOV_WEB_SERVICE_PRIV) View Units of Measure List of Values by Web Service (RCS_VIEW_UNITS_OF_MEASURE_LOV_WEB_SERVICE_PRIV) | L57: OPT IN | M57: Y | N57: G, Pravalika | O57: Inventory Work Area
A58: 57 | B58: Inventory Management | C58: Inventory Management | D58: Manage Item Transaction Defaults on a Redesigned Page | E58: 24B | F58: 26A | G58: Wave2 - Modarate Pages | H58: 26A | I58: View Item Redwood Items (EGP_VIEW_REDWOOD_ITEM_PRIV) Manage Item Supplier Associations (EGP_MANAGE_REDWOOD_ITEM_SUPPLIER_ASSOCIATION_PRIV) | L58: Role Setup+Profile option | M58: Y | N58: G, Pravalika | O58: Inventory Work Area
A59: 58 | B59: Procurement | C59: Purchasing | D59: Search for Purchase Agreements Using a Redwood Page | E59: 24B | F59: 26A | G59: Wave1 - Simple Pages | H59: 26A | I59: View Item Redwood Items (EGP_VIEW_REDWOOD_ITEM_PRIV) Manage Item Redwood Items (EGP_MANAGE_REDWOOD_ITEM_PRIV) | J59: Manage Administrator Profile Values > ORA_PO_MANAGE_AGREEMENTS_REDWOOD_ENABLED = Y | K59: 1. Submit the ESS job to create index definition and perform initial ingest to OSCS scheduled process with this index name: Purchase Agreements: fa-prc-pa 2. We can Confiure Guided Journey 3. We can use VBCS to hide or show field | L59: OPT IN+ Profile Option | M59: Y | N59: Panwar, Mukesh | O59: Purchase Agreement Header
A60: 59 | B60: Procurement | C60: Responsive Self Service Procurement | D60: Create Multiple Distributions on Requisitions | E60: 24B | F60: 26A | G60: Wave2 - Modarate Pages | H60: 25C | I60: For items: View Item Redwood (ORA_EGP_REDWOOD_VIEW_ITEM_DUTY) For landing page: Access Product Management Landing Page (EGP_ACCESS_LANDING_PAGE_PRIV) Access Clipboard (ACA_ACCESS_CLIPBOARD_PRIV) Access HCM Common Components (HRC_ACCESS_HCM_COMMON_COMPONENTS_PRIV) For manufacturers: View Manufacturer (EGP_VIEW_MANUFACTURER_PRIV) For change orders: View Change Order (ACA_VIEW_CHANGE_ORDERS_PRIV) or Manage Change Orders (ACA_MANAGE_CHANGE_ORDERS_PRIV) | L60: Role Setup+Profile option | M60: Y | N60: DESHPANDE, NILESH | O60: Requisition Line
A61: 60 | B61: Procurement | C61: Responsive Self Service Procurement | D61: View Requisition Lifecycle Information | E61: 24B | F61: 25D | G61: Wave2 - Modarate Pages | H61: 25C | I61: Product Management Search Page Product Search (ORA_EGI_PRODUCT_SEARCH_DUTY) and Product Search (ORA_EGI_PRODUCT_SEARCH_HCM_DUTY) duty roles contain the following privileges: Access Product Development Configurations Using a REST Service (ACA_GET_PD_CONFIGURATIONS_REST_PRIV) GET Product Management Index REST (EGP_GET_PM_INDEX_REST_PRIV) Get Item Index Available Attributes REST (EGP_GET_PM_ITEM_AVAIL_REST_PRIV) Get Search View REST (EGP_GET_SEARCH_VIEW_REST_PRIV) Manage Search View REST (EGP_MANAGE_SEARCH_VIEW_REST_PRIV) Manage System Searches (HRC_MANAGE_SYSTEM_SEARCHES_PRIV) Use REST Service - Saved Searches (HRC_REST_SERVICE_ACCESS_SAVED_SEARCHES_PRIV) View Product Management Search (EGP_VIEW_PRODUCT_MGT_SEARCH_PRIV) Access HCM Common Components (HRC_ACCESS_HCM_COMMON_COMPONENTS_PRIV) Manage Search Consumer Applications Rest (EGP_MANAGE_SEARCH_CONS_REST_PRIV) | L61: OPT IN | M61: Y | N61: DESHPANDE, NILESH | O61: Requisition Line
A62: 61 | B62: Procurement | C62: Responsive Self Service Procurement | D62: View Requisition Document History | E62: 24B | F62: 25D | G62: Wave1 - Simple Pages | H62: 25C | I62: To search for manufacturers using a Redwood page: Access Product Development Configurations Using a REST Service(ACA_GET_PD_CONFIGURATIONS_REST_PRIV) Access Product Management Landing Page(EGP_ACCESS_LANDING_PAGE_PRIV) Get Search View REST(EGP_GET_SEARCH_VIEW_REST_PRIV) Manage Product Management Data Security EGO_MGT_PRODUCT_MGT_DATA_SECURITY_PRIV) View Feature States Value by Web Service(RCS_VIEW_FEATURE_STATES_WEB_SERVICE_PRIV) Get View Available Attribute REST (EGP_VIEW_AVAIL_ATTR_REST_PRIV) Grant Search Framework Manager Permissions (FND_SEARCH_FWK_MGR_PRIV) To view only manufacturers: View Manufacturer (EGP_VIEW_MANUFACTURER_PRIV) To edit manufacturers: Manage Item Manufacturer (EGP_MANAGE_ITEM_MANUFACTURER_PRIV) Manage Manufacturers (EGP_MANAGE_MANUFACTURER_PRIV) To create manufacturers: Create Manufacturer (EGP_CREATE_MANUFACTURER_PRIV) Manage Manufacturer (EGP_MANAGE_MANUFACTURER_PRIV) | L62: Role Setup+Profile option | M62: Y | N62: DESHPANDE, NILESH | O62: Requisition Header
A63: 62 | B63: Procurement | C63: Responsive Self Service Procurement | D63: Assign Additional Supplier Contact Emails for Catalog Item-Based Requisitions | E63: 24B | F63: 25D | G63: Wave2 - Modarate Pages | H63: 25C | I63: Manage Requisition with the Responsive Self Service Procurement Application (POR_MANAGE_REQ_WITH_PWA_PRIV). | J63: ORA_POR_RESP_DISABLE_CONTACT_AUTOSOURCING | L63: OPT IN+Profile option+Role Setup | M63: Y | N63: DESHPANDE, NILESH | O63: Requisition Line
A64: 63 | B64: Procurement | C64: Responsive Self Service Procurement | D64: Change Description for Agreement Based Items During Shopping | E64: 24B | F64: 25D | G64: Wave2 - Modarate Pages | H64: 25C | I64: Manage Requisition with the Responsive Self Service Procurement Application (POR_MANAGE_REQ_WITH_PWA_PRIV) | L64: OPT IN+Role Setup | M64: Y | N64: DESHPANDE, NILESH | O64: Requisition Line
A65: 64 | B65: Procurement | C65: Responsive Self Service Procurement | D65: Refine Requisition Search Using Filters | E65: 24B | F65: 25D | G65: Wave2 - Modarate Pages | H65: 25C | I65: Requisition Self Service Responsive Application User Duty (ORA_POR_REQUISITION_SELF_SERVICE_PWA_USER_DUTY) | L65: OPT IN+Role Setup | M65: Y | N65: DESHPANDE, NILESH | O65: My Requisition
A66: 65 | B66: Product Hub | C66: Product Hub | D66: Search Product Management Content Using the Redwood User Experience | E66: 24B | F66: 26C | G66: Wave1 - Simple Pages | H66: 26C | I66: View Product Management Search (EGP_VIEW_PRODUCT_MGT_SEARCH_PRIV) Get Search View Rest (EGP_GET_SEARCH_VIEW_REST_PRIV) GET Product Management Index REST (EGP_GET_PM_INDEX_REST_PRIV) | K66: Mandate version is not specified hence considering the mandate version as per Roadmap for PLM module which is 26B. | L66: OPT IN+Role Setup | M66: Y | N66: Sujay Parab | O66: Product Management Experience
A67: 66 | B67: Product Hub | C67: Product Hub | D67: Manage Spoke Systems Using the Redwood User Experience | E67: 24B | F67: 26C | G67: Wave1 - Simple Pages | H67: 26C | I67: Manage Item Source System (EGI_MANAGE_ITEM_SOURCE_SYSTEM_PRIV) | J67: ORA_EGI_SPOKE_SYSTEM_REDWOOD_PAGES_ENABLED | K67: Mandate version is not specified hence considering the mandate version as per Roadmap for PLM module which is 26B. | L67: Role Setup+Profile option | M67: Y | N67: Sujay Parab | O67: Manage Spoke Systems
A68: 67 | B68: Product Hub | C68: Product Hub | D68: Manage Delete Groups Using the Redwood User Experience | E68: 24B | F68: 26C | G68: Wave1 - Simple Pages | H68: 26C | I68: Manage Item Delete Group (EGP_MANAGE_ITEM_DELETE_GROUP_PRIV) Access Item Structure Data Using a REST Service (EGP_GET_ITEM_STRUCTURE_REST_PRIV) Access Change Order Using a REST Service (ACA_GET_CHANGE_REST_PRIV) Manage Delete Group Rest (EGP_DG_REST_PRIV) GET Product Management Index REST (EGP_GET_PM_INDEX_REST_PRIV) Get Search View REST (EGP_GET_SEARCH_VIEW_REST_PRIV) Grant Search Framework Manager Permissions (FND_SEARCH_FWK_MGR_PRIV) View Product Management Search (EGP_VIEW_PRODUCT_MGT_SEARCH_PRIV) | J68: ORA_EGP_DELETE_GROUPS_REDWOOD_PAGES_ENABLED | K68: Mandate version is not specified hence considering the mandate version as per Roadmap for PLM module which is 26B. | L68: Role Setup+Profile option | M68: Y | N68: Sujay Parab | O68: Manage Delete Groups
A69: 68 | B69: Inventory Management | C69: Inventory Management | D69: Manage Lots and Serial Numbers Using a Redwood Page | E69: 24C | F69: 26B | G69: Wave2 - Modarate Pages | H69: 26A | I69: Manage Lots and Serial Numbers Using Responsive Inventory Duty (ORA_INV_MANAGE_LOT_SERIAL_PWA_DUTY) | J69: ORA_INV_LOTS_AND_SERIAL_NUMBERS_REDWOOD_ENABLED | L69: Role Setup+Profile option | M69: Y | N69: G, Pravalika | O69: Inventory Work Area
A70: 69 | B70: Inventory Management | C70: Inventory Management | D70: Create Multiple New Subinventories and Locators Simultaneously | E70: 24C | F70: 26B | G70: Wave2 - Modarate Pages | H70: 26A | I70: Configure Subinventory Using Responsive Inventory (ORA_INV_CONFIGURE_SUBINVENTORY_PWA_DUTY) | L70: OPT IN | M70: Y | N70: G, Pravalika | O70: Subinventories page
A71: 70 | B71: Inventory Management | C71: Inventory Management | D71: Approve Count Sequences Using a Redwood Page | E71: 24C | F71: 26B | G71: Wave1 - Simple Pages | H71: 26A | I71: Approve Cycle Count Using Responsive Inventory Duty (ORA_INV_APPROVE_CYCLE_COUNT_PWA_DUTY) | J71: ORA_INV_CYCLE_COUNT_REDWOOD_ENABLED | L71: Role Setup+Profile option | M71: Y | N71: G, Pravalika | O71: Cycle Count UI
A72: 71 | B72: Inventory Management | C72: Inventory Management | D72: Create Outbound Shipment Requests Using a Redwood Page | E72: 24C | F72: 26B | G72: Wave2 - Modarate Pages | H72: 26A | I72: Create Outbound Shipment Request Using Responsive Shipping (ORA_WSH_CREATE_OUTBOUND_SHIPMENT_REQUEST_PWA_DUTY) | J72: ORA_WSH_PICK_WAVE_SHIPMENT_REQUEST_REDWOOD_PAGES_ENABLED | L72: Role Setup+Profile option | M72: Y | N72: G, Pravalika | O72: Outbound Shipment Request
A73: 72 | B73: Inventory Management | C73: Inventory Management | D73: Create Pick Waves Using a Redwood Page | E73: 24C | F73: 26B | G73: Wave2 - Modarate Pages | H73: 26A | I73: Create Pick Wave Using Responsive Shipping (ORA_WSH_CREATE_PICK_WAVE_PWA_DUTY) | J73: ORA_WSH_PICK_WAVE_SHIPMENT_REQUEST_REDWOOD_PAGES_ENABLED | L73: Role Setup+Profile option | M73: Y | N73: G, Pravalika | O73: Pick Wave UI
A74: 73 | B74: SCM Common Components | C74: Global Order Promising | D74: Review Calendar Associations Using a Redwood Page | E74: 24C | F74: 26B | G74: Wave2 - Modarate Pages | H74: 26B | I74: View Planning Calendars (MSP_REVIEW_PLANNING_CALENDAR_PRIV) Edit Planning Calendars (MSP_REVIEW_PLANNING_CALENDAR_ASSIGNMENT_PRIV) Monitor Backlog Management Work Area (MSC_MONITOR_BACKLOG_MANAGEMENT_WORK_AREA_PRIV) Create Backlog Plan (MSC_CREATE_BACKLOG_PLAN_PRIV) | J74: Redwood Backlog Management Pages Enabled (ORA_MSC_BACKLOG_MANAGEMENT_REDWOOD_ENABLED) | K74: Dependent on Review Planning Calendars Using a Redwood Page | L74: OPT IN | M74: Y | N74: Pahwa, Madhur | O74: Planning Calendars UI
A75: 74 | B75: Inventory Management | C75: Cost Management | D75: Redwood: Create and Edit Cost Analysis Groups Using a New User Experience | E75: 25B | F75: 26B | G75: Wave2 - Modarate Pages | H75: 26A | I75: Manage Workflow Notifications (FUN_MANAGE_WORKFLOW_NOTIFICATIONS_PRIV) to view approvers. 2) Manage Requisition with the Responsive Self Service Procurement Application (POR_MANAGE_REQ_WITH_PWA_PRIV) to access the responsive application. | L75: Auto Enabled | M75: Yes | N75: Krishnan, Karthikeyan | O75: Cost Analysis Groups Page
A76: 75 | B76: Procurement | C76: Responsive Self Service Procurement | D76: View Requisitions Created by Other Preparers | E76: 24C | F76: 26B | G76: Wave1 - Simple Pages | H76: 26A | I76: Manage Requisition with the Responsive Self Service Procurement Application (POR_MANAGE_REQ_WITH_PWA_PRIV) to access the responsive application. 2) View Requisition - All (POR_VIEW_REQUISITION_ALL_PRIV) to view all requisitions in accessible requisitioning BUs | L76: OPT IN+Role Setup | M76: Y | N76: DESHPANDE, NILESH | O76: My Requisition
A77: 76 | B77: Procurement | C77: Responsive Self Service Procurement | D77: Manage Approvers on Requisitions during Shopping Checkout | E77: 24C | F77: 26B | G77: Wave1 - Simple Pages | H77: 26A | I77: Manage Workflow Notifications (FUN_MANAGE_WORKFLOW_NOTIFICATIONS_PRIV) to view approvers. 2) Manage Requisition with the Responsive Self Service Procurement Application (POR_MANAGE_REQ_WITH_PWA_PRIV) to access the responsive application. | L77: OPT IN+Role Setup | M77: Y | N77: DESHPANDE, NILESH | O77: Requisition Shopping Cart Page
A78: 77 | B78: Procurement | C78: Responsive Self Service Procurement | D78: Modify Requisitions as an Approver | E78: 24C | F78: 26B | G78: Wave1 - Simple Pages | H78: 26A | I78: Manage Requisition with the Responsive Self Service Procurement Application (POR_MANAGE_REQ_WITH_PWA_PRIV). 2) Edit Requisition as Approver (POR_CREATE_REQUISITION_ALLOW_APPROVER_MODIFICATION_PRIV) | L78: OPT IN+Role Setup | M78: Y | N78: DESHPANDE, NILESH | O78: Requisiton Approval UI
A79: 78 | B79: Procurement | C79: Responsive Self Service Procurement | D79: Create Urgent Requisitions | E79: 24C | F79: 26B | G79: Wave1 - Simple Pages | H79: 26A | I79: Manage Requisition with the Responsive Self Service Procurement Application (POR_MANAGE_REQ_WITH_PWA_PRIV) | L79: OPT IN+Role Setup | M79: Y | N79: DESHPANDE, NILESH | O79: Requisition Line
A80: 79 | B80: Procurement | C80: Responsive Self Service Procurement | D80: Update the Preparer and Requester on Requisitions | E80: 24C | F80: 26B | G80: Wave1 - Simple Pages | H80: 26A | I80: Manage Requisition with the Responsive Self Service Procurement Application (POR_MANAGE_REQ_WITH_PWA_PRIV) | J80: ORA_POR_USE_SUPP_SITE_INVOICE_CURR) | L80: OPT IN+Profile option+Role Setup | M80: Y | N80: DESHPANDE, NILESH | O80: Requisition Line
A81: 80 | B81: Procurement | C81: Responsive Self Service Procurement | D81: Create Requisitions as an Advanced User | E81: 24C | F81: 26B | G81: Wave1 - Simple Pages | H81: 26A | I81: Manage Requisition with the Responsive Self Service Procurement Application (POR_MANAGE_REQ_WITH_PWA_PRIV). Create Requisition with Quick Entry (POR_CREATE_REQUISITION_ALLOW_QUICK_ENTRY_PRIV). View Total On Hand Quantity in Supply Source (DOS_VIEW_AVAILABLE_ONHAND_QTY_PRIV) to view available quantity in a source organization. View Subinventory List of Values by Web Service for Self Service Procurement User (INV_VIEW_SUBINVENTORY_LOV_PRC_WEB_SERVICE_PRIV) to view subinventory list of values. | L81: OPT IN+Role Setup | M81: Y | N81: DESHPANDE, NILESH | O81: Requisition Line
A82: 81 | B82: Procurement | C82: Responsive Self Service Procurement | D82: Populate Currency on Requisition Lines Automatically from the Supplier Site’s Invoice Currency | E82: 24C | F82: 26B | G82: Wave1 - Simple Pages | H82: 26A | I82: Manage Requisition with the Responsive Self Service Procurement Application (POR_MANAGE_REQ_WITH_PWA_PRIV). | J82: ORA_POR_USE_SUPP_SITE_INVOICE_CURR) | L82: OPT IN+Role Setup | M82: Y | N82: DESHPANDE, NILESH | O82: Requisition Line
A83: 82 | B83: Supply Chain Orchestration | C83: Supply Chain Orchestration | D83: Use Redesigned Pages to View Supply Request Lines | E83: 24C | F83: 26B | G83: Wave1 - Simple Pages | H83: 26C | I83: Process Supply Order Interface (DOS_PROCESS_SUPPLY_ORDER_INTERFACE_PRIV) View Supply Orders (DOS_VIEW_SUPPLY_ORDERS_PRIV) Manage Supply Request Exceptions (DOS_MANAGE_SUPPLY_REQUEST_EXCEPTIONS_PRIV) View Supply Order Exceptions and Status (DOS_VIEW_SUPPLY_ORDER_EXCEPTIONS_AND_STATUS_PRIV) | L83: Auto Enabled | M83: Y | N83: Sumalatha, A | O83: View Supply Request Line Details
A84: 83 | B84: Product Hub | C84: Product Development | D84: Enhance Manufacturer Management | E84: 24C | F84: 26B | G84: Wave2 - Modarate Pages | H84: 26C | I84: To search for manufacturers using a Redwood page: Get Search View REST(EGP_GET_SEARCH_VIEW_REST_PRIV) To view only manufacturers: View Manufacturer (EGP_VIEW_MANUFACTURER_PRIV) To edit manufacturers: Manage Manufacturer (EGP_MANAGE_MANUFACTURER_PRIV) To create manufacturers: Create Manufacturer (EGP_CREATE_MANUFACTURER_PRIV) Manage Manufacturer (EGP_MANAGE_MANUFACTURER_PRIV) | K84: Mandate version is not specified hence considering the mandate version as per Roadmap for PLM module which is 26B. | L84: Role Setup+Profile option | M84: Y | N84: Sujay Parab | O84: Manage Manufacturer
A85: 84 | B85: Manufacturing | C85: Manufacturing | D85: Search for, Create, and Edit Work Definition Names Using the Redwood User Experience | E85: 24B | F85: 26A | G85: Wave1 - Simple Pages | H85: 26A | J85: ORA_WIS_WORK_DEFINITION_NAMES_REDWOOD_ENABLED | L85: Role Setup+Profile option | N85: Muthu Kumar Madhavan | O85: Work Definition UI
A86: 85 | B86: Manufacturing | C86: Manufacturing | D86: Search for, Create, and Edit Work Areas Using the Redwood User Experience | E86: 24B | F86: 26A | G86: Wave1 - Simple Pages | H86: 26A | J86: ORA_WIS_WORK_AREAS_REDWOOD_ENABLED | L86: Role Setup+Profile option | N86: Muthu Kumar Madhavan | O86: Manufacturing Work Area
A87: 86 | B87: Manufacturing | C87: Smart Operations | D87: Create, Edit, and Search for Workstations | E87: 24C | F87: 26A | G87: Wave2 - Modarate Pages | H87: 26B | L87: OPT IN | M87: Y | N87: Muthu Kumar Madhavan | O87: Workstation UI
A88: 87 | B88: Manufacturing | C88: Smart Operations | D88: Execute Production at a Workstation and Automate Resource Transactions | E88: 24C | F88: 26A | G88: Wave2 - Modarate Pages | H88: 26B | L88: OPT IN | M88: Y | N88: Muthu Kumar Madhavan | O88: Execute Production at a Workstation page
A89: 88 | B89: Manufacturing | C89: Smart Operations | D89: Create Shift Notes During Work Execution at a Workstation for Operator Handoff | E89: 24C | F89: 26A | G89: Wave2 - Modarate Pages | H89: 26B | L89: OPT IN+Setup | M89: Y | N89: Muthu Kumar Madhavan | O89: Workstation UI
A90: 89 | B90: Manufacturing | C90: Manufacturing | D90: Search for, Create, and Edit Work Order Statuses Using the Redwood User Experience | E90: 24C | F90: 26A | G90: Wave2 - Modarate Pages | H90: 26B | J90: ORA_WIE_WO_STATUSES_REDWOOD_ENABLED | L90: Role Setup+Profile option | M90: Y | N90: Muthu Kumar Madhavan | O90: Manage Work Order Statuses
A91: 90 | B91: Manufacturing | C91: Manufacturing | D91: Search for, Create, and Edit Work Centers Using the Redwood User Experience | E91: 24C | F91: 26A | G91: Wave2 - Modarate Pages | H91: 26B | J91: ORA_WIS_WORK_CENTERS_REDWOOD_ENABLED | L91: Role Setup+Profile option | M91: Y | N91: Muthu Kumar Madhavan | O91: Work Center
A92: 91 | B92: Manufacturing | C92: Manufacturing | D92: Search for, Create, and Edit Standard Operations Using a Redwood User Experience | E92: 24C | F92: 26A | G92: Wave2 - Modarate Pages | H92: 26B | J92: ORA_WIS_STANDARD_OPERATIONS_REDWOOD_ENABLED | L92: Role Setup+Profile option | M92: Y | N92: Muthu Kumar Madhavan | O92: Manage Standard Operations
A93: 92 | B93: Manufacturing | C93: Manufacturing | D93: Manage Work Definition Productivity Improvements Using the Redwood User Experience | E93: 24C | F93: 26A | G93: Wave2 - Modarate Pages | H93: 26B | J93: ORA_WIS_WORK_DEFINITIONS_REDWOOD_ENABLED | L93: Role Setup+Profile option | M93: Y | N93: Muthu Kumar Madhavan | O93: Work Definition UI
A94: 93 | B94: Inventory Management | C94: Inventory Management | D94: Redwood: Create Cycle Counts Using a Redwood Page | E94: 24D | F94: 26A | G94: Wave2 - Modarate Pages | H94: 26A | J94: ORA_INV_CREATE_CYCLE_COUNT_REDWOOD_ENABLED | L94: OPT IN | M94: Y | N94: G, Pravalika | O94: Cycle Count UI
A95: 94 | B95: Inventory Management | C95: Inventory Management | D95: Redwood: View Item Quantities Using a Redwood Page | E95: 24D | F95: 25B | G95: Wave2 - Modarate Pages | H95: 26A | L95: OPT IN | M95: Y | N95: G, Pravalika | O95: Item Quantities page
A96: 95 | B96: Inventory Management | C96: Receiving | D96: Redwood: Inspect Receipts Using a Redwood Page | E96: 24D | F96: 25B | G96: Wave2 - Modarate Pages | H96: 26A | J96: Manage Administrator Profile Values > ORA_RCV_INSPECT_RECEIPT_LINES_REDWOOD_ENABLED = Yes | K96: 1. Activate Sandbox to enable the Inventory Management (New) 2. Run the "ESS job to create index definition and perform Initial Ingest to OSCS" Refer: https://docs.oracle.com/en/cloud/saas/readiness/scm/24b/inv24b/24B-inventory-wn-f31373.htm | L96: Profile Option | M96: Y | N96: G, Pravalika | O96: Inspect Receipt Line
A97: 96 | B97: Inventory Management | C97: Receiving | D97: Redwood: Create Receipt Returns Using a Redwood Page | E97: 24D | F97: 25B | G97: Wave2 - Modarate Pages | H97: 26A | J97: Manage Receiving Profile Options > ORA_RCV_RECEIVING_RETURNS_REDWOOD_ENABLED = Yes | L97: Profile Option | M97: Y | N97: G, Pravalika | O97: Receipt Returns
A98: 97 | B98: Inventory Management | C98: Receiving | D98: Redwood: Create Unordered Receipts Using a Redwood Page | E98: 24D | F98: 26A | G98: Wave2 - Modarate Pages | H98: 26A | J98: Manage Inventory Profile Options > ORA_RCV_UNORDERED_RECEIPTS_REDWOOD_ENABLED = Yes | L98: Profile Option | M98: Y | N98: G, Pravalika | O98: Create Unordered Receipts
A99: 98 | B99: Inventory Management | C99: Receiving | D99: Redwood: Correct Receipts Using a Redwood Page | E99: 24D | F99: 26A | G99: Wave2 - Modarate Pages | H99: 26A | J99: Manage Administrator Profile Values > ORA_RCV_CORRECT_RECEIPTS_REDWOOD_ENABLED = Yes | L99: Profile Option | M99: Y | N99: G, Pravalika | O99: Correct Receipt Line
A100: 99 | B100: Order Management | C100: Order Management | D100: Redwood: Create and Manage Sales Orders | E100: 24D | F100: 26A | G100: Wave2 - Modarate Pages | H100: 26B | I100: View Orders (FOM_VIEW_ORDERS_PRIV) Revise Order (FOM_REVISE_ORDER_PRIV) Cancel Order (FOM_CANCEL_ORDER_PRIV) Prepare Sales Orders for Redesigned Pages (FOM_PREPARE_SALES_ORDERS_FOR_REDESIGNED_PAGES_PRIV) Modify Orchestration Order Fulfillment Line Schedule Date (DOO_MODIFY_ORCHESTRATION_ORDER_FULFILLMENT_LINE_SCHEDULE_DATE_PRIV) View Purchase Order (PO_VIEW_PURCHASE_ORDER_PRIV) View Receipt Summary and Transaction History using Responsive Receiving (RCV_VIEW_RECEIPT_SUMMARY_TXN_HISTORY_PWA_PRIV) View Shipment Using Responsive Shipping (WSH_VIEW_SHIPMENT_USING_RESPONSIVE_SHIPPING_PWA) View Supply Orders (DOS_VIEW_SUPPLY_ORDERS_PRIV) | K100: Redwood: Manage Configured Items on Sales Orders | L100: OPT IN+Role Setup | M100: Y | N100: Arepally, Susmitha | O100: Sales Order New , Sales orders
...

Sheet Pivot
A3: Row Labels | B3: Count of Feature Names
A4: Inventory Management | B4: 290
A5: Maintenance | B5: 100
A6: Manufacturing | B6: 114
A7: Order Management | B7: 110
A8: Procurement | B8: 354
A9: Product Hub | B9: 18
A10: Product Lifecycle Management | B10: 62
A11: Quality Management | B11: 12
A12: SCM Common Components | B12: 21
A13: Supply Chain Collaboration | B13: 20
A14: Supply Chain Orchestration | B14: 18
A15: Supply Chain Planning | B15: 145
... A17: Grand Total | B17: 1295

Sheet Mandate Version
A1: Product | B1: Module | H1: Module | I1: Version
A2: Product Lifecycle Management | B2: Product Management | H2: Supplier Model | I2: 25A
A3: Inventory Management | B3: Cost Management | H3: Cost Management | I3: 25B
A4: Inventory Management | B4: Receipt Accounting | H4: Responsive Self Service Procurement | I4: 25C
A5: Supply Chain Orchestration | B5: Supply Chain Orchestration | H5: Quality Inspection Management | I5: 25D
A6: Inventory Management | B6: Advanced Inventory Management | H6: Manufacturing | I6: 26A
A7: Supply Chain Planning | B7: Sales and Operations Planning | H7: Product Lifecycle Management | I7: 26B
A8: Order Management | B8: Global Order Promising | H8: Service Logistics | I8: 26B
A9: Procurement | B9: Sourcing | H9: Sourcing | I9: 26B
A10: Supply Chain Planning | B10: Replenishment Planning | H10: Purchasing | I10: 26B
A11: SCM Common Components | B11: Configurator | H11: Order Management | I11: 26B
A12: Maintenance | B12: Maintenance | H12: Supply Chain Planning | I12: 26B
... A14: Supply Chain Planning | B14: Demand Management | H14: Maintenance | I14: 26C
A15: SCM Common Components | B15: Global Order Promising | I15: 26D
A16: Manufacturing | B16: Manufacturing | I16: 27A
A17: Inventory Management | B17: Collaboration Messaging Framework
A18: Supply Chain Planning | B18: Supply Planning
A19: Procurement | B19: Collaboration Messaging Framework
A20: Supply Chain Planning | B20: Backlog Management
A21: Supply Chain Planning | B21: Backlog Management
A22: Procurement | B22: Supplier Model
A23: Procurement | B23: Spend Classification
A24: Inventory Management | B24: Inventory Management
A25: Order Management | B25: Order Management
A26: Procurement | B26: External Purchase Prices
A27: Inventory Management | B27: Product Recall Management
A28: Procurement | B28: Purchasing
... A76: Product Lifecycle Management | B76: SCM Common Components

Sheet Overall Sheet
A1: S.no | B1: Product | C1: Module | D1: Feature Names | F1: Update Version | G1: Mandate Version | H1: Wave | I1: CSS Mandate Version | J1: Privilage Name | K1: Profile Options Value | L1: Additional Info | M1: Action Required | N1: Availability of PPT | O1: SME | P1: UI Page Name | Q1: Remarks
A2: 1 | B2: Inventory Management | C2: Mobile Inventory | D2: Redwood: Create an Interorganization Transfer Using a Mobile Device | F2: 24D | G2: 25B | H2: Wave1 - Simple Pages | I2: 26B | J2: Create Interorganization Transfer Using Responsive Inventory Duty (ORA_INV_CREATE_INTERORG_TRANSFER_PWA_DUTY). | M2: Role Setup | N2: Y | O2: Pragyan Dash | P2: Inventory Management (Mobile)
A3: 2 | B3: Inventory Management | C3: Mobile Inventory | D3: Redwood: View the Inventory Management (New) Tile as Inventory Management (Mobile) | F3: 24D | G3: 25B | H3: Wave1 - Simple Pages | I3: 26B | M3: Auto Enabled | P3: Inventory Management (Mobile)
A4: 3 | B4: Inventory Management | C4: Mobile Inventory | D4: Redwood: Inspect Received Goods Using a Mobile Device | F4: 24D | G4: 25B | H4: Wave1 - Simple Pages | I4: 26B | J4: New: Inspect goods using the responsive receiving application (ORA_RCV_INSPECT_GOODS_PWA_DUTY) | K4: Manage Inventory Profile Options > ORA_INV_MOBILE_INVENTORY_MANAGEMENT_REDWOOD_ENABLED = Yes | L4: 1. Activate Sandbox to enable the Inventory Management (New) 2. Run the "ESS job to create index definition and perform Initial Ingest to OSCS" Refer: https://docs.oracle.com/en/cloud/saas/readiness/scm/24b/inv24b/24B-inventory-wn-f31373.htm | M4: Profile Option | P4: Inventory Management (Mobile)
A5: 4 | B5: Inventory Management | C5: Mobile Inventory | D5: Redwood: View Lot Attributes in Mobile Inventory Transactions | F5: 24D | G5: 25B | H5: Wave1 - Simple Pages | I5: 26B | M5: Auto Enabled | P5: Inventory Management (Mobile)
A6: 5 | B6: Inventory Management | C6: Cost Management | D6: Redwood: View Rollup Costs Using a New User Experience | F6: 25A | G6: 25B | H6: Wave1 - Simple Pages | I6: 26A | J6: Users who are assigned a configured job role that contains the following privilege can access this feature: View Rolled Up Costs (CST_REVIEW_ROLLEDUP_COSTS) | K6: On the Manage Administrator Profile Values page, search for and select the ORA_CST_VIEW_ROLLEDUP_COSTS_REDWOOD_ENABLED profile option code. In the Profile Values section, set the Site level to Yes. The default value is No. Click Save and Close. Changes in the profile value will affect users the next time they sign in. Yes = enables the feature No = disables the feature | M6: Role Setup+Profile option | N6: Y | O6: Miriam Chandni | P6: Cost Accounting Work Area
A7: 6 | B7: Inventory Management | C7: Cost Management | D7: Redwood: Create and Update Cost Scenarios Using a New User Experience | F7: 25A | G7: 25B | H7: Wave2 - Modarate Pages | I7: 26A | J7: Users who are assigned a configured job role that contains the following privilege can access this feature: Manage Cost Planning Scenario Definition (CST_MANAGE_SCENARIO) | K7: On the Manage Administrator Profile Values page, search for and select the ORA_CST_PLANNING_SCENARIOS_REDWOOD_ENABLED profile option code. In the Profile Values section, set the Site level to Yes. The default value is No. Click Save and Close. Changes in the profile value will affect users the next time they sign in. Yes = enables the feature No = disables the feature | M7: Role Setup+Profile option | N7: Y | O7: Miriam Chandni | P7: Cost Accounting Work Area
A8: 7 | B8: Inventory Management | C8: Cost Management | D8: Redwood: Review Standard Costs Import Exceptions Using a New User Experience | F8: 25A | G8: 25B | H8: Wave1 - Simple Pages | I8: 26A | J8: Users who are assigned a configured job role that contains the following privilege can access this feature: Estimate Costs (CST_ESTIMATE_COSTS) | K8: On the Manage Administrator Profile Values page, search for and select the ORA_CST_STD_COST_IMPORT_EXCEPTIONS_REDWOOD_ENABLED profile option code. In the Profile Values section, set the Site level to Yes. The default value is No. Click Save and Close. Changes in the profile value will affect users the next time they sign in. Yes = enables the feature No = disables the feature | M8: Role Setup+Profile option | N8: Y | O8: Miriam Chandni | P8: Cost Accounting Work Area
A9: 8 | B9: Inventory Management | C9: Receiving | D9: Redwood: Manage Inbound Shipments and Create ASN or ASBN Using a Redwood Page | F9: 24D | G9: 25C | H9: Wave1 - Simple Pages | I9: 26A | J9: 1. Manage Inbound Shipment Using Responsive Receiving (RCV_MANAGE_INBOUND_SHIPMENT_PWA) 2. Manage Inbound Shipment as Supplier Using Responsive Receiving (RCV_MANAGE_INBOUND_SHIPMENT_AS_SUPPLIER_PWA) 3. Create Advance Shipment Notice Using Responsive Receiving (RCV_CREATE_ADVANCE_SHIPMENT_NOTICE_PWA) 4. Create Advance Shipment Notice as Supplier Using Responsive Receiving (RCV_CREATE_ADVANCE_SHIPMENT_NOTICE_AS_SUPPLIER_PWA) | K9: Manage Receiving Profile Options > 1. ORA_RCV_INBOUND_SHIPMENTS_REDWOOD_ENABLED = Yes 2. ORA_RCV_ADVANCE_SHIPMENT_NOTICE_REDWOOD_ENABLED = Yes 3. ORA_RCV_INBOUND_SHIPMENTS_SUPPLIER_PORTAL_REDWOOD_ENABLED = Yes 4. ORA_RCV_ADVANCE_SHIPMENT_NOTICE_SUPPLIER_PORTAL_REDWOOD_ENABLED = Yes | L9: 1. Activate Sandbox to enable the Inventory Management (New) 2. Run the "ESS job to create index definition and perform Initial Ingest to OSCS" Refer: https://docs.oracle.com/en/cloud/saas/readiness/scm/24b/inv24b/24B-inventory-wn-f31373.htm | M9: Profile Option | N9: Y | O9: Mukesh Panwar | P9: Receipts
A10: 9 | B10: Inventory Management | C10: Receiving | D10: Redwood: View Receipts and Receipt Returns in Supplier Portal Using a Redwood Page | F10: 24D | G10: 25C | H10: Wave1 - Simple Pages | I10: 26A | J10: View Receiving Receipt and Receipt Return as Supplier (RCV_VIEW_RECEIVING_RECEIPT_AND_RECEIPT_RETURN_AS_SUPPLIER_PRIV) | K10: Manage Receiving Profile Options task > ORA_RCV_RECEIPTS_RETURNS_SUPPLIER_PORTAL_REDWOOD_ENABLED = Yes | M10: Profile Option | N10: Y | O10: Pragyan Dash | P10: Supplier Portal
A11: 10 | B11: Inventory Management | C11: Cost Management | D11: Create and Edit Overhead Rates Using Redwood Pages | F11: 24C | G11: 26B | H11: Wave2 - Modarate Pages | I11: 26A | J11: Users who are assigned a configured job role that contains the following privilege can access this feature: Manage Resource and Overhead Rate Plans (CST_MANAGE_RATE_PLANS) | K11: On the Manage Administrator Profile Values page, search for and select the ORA_CST_RESOURCE_RATES_REDWOOD_ENABLED profile option code. In the Profile Values section, set the Site level to Yes. The default value is No. Yes = enables the feature No = disables the feature | L11: Part of the standard setups | M11: Role Setup+Profile option | O11: Rekha Bhoopathy | P11: Overhead Rates
A12: 11 | B12: Inventory Management | C12: Fiscal Document Capture | D12: Manage Tolerances Using the Redwood Experience | F12: 24C | G12: 26B | H12: Wave2 - Modarate Pages | I12: 26B | J12: Set Up Fiscal Document Tolerances (CMF_FISCAL_DOC_TOLERANCES) Manage Fiscal Document Tolerances by Web Service (CMF_FISCAL_DOC_TOLERANCE_WEB_SERVICE) | K12: On the Manage Administrator Profile Values page, enable the new ORA_CMF_TOLERANCE_RULES_REDWOOD_ENABLED profile option at Site or Product or User level. Select Yes for the Redwood page for Fiscal Document Tolerance Rules Enabled option. | L12: Part of the standard setups | M12: Role Setup+Profile option | O12: Rekha Boopathy | P12: Fiscal Document Tolerance Rules
A13: 12 | B13: Supply Chain Orchestration | C13: Supply Chain Orchestration | D13: Manage Documentation and Accounting Rule in Redwood Pages | F13: 24C | G13: 26B | H13: Wave1 - Simple Pages | I13: 26D | J13: Maintain Documentation and Accounting Rules (FOS_MAINTAIN_TRADE_AND_ACCOUNTING_RULES) Manage Documentation and Accounting Rules (FOS_MANAGE_TRADE_AND_ACCOUNTING_RULES) View Documentation and Accounting Rules (FOS_VIEW_TRADE_AND_ACCOUNTING_RULES) | K13: ORA_FOS_TRADE_ACCOUNTING_RULES_REDWOOD_ENABLED | M13: Role Setup+Profile option | N13: Y | O13: Veeranarayana Swamy | P13: Documentation and Accounting Rules
A14: 13 | B14: Supply Chain Orchestration | C14: Supply Chain Orchestration | D14: Manage Transfer Pricing Rule in Redwood Pages | F14: 24C | G14: 26B | H14: Wave1 - Simple Pages | I14: 26D | J14: Maintain Transfer Pricing Rules (FOS_MAINTAIN_TRANSFER_PRICING_RULES) Manage Transfer Pricing Rules (FOS_MANAGE_TRANSFER_PRICING_RULES) View Transfer Pricing Rules (FOS_VIEW_TRANSFER_PRICING_RULES) | K14: ORA_FOS_TRANSFER_PRICING_RULES_REDWOOD_ENABLED | M14: Role Setup+Profile option | N14: Y | O14: Miriam Chandni | P14: Financial Orchestration Work Area
A15: 14 | B15: Inventory Management | C15: Cost Management | D15: Create and Update Resource Rates Using Redwood Pages | F15: 24B | G15: 26B | H15: Wave2 - Modarate Pages | I15: 26A | J15: Users who are assigned a configured job role that contains the following privilege can access this feature: Manage Resource and Overhead Rate Plans (CST_MANAGE_RATE_PLANS) | K15: On the Manage Administrator Profile Values page, search for and select the ORA_CST_RESOURCE_RATES_REDWOOD_ENABLED profile option code. In the Profile Values section, set the Site level to Yes. The default value is No. Yes = enables the feature No = disables the feature | L15: Part of the standard setups | M15: Role Setup+Profile option | O15: Rekha Bhoopathy | P15: Resource Rates
A16: 15 | B16: Inventory Management | C16: Cost Management | D16: Redwood: View Scenario Exceptions Using a New User Experience | F16: 25A | G16: 25B | H16: Wave1 - Simple Pages | I16: 26A | J16: Users who are assigned a configured job role that contains the following privilege can access this feature: View Scenario Exceptions (CST_MANAGE_SCENRIO_EXCEPTIONS) | K16: On the Manage Administrator Profile Values page, search for and select the ORA_CST_SCENARIO_EXCEPTIONS_REDWOOD_ENABLED profile option code. In the Profile Values section, set the Site level to Yes. The default value is No. Click Save and Close. Changes in the profile value will affect users the next time they sign in. Yes = enables the feature No = disables the feature | M16: Role Setup+Profile option | N16: Y | O16: Miriam Chandni | P16: Cost Accounting Work Area
A17: 16 | B17: Manufacturing | C17: Manufacturing | D17: Search for, Create, and Edit a Standard Item Work Definition Using the Redwood User Experience | F17: 24B | G17: 26B | H17: Wave1 - Simple Pages | I17: 26A | K17: ORA_WIS_WORK_DEFINITIONS_REDWOOD_ENABLED | M17: Role Setup+Profile option | N17: Y | O17: Yoga Gopalakrishnan | P17: Manage Work Definitions Page
A18: 17 | B18: Order Management | C18: Channel Revenue Management | D18: Redwood: Define Product Eligibility Based on Item Categories for Customer Rebate Programs | F18: 24D | G18: 25A | H18: Wave3 - Complex Pages | I18: 26C | J18: Manage Customer Programs (CJM_MANAGE_CUSTOMER_PROGRAMS_PRIV) | L18: Use the Opt In UI to enable this feature. | M18: OPT IN+Role Setup | O18: TBD | P18: Customer Rebate Work Area
A19: 18 | B19: Order Management | C19: Channel Revenue Management | D19: Redwood: Exclude Multiple Items or Item Categories in Product Eligibility Rules | F19: 24D | G19: 25C | H19: Wave3 - Complex Pages | I19: 26C | J19: Manage Customer Programs (CJM_MANAGE_CUSTOMER_PROGRAMS_PRIV) | L19: Use the Opt In UI to enable this feature. | M19: OPT IN+Role Setup | O19: TBD | P19: Customer Rebate Work Area
A20: 19 | B20: Order Management | C20: Channel Revenue Management | D20: Redwood: Manage Manual Accrual Adjustments for Customer Rebate Programs | F20: 24D | G20: 26B | H20: Wave3 - Complex Pages | I20: 26C | J20: Manage Customer Manual Adjustments (CJM_MANAGE_CUSTOMER_MANUAL_ADJUSTMENTS_PRIV), View Customer Manual Adjustments (CJM_VIEW_CUSTOMER_MANUAL_ADJUSTMENTS_PRIV) | L20: Use the Opt In UI to enable this feature. | M20: OPT IN+Role Setup | O20: TBD | P20: Customer Rebate Work Area
A21: 20 | B21: Order Management | C21: Pricing | D21: Redwood: Apply Pricing Promotions According to Pricing Strategies and Payment Terms | F21: 24D | G21: 26B | H21: Wave3 - Complex Pages | I21: 26C | J21: Manage Draft Pricing Promotions (QP_MANAGE_DRAFT_PRICING_PROMOTIONS) Manage Pricing Promotions (QP_MANAGE_PRICING_PROMOTIONS) View Pricing Promotions (QP_VIEW_PRICING_PROMOTIONS) Activate Pricing Promotions (QP_ APPROVE_PRICING_PROMOTIONS) Manage Dynamic Rules (QP_MANAGE_DYNAMIC_RULES) | L21: This is a new feature not available on classic UI | M21: OPT IN | N21: Y | O21: Mukesh Panwar | P21: Pricing Promotions
A22: 21 | B22: Order Management | C22: Pricing | D22: Redwood: Copy and Delete Pricing Promotions | F22: 24D | G22: 26B | H22: Wave3 - Complex Pages | I22: 26C | J22: Manage Promotions (QP_MANAGE_PROMOTIONS) | L22: This is a new feature not available on classic UI | M22: OPT IN | N22: Y | O22: Mukesh Panwar | P22: Pricing Promotions
A23: 22 | B23: Order Management | C23: Pricing | D23: Redwood: Define Tiered Adjustments on Rate Plan Charges | F23: 24D | G23: 26B | H23: Wave3 - Complex Pages | I23: 26C | J23: Manage Price Lists (QP_MANAGE_PRICE_LISTS) Manage In-Progress Price Lists (QP_MANAGE_IN_PROGRESS_PRICE_LISTS) View Price Lists (QP_VIEW_PRICE_LISTS) Approve Price Lists QP_APPROVE_PRICE_LISTS | L23: This is a new feature not available on classic UI | M23: OPT IN+Role Setup | N23: Y | O23: Mukesh Panwar | P23: Price List
A24: 23 | B24: Order Management | C24: Pricing | D24: Create Pricing Promotions for Sales Orders Using Redwood Pages | F24: 24C | G24: 26A | H24: Wave3 - Complex Pages | I24: 26C | J24: Manage Draft Pricing Promotions (QP_MANAGE_DRAFT_PRICING_PROMOTIONS) Manage Pricing Promotions (QP_MANAGE_PRICING_PROMOTIONS) View Pricing Promotions (QP_VIEW_PRICING_PROMOTIONS) Activate Pricing Promotions (QP_ APPROVE_PRICING_PROMOTIONS) Manage Dynamic Rules (QP_MANAGE_DYNAMIC_RULES) | L24: This is a new feature not available on classic UI | M24: OPT IN+Role Setup | N24: Y | O24: Mukesh Panwar | P24: Pricing Promotions
A25: 24 | B25: Order Management | C25: Channel Revenue Management | D25: Add Notes for Customer Programs and Claims in Redwood Pages | F25: 23C | G25: 25B | H25: Wave3 - Complex Pages | I25: 26C | J25: Manage Customer Programs (CJM_MANAGE_CUSTOMER_PROGRAMS_PRIV) Manage Customer Claims (CJM_MANAGE_CUSTOMER_CLAIMS_PRIV) View Only Activity (ZMM_VIEW_ONLY_ACTIVITY_PRIV) | L25: Use the Opt In UI to enable this feature. | M25: OPT IN+Role Setup | O25: TBD | P25: Customer Rebate Work Area
A26: 25 | B26: Order Management | C26: Channel Revenue Management | D26: Improve Usability of Claim Pages in Redwood | F26: 23C | G26: 25B | H26: Wave3 - Complex Pages | I26: 26C | J26: Manage Customer Claims (CJM_MANAGE_CUSTOMER_CLAIMS_PRIV) Create Customer Claims (CJM_CREATE_CUSTOMER_CLAIMS_PRIV) View Customer Claims (CJM_VIEW_CUSTOMER_CLAIMS_PRIV) | L26: Use the Opt In UI to enable this feature. | M26: OPT IN+Role Setup | O26: TBD | P26: Customer Claims Work Area
A27: 26 | B27: Order Management | C27: Channel Revenue Management | D27: Update and Settle Multiple Claims Using Redwood Pages | F27: 23C | G27: 25B | H27: Wave3 - Complex Pages | I27: 26C | J27: Manage Customer Claims (CJM_MANAGE_CUSTOMER_CLAIMS_PRIV) View Only Activity (ZMM_VIEW_ONLY_ACTIVITY_PRIV) | L27: Use the Opt In UI to enable this feature. | M27: OPT IN+Role Setup | O27: TBD | P27: Customer Claims Work Area
A28: 27 | B28: Order Management | C28: Channel Revenue Management | D28: Manage Deduction Claims Using Redwood Pages | F28: 23B | G28: 26A | H28: Wave3 - Complex Pages | I28: 25C | J28: No additional roles needed to access redwood pages if you already have access to Deductions and Settlement in 23B. Add reference data set access to existing Channel Claim Manager users, in addition to their existing business unit data access. | L28: Use the Opt In UI to enable this feature. | M28: OPT IN+Role Setup | O28: TBD | P28: Customer Claims Work Area
A29: 28 | B29: Procurement | C29: Sourcing | D29: Redwood: Respond to Simple Negotiations in Supplier Portal | F29: 24D | G29: 26A | H29: Wave1 - Simple Pages | I29: 26B | J29: Create Supplier Negotiation Response (PON_CREATE_SUPPLIER_NEGOTIATION_RESPONSE_PRIV) Edit Supplier Negotiation Response (PON_EDIT_SUPPLIER_NEGOTIATION_RESPONSE_PRIV) | M29: Log Service Request | N29: Y | O29: Karthik Gopal | P29: Requirements
A30: 29 | B30: Procurement | C30: Sourcing | D30: Redwood: Use Enhanced Negotiation Search in Supplier Portal | F30: 24D | G30: 26A | H30: Wave1 - Simple Pages | I30: 26B | J30: View Supplier Negotiation as Supplier (PON_VIEW_SUPPLIER_NEGOTIATION_SUPPLIER_FACING_PRIV) | M30: OPT IN | N30: Y | O30: Ashoka Veerabhadrappa | P30: negotiation in supplier portal
A31: 30 | B31: Procurement | C31: Sourcing | D31: Redwood: Use New Buyer Experience for Negotiation Messages | F31: 24D | G31: 25C | H31: Wave1 - Simple Pages | I31: 26B | J31: View Supplier Negotiation Online Message (PON_VIEW_ONLINE_MESSAGE_PRIV) Create Supplier Negotiation Online Message (PON_CREATE_ONLINE_MESSAGE_PRIV) Reply Supplier Negotiation Online Message (PON_REPLY_ONLINE_MESSAGE_PRIV) | M31: OPT IN+ Profile Option | N31: Y | O31: Ashoka Veerabhadrappa | P31: negotiation Messages
A32: 31 | B32: Procurement | C32: Sourcing | D32: Redwood: Use New Supplier Experience for Negotiation Messages | F32: 24D | G32: 26A | H32: Wave1 - Simple Pages | I32: 26B | J32: View Supplier Negotiation Online Message as Supplier (PON_VIEW_ONLINE_MESSAGE_SUPPLIER_FACING_PRIV) Create Supplier Negotiation Online Message as Supplier (PON_CREATE_ONLINE_MESSAGE_SUPPLIER_FACING_PRIV) Reply Supplier Negotiation Online Message as Supplier (PON_REPLY_ONLINE_MESSAGE_SUPPLIER_FACING_PRIV) | M32: OPT IN | N32: Y | O32: Ashoka Veerabhadrappa | P32: negotiation Messages
A33: 32 | B33: Procurement | C33: Supplier Model | D33: Redwood: Next Generation User Experience for Supplier Registration | F33: 24D | G33: 25C | H33: Wave1 - Simple Pages | I33: 25C | M33: OPT IN | N33: Y | O33: Ashoka Veerabhadrappa | P33: Supplier Registration UI
A34: 33 | B34: Procurement | C34: Supplier Qualification Management | D34: Redwood: Use Questionnaires in Internal Supplier Registration | F34: 24D | G34: 25C | H34: Wave2 - Modarate Pages | J34: POZ_SUBMIT_SUPPLIER_REGISTRATION_PRIV | L34: Opt in : Redwood: Next Generation User Experience for Supplier Registration | M34: OPT IN+Role Setup | N34: Y | O34: Ashoka Veerabhadrappa | P34: Supplier Registration UI
A35: 34 | B35: Procurement | C35: Common Procurement | D35: Extend Procurement Redwood Application Pages Using Visual Builder Studio | F35: 24C | G35: 25C | H35: Wave3 - Complex Pages | I35: 25C | M35: Visual Builder | O35: Pravalika G | P35: Vishual Builder | R35: Manufacturing and Product Life Cylce Management
A36: 35 | B36: Product Hub | C36: Product Development | D36: Redwood: Secure Manufacturers Using Access Control Lists | F36: 24D | G36: 26A | H36: Wave3 - Complex Pages | I36: 26C | J36: To configure manufacturer conditions using a filtered list: Use REST Service - Identity Integration (ASE_REST_SERVICE_ACCESS_IDENTITY_INTEGRATION_PRIV) Use Atom Feed - Employees Workspace (PER_ATOM_WORKSPACE_ACCESS_EMPLOYEES_PRIV) Manage HCM Lists (HRC_MANAGE_HCM_LISTS_PRIV) Human Capital Management Application Administrator (ORA_HRC_HUMAN_CAPITAL_MANAGEMENT_APPLICATION_ADMINISTRATOR_JOB) To configure teams, permission sets, and conditions: Monitor Product Development (ACA_MONITOR_PRODUCT_DEVELOPMENT_PRIV) Configure Access Control Teams, Permission Sets, and Conditions (EGP_ACCESS_CONTROL_TEAMS_PRIV) Use REST Service - Identity Integration (ASE_REST_SERVICE_ACCESS_IDENTITY_INTEGRATION_PRIV) Use Atom Feed - Employees Workspace (PER_ATOM_WORKSPACE_ACCESS_EMPLOYEES_PRIV) Manage HCM Lists (HRC_MANAGE_HCM_LISTS_PRIV) Manage HCM Rules (HRC_MANAGE_HCM_RULES_PRIV) Run Scheduled Processes (HEY_RUN_SCHEDULED_PROCESSES_PRIV) Manage Scheduled Processes(FND_MANAGE_SCHEDULED_PROCESSES_PRIV) To access the secured manufacturer data: Create Manufacturer (EGP_CREATE_MANUFACTURER_PRIV) View Manufacturers (EGP_VIEW_MANUFACTURER_PRIV) Manage Manufacturers (EGP_MANAGE_MANUFACTURER_PRIV) To access journeys setup and configure the roles in role hierarchy: Manage Journey (ORA_PER_MANAGE_JOURNEY_TEMPLATE) Manage Guided Journeys (ORA_PER_MANAGE_GUIDED_JOURNEYS) Use REST Service - Guided Journeys Read Only (ORA_PER_REST_SERVICE_ACCESS_GUIDED_JOURNEYS_RO) Use REST Service - Journey Categories List of Values (ORA_PER_REST_SERVICE_ACCESS_JOURNEY_CATEGORIES_LOV) To access business rules: Administer Sandbox (FND_ADMINISTER_SANDBOX_PRIV) | L36: Mandate version is not specified hence considering the mandate version as per Roadmap for PLM module which is 26B. | M36: OPT IN | N36: Y | O36: Miriam Chandni | P36: Product Management Work Area
A37: 36 | B37: Product Hub | C37: Product Lifecycle Management | D37: Redwood: Create and Manage Personalized Views in Product Management Search | F37: 24D | G37: 26A | H37: Wave1 - Simple Pages | I37: 26C | J37: View Product Management Search (EGP_VIEW_PRODUCT_MGT_SEARCH_PRIV) Get Search View REST (EGP_GET_SEARCH_VIEW_REST_PRIV) GET Product Management Index REST (EGP_GET_PM_INDEX_REST_PRIV) Manage Search View REST (EGP_MANAGE_SEARCH_VIEW_REST_PRIV) | L37: Mandate version is not specified hence considering the mandate version as per Roadmap for PLM module which is 26B. | M37: Role Setup+Profile option | N37: Y | O37: Miriam Chandni | P37: Product Information Management Work Area
A38: 37 | B38: Product Hub | C38: Product Lifecycle Management | D38: Redwood: Search Workflow Approvals | F38: 24D | G38: 25C | H38: Wave1 - Simple Pages | I38: 26C | J38: Users with view only access to changes require the following privileges: Access Product Management Change Search (EGO_VIEW_PRODUCT_MANAGEMENT_CHANGE_SEARCH) Get Search View REST (EGP_GET_SEARCH_VIEW_REST_PRIV) GET Product Management Index REST (EGP_GET_PM_INDEX_REST_PRIV) You should have Monitor Product Management Workflow Objects (ACA_MONITOR_PRODUCT_MANAGEMENT_WORFLOW_OBJECTS_PRIV) and one of the following privileges: For change orders: View Change Order (ACA_VIEW_CHANGE_ORDERS_PRIV) or Manage Change Orders (ACA_MANAGE_CHANGE_ORDERS_PRIV) For change requests: View Change Request (ACA_VIEW_CHANGE_REQUESTS_PRIV) Manage Change Requests (ACA_MANAGE_CHANGE_REQUESTS_PRIV) For problem reports: View Problem Report (ACA_VIEW_PROBLEM_REPORTS_PRIV) Manage Problem Report (ACA_MANAGE_PROBLEM_REPORT_PRIV) For corrective and preventive actions: View Corrective Action (ACA_VIEW_CORRECTIVE_ACTIONS_PRIV) Manage Corrective Action (ACA_MANAGE_CORRECTIVE_ACTION_PRIV) To configure the index: Manage Product Management Index (EGP_MANAGE_PM_INDEXES_PRIV) Manage Scheduled Job Definition (FND_MANAGE_SCHEDULED_JOB_DEFINITION_PRIV) Grant Search Framework Manager Permissions (FND_SEARCH_FWK_MGR_PRIV) To rebuild the index: Rebuild Product Management Indexes (EGO_REBUILD_PRODUCT_MGT_INDEXES_PRIV) To create search views: Manage Product Management View (EGP_MANAGE_PM_VIEWS_PRIV) Manage Scheduled Job Definition (FND_MANAGE_SCHEDULED_JOB_DEFINITION_PRIV) Grant Search Framework Manager Permissions (FND_SEARCH_FWK_MGR_PRIV) Access Product Development Configurations Using a REST Service (ACA_GET_PD_CONFIGURATIONS_REST_PRIV) Manage Search View REST (EGP_MANAGE_SEARCH_VIEW_REST_PRIV) Get View Available Attribute REST (EGP_VIEW_AVAIL_ATTR_REST_PRIV) | L38: Mandate version is not specified hence considering the mandate version as per Roadmap for PLM module which is 26B. | M38: Role Setup+Profile option | N38: Y | O38: Miriam Chandni | P38: Product Management Experience
A39: 38 | B39: Product Hub | C39: Product Lifecycle Management | D39: Redwood: Search Workflow History | F39: 24D | G39: 25C | H39: Wave1 - Simple Pages | I39: 26C | J39: Users with view only access to changes require the following privileges: Access Product Management Change Search (EGO_VIEW_PRODUCT_MANAGEMENT_CHANGE_SEARCH) View Change History (EGO_VIEW_CHANGE_HISTORY_PRIV) Get Search View REST (EGP_GET_SEARCH_VIEW_REST_PRIV) GET Product Management Index REST (EGP_GET_PM_INDEX_REST_PRIV) You should have Monitor Product Management Workflow Objects (ACA_MONITOR_PRODUCT_MANAGEMENT_WORFLOW_OBJECTS_PRIV) and one of the following privileges: For change orders: View Change Order (ACA_VIEW_CHANGE_ORDERS_PRIV) or Manage Change Orders (ACA_MANAGE_CHANGE_ORDERS_PRIV) For change requests: View Change Request (ACA_VIEW_CHANGE_REQUESTS_PRIV) Manage Change Requests (ACA_MANAGE_CHANGE_REQUESTS_PRIV) For problem reports: View Problem Report (ACA_VIEW_PROBLEM_REPORTS_PRIV) Manage Problem Report (ACA_MANAGE_PROBLEM_REPORT_PRIV) For corrective and preventive actions: View Corrective Action (ACA_VIEW_CORRECTIVE_ACTIONS_PRIV) Manage Corrective Action (ACA_MANAGE_CORRECTIVE_ACTION_PRIV) To configure the index: Manage Product Management Index (EGP_MANAGE_PM_INDEXES_PRIV) Manage Scheduled Job Definition (FND_MANAGE_SCHEDULED_JOB_DEFINITION_PRIV) Grant Search Framework Manager Permissions (FND_SEARCH_FWK_MGR_PRIV) To rebuild the index: Rebuild Product Management Indexes (EGO_REBUILD_PRODUCT_MGT_INDEXES_PRIV) To create search views: Manage Product Management View (EGP_MANAGE_PM_VIEWS_PRIV) Manage Scheduled Job Definition (FND_MANAGE_SCHEDULED_JOB_DEFINITION_PRIV) Grant Search Framework Manager Permissions (FND_SEARCH_FWK_MGR_PRIV) Access Product Development Configurations Using a REST Service (ACA_GET_PD_CONFIGURATIONS_REST_PRIV) Manage Search View REST (EGP_MANAGE_SEARCH_VIEW_REST_PRIV) Get View Available Attribute REST (EGP_VIEW_AVAIL_ATTR_REST_PRIV) | L39: Mandate version is not specified hence considering the mandate version as per Roadmap for PLM module which is 26B. | M39: Role Setup+Profile option | N39: Y | O39: Miriam Chandni | P39: Product Management Experience
A40: 39 | B40: Product Hub | C40: Product Development | D40: Create, Edit, and Extend Manufacturers Using a Redwood Page | F40: 24B | G40: 25B | H40: Wave2 - Modarate Pages | I40: 26C | J40: To search for manufacturers using a Redwood page: Get Search View REST(EGP_GET_SEARCH_VIEW_REST_PRIV) To view only manufacturers: View Manufacturer (EGP_VIEW_MANUFACTURER_PRIV) To edit manufacturers: Manage Manufacturer (EGP_MANAGE_MANUFACTURER_PRIV) To create manufacturers: Create Manufacturer (EGP_CREATE_MANUFACTURER_PRIV) Manage Manufacturer (EGP_MANAGE_MANUFACTURER_PRIV) | K40: EGP_MANUFACTURER_REDWOOD_ENABLED | L40: Mandate version is not specified hence considering the mandate version as per Roadmap for PLM module which is 26B. | M40: Role Setup+Profile option | N40: Y | O40: Miriam Chandni | P40: Product Management Search
A41: 40 | B41: Product Hub | C41: Product Development & Product Hub Common | D41: Access Side Panel View of Item Data from Search Results Using a Redwood Page | F41: 24B | G41: 25D | H41: Wave1 - Simple Pages | I41: 26C | J41: To view the item search: View Product Management Search (EGP_VIEW_PRODUCT_MGT_SEARCH) View Item (EGP_VIEW_ITEM) Get Search View REST (EGP_GET_SEARCH_VIEW_REST_PRIV) Data Security: View Item Basic To view the item AML in Redwood: Manage Trading Partner Item (EGP_MANAGE_TRADING_PARTNER_ITEM_PRIV) View Trading Partner Item (EGP_VIEW_TRANDING_PARTNER_ITEM_PRIV) View Manufacturers (EGP_VIEW_MANUFACTURER_PRIV) Get Trading Partner Item Relationship Rest (EGI_GET_TPI_REL_REST_PRIV) To view the item pending changes in Redwood: Manage Change Orders (ACA_MANAGE_CHANGE_ORDERS_PRIV) Manage Change Requests (ACA_MANAGE_CHANGE_REQUESTS_PRIV) View Change Order (ACA_VIEW_CHANGE_ORDERS_PRIV) View Change Request (ACA_VIEW_CHANGE_REQUESTS_PRIV) Data Security: View Item Change Order (EGO_ENGINEERING_CHANGES_B) To view the quality issues, quality actions, problem reports and corrective actions: Manage Problem Report (ACA_MANAGE_PROBLEM_REPORT_PRIV) View Problem Report (ACA_VIEW_PROBLEM_REPORTS_PRIV) Manage Corrective Action (ACA_MANAGE_CORRECTIVE_ACTION_PRIV) View Corrective Action (ACA_VIEW_CORRECTIVE_ACTIONS_PRIV) Manage Quality Issue (ENQ_MANAGE_QUALITY_ISSUE_PRIV) View Quality Issue (ENQ_VIEW_QUALITY_ISSUE_PRIV) Manage Quality Action (ENQ_MANAGE_QUALITY_ACTION_PRIV) View Quality Action (ENQ_VIEW_QUALITY_ACTION_PRIV) | L41: Mandate version is not specified hence considering the mandate version as per Roadmap for PLM module which is 26B. | M41: Role Setup+Profile option | N41: Y | O41: Miriam Chandni | P41: Product Management Search
A42: 41 | B42: Product Hub | C42: Product Development & Product Hub Common | D42: Access Side Panel View of Structure Component Data Using a Redwood Page | F42: 24B | G42: 25D | H42: Wave2 - Modarate Pages | I42: 26C | J42: To view the item structure in Redwood: View Product Management Search (EGP_VIEW_PRODUCT_MGT_SEARCH) View Item (EGP_VIEW_ITEM) Create Item Structure (EGP_CREATE_ITEM_STRUCTURE_PRIV) Get Search View REST (EGP_GET_SEARCH_VIEW_REST_PRIV) Data Security: View Item Basic To configure the index: Manage Product Management Index (EGP_MANAGE_PM_INDEXES) Manage Scheduled Job Definition (FND_MANAGE_SCHEDULED_JOB_DEFINITION_PRIV) Grant Search Framework Manager Permissions (FND_SEARCH_FWK_MGR_PRIV) Get Item Index Available Attributes REST (EGP_GET_PM_ITEM_AVAIL_REST_PRIV) To rebuild the index: Rebuild Product Management Indexes (EGO_REBUILD_PRODUCT_MGT_INDEXES) To create the structure view: Manage Product Management View (EGP_MANAGE_PM_VIEWS) Manage Scheduled Job Definition (FND_MANAGE_SCHEDULED_JOB_DEFINITION_PRIV) Grant Search Framework Manager Permissions (FND_SEARCH_FWK_MGR_PRIV) Access Product Development Configurations Using a REST Service (ACA_GET_PD_CONFIGURATIONS_REST_PRIV) Manage Search View REST (EGP_MANAGE_SEARCH_VIEW_REST_PRIV) Get View Available Attribute REST (EGP_VIEW_AVAIL_ATTR_REST_PRIV) To view the quality issues, quality actions, problem report, and corrective action in the side panel: Manage Problem Report (ACA_MANAGE_PROBLEM_REPORT_PRIV) Manage Corrective Action (ACA_MANAGE_CORRECTIVE_ACTION_PRIV) Manage Quality Issue (ENQ_MANAGE_QUALITY_ISSUE_PRIV) Manage Quality Action (ENQ_MANAGE_QUALITY_ACTION_PRIV) | L42: Mandate version is not specified hence considering the mandate version as per Roadmap for PLM module which is 26B. | M42: Role Setup+Profile option | N42: Y | O42: Miriam Chandni | P42: Product Management Search
A43: 42 | B43: Quality Management | C43: Quality Inspection Management | D43: Manage Inspection Levels using the Redwood Experience | F43: 24C | G43: 26A | H43: Wave1 - Simple Pages | I43: 26C | J43: View Product Management Search (EGP_VIEW_PRODUCT_MGT_SEARCH_PRIV) Get Search View Rest (EGP_GET_SEARCH_VIEW_REST_PRIV) GET Product Management Index REST (EGP_GET_PM_INDEX_REST_PRIV) | K43: ORA_QA_INSPECTION_LEVEL_REDWOOD_ENABLED | M43: Role Setup+Profile option | N43: Y | O43: Ashoka Veerabhadrappa | P43: Quality Management Landing Page
A44: 43 | B44: Quality Management | C44: Quality Inspection Management | D44: Manage Inspection Plans using the Redwood Experience | F44: 24C | G44: 26A | H44: Wave1 - Simple Pages | I44: 26C | J44: Manage Item Source System (EGI_MANAGE_ITEM_SOURCE_SYSTEM_PRIV) | K44: ORA_QA_INSPECTION_PLAN_REDWOOD_ENABLED | M44: Role Setup+Profile option | N44: Y | O44: Ashoka Veerabhadrappa | P44: Quality Management Landing Page
A45: 44 | B45: Quality Management | C45: Quality Inspection Management | D45: Perform Quality Inspections using the Redwood Experience | F45: 24C | G45: 25B | H45: Wave1 - Simple Pages | I45: 26C | J45: Manage Item Delete Group (EGP_MANAGE_ITEM_DELETE_GROUP_PRIV) Access Item Structure Data Using a REST Service (EGP_GET_ITEM_STRUCTURE_REST_PRIV) Access Change Order Using a REST Service (ACA_GET_CHANGE_REST_PRIV) Manage Delete Group Rest (EGP_DG_REST_PRIV) GET Product Management Index REST (EGP_GET_PM_INDEX_REST_PRIV) Get Search View REST (EGP_GET_SEARCH_VIEW_REST_PRIV) Grant Search Framework Manager Permissions (FND_SEARCH_FWK_MGR_PRIV) View Product Management Search (EGP_VIEW_PRODUCT_MGT_SEARCH_PRIV) | K45: ORA_QA_INSPECTIONS_REDWOOD_ENABLED | M45: Role Setup+Profile option | N45: Y | O45: Yoga Gopalakrishnan | P45: Quality Inspections Landing page
A46: 45 | B46: Quality Management | C46: Quality Inspection Management | D46: Manage Inspection Characteristics in Redwood Pages | F46: 24B | G46: 26B | H46: Wave1 - Simple Pages | I46: 26C | J46: To search for manufacturers using a Redwood page: Get Search View REST(EGP_GET_SEARCH_VIEW_REST_PRIV) To view only manufacturers: View Manufacturer (EGP_VIEW_MANUFACTURER_PRIV) To edit manufacturers: Manage Manufacturer (EGP_MANAGE_MANUFACTURER_PRIV) To create manufacturers: Create Manufacturer (EGP_CREATE_MANUFACTURER_PRIV) Manage Manufacturer (EGP_MANAGE_MANUFACTURER_PRIV) | K46: ORA_QA_CHARACTERISTIC_REDWOOD_ENABLED | M46: Role Setup+Profile option | N46: Y | O46: Yoga Gopalakrishnan | P46: Quality Inspections Landing page
A47: 46 | B47: SCM Common Components | C47: SCM Common Components | D47: Create Guided Journeys for Redwood Pages | F47: 24C | G47: 26A | H47: Wave1 - Simple Pages | I47: 26B | J47: Manage Publication Maps (EGI_MANAGE_PUBLICATION_MAPS_PRIV) Manage Publishable Attributes REST (EGI_MANAGE_PUBLISHABLE_ATTR_REST_PRIV) Manage Publication Maps REST (EGI_MANAGE_PUBLICATION_MAPS_REST_PRIV) | M47: Visual Builder | O47: Pravalika G | P47: Visual Builder
A48: 47 | B48: Inventory Management | C48: Cost Management | D48: Redwood: Create and Update Standard Costs Using a New User Experience | F48: 25A | G48: 25B | H48: Wave2 - Modarate Pages | I48: 26A | J48: To search for manufacturers using a Redwood page: Get Search View REST(EGP_GET_SEARCH_VIEW_REST_PRIV) To view manufacturers: View Manufacturer (EGP_VIEW_MANUFACTURER_PRIV) To edit manufacturers: Manage Manufacturer (EGP_MANAGE_MANUFACTURER_PRIV) To create manufacturers: Create Manufacturer (EGP_CREATE_MANUFACTURER_PRIV) Manage Manufacturer (EGP_MANAGE_MANUFACTURER_PRIV) | K48: On the Manage Administrator Profile Values page, search for and select the ORA_CST_STANDARD_COSTS_REDWOOD_ENABLED profile option code. In the Profile Values section, set the Site level to Yes. The default value is No. Click Save and Close. Changes in the profile value will affect users the next time they sign in. Yes = enables the feature No = disables the feature | M48: Role Setup+Profile option | N48: Y | O48: Miriam Chandni | P48: Cost Accounting Work Area
A49: 48 | B49: Inventory Management | C49: Cost Management | D49: Redwood: Compare Standard Costs Using a New User Experience | F49: 25A | G49: 25B | H49: Wave2 - Modarate Pages | I49: 26A | J49: Access Clipboard (ACA_ACCESS_CLIPBOARD_PRIV) | K49: On the Manage Administrator Profile Values page, search for and select the ORA_CST_COMPARE_STD_COSTS_REDWOOD_ENABLED profile option code. In the Profile Values section, set the Site level to Yes. The default value is No. Click Save and Close. Changes in the profile value will affect users the next time they sign in. Yes = enables the feature No = disables the feature | M49: Role Setup+Profile option | N49: Y | O49: Miriam Chandni | P49: Cost Accounting Work Area
A50: 49 | B50: Supply Chain Collaboration | C50: Supply Chain Collaboration | D50: Manage Supplier On-Hand Quantities Using a Redwood Page | F50: 24C | G50: 26A | H50: Wave1 - Simple Pages | I50: 26C | J50: To view the item structure on the Redwood page: View Product Management Search (EGP_VIEW_PRODUCT_MGT_SEARCH) View Item (EGP_VIEW_ITEM) Create Item Structure (EGP_CREATE_ITEM_STRUCTURE_PRIV) Get Search View REST (EGP_GET_SEARCH_VIEW_REST_PRIV) Data Security: View Item Basic Access Item Structure Data Using a REST Service (EGP_GET_ITEM_STRUCTURE_REST_PRIV) Access Structure Attributes for Indexing Using REST (EGP_GET_PM_STRUCTURE_AVAIL_REST_PRIV) | M50: OPT IN+Role Setup | N50: Y | O50: Veeranarayana Swamy | P50: Supplier On-Hand Quantities
A51: 50 | B51: Supply Chain Collaboration | C51: Supply Chain Collaboration | D51: Manage Supply Collaboration Network Using a Redwood Page | F51: 24C | G51: 25D | H51: Wave1 - Simple Pages | I51: 26C | J51: You should have Monitor Product Management Workflow Objects (ACA_MONITOR_PRODUCT_MANAGEMENT_WORFLOW_OBJECTS_PRIV) and one of the following privileges: For change orders: View Change Order (ACA_VIEW_CHANGE_ORDERS_PRIV) or Manage Change Orders (ACA_MANAGE_CHANGE_ORDERS_PRIV) For change requests: View Change Request (ACA_VIEW_CHANGE_REQUESTS_PRIV) or Manage Change Requests (ACA_MANAGE_CHANGE_REQUESTS_PRIV) For problem reports: View Problem Report (ACA_VIEW_PROBLEM_REPORTS_PRIV) or Manage Problem Report (ACA_MANAGE_PROBLEM_REPORT_PRIV) For corrective and preventive actions: View Corrective Action (ACA_VIEW_CORRECTIVE_ACTIONS_PRIV) or Manage Corrective Action (ACA_MANAGE_CORRECTIVE_ACTION_PRIV) | M51: OPT IN+Role Setup | O51: Venkat | P51: Supply Collaboration Network
A52: 51 | B52: Supply Chain Collaboration | C52: Supply Chain Collaboration | D52: Manage Upload Supply Data Using a Redwood Page | F52: 24C | G52: 26A | H52: Wave1 - Simple Pages | I52: 26C | J52: You should have Monitor Product Management Workflow Objects (ACA_MONITOR_PRODUCT_MANAGEMENT_WORFLOW_OBJECTS_PRIV) and one of the following privileges: For change orders: View Change Order (ACA_VIEW_CHANGE_ORDERS_PRIV) or Manage Change Orders (ACA_MANAGE_CHANGE_ORDERS_PRIV) For change requests: View Change Request (ACA_VIEW_CHANGE_REQUESTS_PRIV) or Manage Change Requests (ACA_MANAGE_CHANGE_REQUESTS_PRIV) For problem reports: View Problem Report (ACA_VIEW_PROBLEM_REPORTS_PRIV) or Manage Problem Report (ACA_MANAGE_PROBLEM_REPORT_PRIV) For corrective and preventive actions: View Corrective Action (ACA_VIEW_CORRECTIVE_ACTIONS_PRIV) or Manage Corrective Action (ACA_MANAGE_CORRECTIVE_ACTION_PRIV) Users who are assigned a configured job role that contains these privileges can access assigned notifications: For Item Change Orders: EGO_VIEW_ITEM_CHANGE_ORDER_PRIV For New Item Request: EGO_VIEW_NEW_ITEM_REQUEST_PRIV | M52: OPT IN+Role Setup | O52: Venkat | P52: Upload Supply Data
A53: 52 | B53: Supply Chain Collaboration | C53: Supply Chain Collaboration | D53: Manage Collaboration Planners Using a Redwood Page | F53: 24B | G53: 25B | H53: Wave1 - Simple Pages | I53: 26C | J53: Landing Page (ORA_EGP_LANDING_PAGE_DUTY) contains: View Item Redwood (ORA_EGP_REDWOOD_VIEW_ITEM_DUTY) Product Search (ORA_EGI_PRODUCT_SEARCH_DUTY) Access Object Tag Set Repository (ACA_ACCESS_OBJECT_TAG_SETS_PRIV) Access Object Tags Repository (ACA_ACCESS_OBJECT_TAGS_PRIV) Access Product Management Landing Page (EGP_ACCESS_LANDING_PAGE_PRIV) Manage Landing Page Layout (EGP_MANAGE_LANDING_PAGE_LAYOUT_PRIV) Access Clipboard (ACA_ACCESS_CLIPBOARD_PRIV) Access HCM Common Components (HRC_ACCESS_HCM_COMMON_COMPONENTS_PRIV) Manage Search Consumer Applications Rest (EGP_MANAGE_SEARCH_CONS_REST_PRIV) | M53: OPT IN+Role Setup | O53: Venkat | P53: Collaboration Planners
A54: 53 | B54: Supply Chain Collaboration | C54: Supply Chain Collaboration | D54: Manage Collaboration Plans Using a Redwood Page | F54: 24B | G54: 25B | H54: Wave1 - Simple Pages | I54: 26C | M54: OPT IN+Role Setup | O54: Venkat | P54: Collaboration Plans
A55: 54 | B55: Supply Chain Collaboration | C55: Supply Chain Collaboration | D55: Manage VMI Analysts Using a Redwood Page | F55: 24B | G55: 25B | H55: Wave1 - Simple Pages | I55: 26C | J55: View Item Redwood Items (EGP_VIEW_REDWOOD_ITEM_PRIV) View Item Redwood Attachments (EGP_VIEW_REDWOOD_ITEM_ATTACHMENT_PRIV) View Item Redwood Associations (EGP_VIEW_REDWOOD_ITEM_ASSOCIATION_PRIV) View Item Redwood Structures (EGP_VIEW_REDWOOD_ITEM_STRUCTURE_PRIV) View Item Redwood Changes (EGP_VIEW_REDWOOD_ITEM_CHANGE_PRIV) View Item Redwood Item Categories (EGP_VIEW_REDWOOD_ITEM_CATEGORIES_PRIV) View Item Redwood Relationships (EGP_VIEW_REDWOOD_ITEM_RELATIONSHIP_PRIV) View Item Redwood Quality (EGP_VIEW_REDWOOD_ITEM_QUALITY_PRIV) Supply Chain Common View Web Service (ORA_RCS_SCM_COMMON_VIEW_WEB_SERVICE_DUTY) Enter Trading Community Organization Information (HZ_ENTER_TRADING_COMMUNITY_ORGANIZATION_INFORMATION_PRIV) Get Failure Condition Event Codes (MNT_GET_FAILURE_CONDITION_EVENT_CODE_BY_SERVICE_PRIV) Get Item Attribute Control REST (EGP_ITEM_ATTRIBUTE_CONTROL_READ_PRIV) Get Item Lifecycle Phases Read Rest (EGP_ITEM_LIFECYCLE_PHASES_READ_REST_PRIV) Get Item Status REST (EGP_ITEM_STATUSES_READ_PRIV) Get New Item Request Rest (EGI_NEW_ITEM_REQUEST_REST_PRIV) Get Template REST (EGP_TEMPLATE_READ_PRIV) Manage Material Planner (MSP_MANAGE_MATERIAL_PLANNER_PRIV) Manage Subscription Setup (OSS_MANAGE_SUBSCRIPTION_SETUP_PRIV) Remove Trading Community Organization (HZ_REMOVE_TRADING_COMMUNITY_ORGANIZATION_PRIV) Set Up Receivables Payment Terms (AR_SET_UP_RECEIVABLES_PAYMENT_TERM_PRIV) Update Trading Community Organization (HZ_UPDATE_TRADING_COMMUNITY_ORGANIZATION_PRIV) Verify Tax Configuration (ZX_VERIFY_TAX_CONFIGURATION_PRIV) View Procurement Buyers List of Values using REST Service (PO_VIEW_BUYER_LOV_REST_SERVICE_PRIV) View Purchasing Hazard Classes List of Values using REST Service (PO_VIEW_HAZARD_CLASSES_LOV_REST_SERVICE_PRIV) View Purchasing UN Numbers List of Values using REST Service (PO_VIEW_UNNUMBER_LOV_REST_SERVICE_PRIV) View Trading Community Organization (HZ_VIEW_TRADING_COMMUNITY_ORGANIZATION_PRIV) View Trading Community Person (HZ_VIEW_TRADING_COMMUNITY_PERSON_PRIV) Manage Item Redwood Items (EGP_MANAGE_REDWOOD_ITEM_PRIV) Manage Item Redwood Attachments (EGP_MANAGE_REDWOOD_ITEM_ATTACHMENT_PRIV) Manage Item Redwood Associations (EGP_MANAGE_REDWOOD_ITEM_ASSOCIATION_PRIV) Manage Item Redwood Item Categories (EGP_MANAGE_REDWOOD_ITEM_CATEGORY_PRIV) Manage Item Redwood Relationships (EGP_MANAGE_REDWOOD_ITEM_RELATIONSHIP_PRIV) Manage Item Redwood Structures (EGP_MANAGE_REDWOOD_ITEM_STRUCTURE_PRIV) Get New Item Request Rest (EGI_NEW_ITEM_REQUEST_REST_PRIV) Manage Item Status REST (EGP_ITEM_STATUSES_PRIV) | M55: OPT IN+Role Setup | O55: Venkat | P55: VMI Analytics
A56: 55 | B56: Supply Chain Collaboration | C56: Supply Chain Collaboration | D56: Specify Aggregation Schedule Using a Redwood Page | F56: 24B | G56: 26A | H56: Wave1 - Simple Pages | I56: 26C | J56: To access the item on Redwood page: View Item Redwood Items (EGP_VIEW_REDWOOD_ITEM_PRIV) Manage Item Redwood Items (EGP_MANAGE_REDWOOD_ITEM_PRIV) To create, manage, or view the item structure on the Redwood page: Create Item Structure (EGP_CREATE_ITEM_STRUCTURE_PRIV) Manage Item Redwood Structures (EGP_MANAGE_REDWOOD_ITEM_STRUCTURE_PRIV) View Item Redwood Structures (EGP_VIEW_REDWOOD_ITEM_STRUCTURE_PRIV To manage change order on Redwood page: Manage Change Orders (ACA_MANAGE_CHANGE_ORDERS_PRIV) | M56: OPT IN+Role Setup | O56: Venkat | P56: Select Aggregation Schedule
A57: 56 | B57: Inventory Management | C57: Inventory Management | D57: Manage Subinventories and Locators on Redesigned Pages | F57: 24A | G57: 26A | H57: Wave2 - Modarate Pages | I57: 26A | K57: Get Item Rest (EGP_GET_ITEM_REST_PRIV) Manage Inventory Status (INV_MANAGE_INVENTORY_STATUS_PRIV) Manage Subinventory and Locator (INV_MANAGE_SUBINVENTORY_AND_LOCATOR_PRIV) Manage Unit of Measure Usage (INV_MANAGE_UNIT_OF_MEASURE_USAGE_PRIV) View Inventory On-Hand Balance Web Service (INV_VIEW_INVENTORY_ONHAND_BALANCE_WEB_SERVICE_PRIV) View Subinventory and Locator List of Values by Web Service (INV_VIEW_SUBINVENTORY_LOCATOR_LOV_WEB_SERVICE_PRIV) View Inventory Organizations List of Values by Web Service (RCS_VIEW_INV_ORG_LOV_WEB_SERVICE_PRIV) View Units of Measure List of Values by Web Service (RCS_VIEW_UNITS_OF_MEASURE_LOV_WEB_SERVICE_PRIV) | M57: OPT IN | N57: Y | O57: Miriam Chandni | P57: Inventory Management work area
A58: 57 | B58: Inventory Management | C58: Inventory Management | D58: Manage Item Transaction Defaults on a Redesigned Page | F58: 24B | G58: 26A | H58: Wave2 - Modarate Pages | I58: 26A | J58: View Item Redwood Items (EGP_VIEW_REDWOOD_ITEM_PRIV) Manage Item Supplier Associations (EGP_MANAGE_REDWOOD_ITEM_SUPPLIER_ASSOCIATION_PRIV) | M58: Role Setup+Profile option | N58: Y | O58: Miriam Chandni | P58: Inventory Management work area
A59: 58 | B59: Procurement | C59: Purchasing | D59: Search for Purchase Agreements Using a Redwood Page | F59: 24B | G59: 26A | H59: Wave1 - Simple Pages | I59: 26A | J59: View Item Redwood Items (EGP_VIEW_REDWOOD_ITEM_PRIV) Manage Item Redwood Items (EGP_MANAGE_REDWOOD_ITEM_PRIV) | K59: Manage Administrator Profile Values > ORA_PO_MANAGE_AGREEMENTS_REDWOOD_ENABLED = Y | L59: 1. Submit the ESS job to create index definition and perform initial ingest to OSCS scheduled process with this index name: Purchase Agreements: fa-prc-pa 2. We can Confiure Guided Journey 3. We can use VBCS to hide or show field | M59: OPT IN+ Profile Option | N59: Y | O59: Karthik Gopal | P59: Purchase Agreements | R59: Manufacturing and Product Life Cylce Management
A60: 59 | B60: Procurement | C60: Responsive Self Service Procurement | D60: Create Multiple Distributions on Requisitions | F60: 24B | G60: 26A | H60: Wave2 - Modarate Pages | I60: 25C | J60: For items: View Item Redwood (ORA_EGP_REDWOOD_VIEW_ITEM_DUTY) For landing page: Access Product Management Landing Page (EGP_ACCESS_LANDING_PAGE_PRIV) Access Clipboard (ACA_ACCESS_CLIPBOARD_PRIV) Access HCM Common Components (HRC_ACCESS_HCM_COMMON_COMPONENTS_PRIV) For manufacturers: View Manufacturer (EGP_VIEW_MANUFACTURER_PRIV) For change orders: View Change Order (ACA_VIEW_CHANGE_ORDERS_PRIV) or Manage Change Orders (ACA_MANAGE_CHANGE_ORDERS_PRIV) | M60: Role Setup+Profile option | N60: Y | O60: Pragyan Dash | P60: Requisition Line | R60: Manufacturing and Product Life Cylce Management
A61: 60 | B61: Procurement | C61: Responsive Self Service Procurement | D61: View Requisition Lifecycle Information | F61: 24B | G61: 25D | H61: Wave2 - Modarate Pages | I61: 25C | J61: Product Management Search Page Product Search (ORA_EGI_PRODUCT_SEARCH_DUTY) and Product Search (ORA_EGI_PRODUCT_SEARCH_HCM_DUTY) duty roles contain the following privileges: Access Product Development Configurations Using a REST Service (ACA_GET_PD_CONFIGURATIONS_REST_PRIV) GET Product Management Index REST (EGP_GET_PM_INDEX_REST_PRIV) Get Item Index Available Attributes REST (EGP_GET_PM_ITEM_AVAIL_REST_PRIV) Get Search View REST (EGP_GET_SEARCH_VIEW_REST_PRIV) Manage Search View REST (EGP_MANAGE_SEARCH_VIEW_REST_PRIV) Manage System Searches (HRC_MANAGE_SYSTEM_SEARCHES_PRIV) Use REST Service - Saved Searches (HRC_REST_SERVICE_ACCESS_SAVED_SEARCHES_PRIV) View Product Management Search (EGP_VIEW_PRODUCT_MGT_SEARCH_PRIV) Access HCM Common Components (HRC_ACCESS_HCM_COMMON_COMPONENTS_PRIV) Manage Search Consumer Applications Rest (EGP_MANAGE_SEARCH_CONS_REST_PRIV) | M61: OPT IN | N61: Y | O61: Karthik Gopal | P61: Requisition Line
A62: 61 | B62: Procurement | C62: Responsive Self Service Procurement | D62: View Requisition Document History | F62: 24B | G62: 25D | H62: Wave1 - Simple Pages | I62: 25C | J62: To search for manufacturers using a Redwood page: Access Product Development Configurations Using a REST Service(ACA_GET_PD_CONFIGURATIONS_REST_PRIV) Access Product Management Landing Page(EGP_ACCESS_LANDING_PAGE_PRIV) Get Search View REST(EGP_GET_SEARCH_VIEW_REST_PRIV) Manage Product Management Data Security EGO_MGT_PRODUCT_MGT_DATA_SECURITY_PRIV) View Feature States Value by Web Service(RCS_VIEW_FEATURE_STATES_WEB_SERVICE_PRIV) Get View Available Attribute REST (EGP_VIEW_AVAIL_ATTR_REST_PRIV) Grant Search Framework Manager Permissions (FND_SEARCH_FWK_MGR_PRIV) To view only manufacturers: View Manufacturer (EGP_VIEW_MANUFACTURER_PRIV) To edit manufacturers: Manage Item Manufacturer (EGP_MANAGE_ITEM_MANUFACTURER_PRIV) Manage Manufacturers (EGP_MANAGE_MANUFACTURER_PRIV) To create manufacturers: Create Manufacturer (EGP_CREATE_MANUFACTURER_PRIV) Manage Manufacturer (EGP_MANAGE_MANUFACTURER_PRIV) | M62: Role Setup+Profile option | N62: Y | O62: Pragyan Dash | P62: Requisition Header
A63: 62 | B63: Procurement | C63: Responsive Self Service Procurement | D63: Assign Additional Supplier Contact Emails for Catalog Item-Based Requisitions | F63: 24B | G63: 25D | H63: Wave2 - Modarate Pages | I63: 25C | J63: Manage Requisition with the Responsive Self Service Procurement Application (POR_MANAGE_REQ_WITH_PWA_PRIV). | K63: ORA_POR_RESP_DISABLE_CONTACT_AUTOSOURCING | M63: OPT IN+Profile option+Role Setup | N63: Y | O63: Karthik Gopal | P63: Requisition Line
A64: 63 | B64: Procurement | C64: Responsive Self Service Procurement | D64: Change Description for Agreement Based Items During Shopping | F64: 24B | G64: 25D | H64: Wave2 - Modarate Pages | I64: 25C | J64: Manage Requisition with the Responsive Self Service Procurement Application (POR_MANAGE_REQ_WITH_PWA_PRIV) | M64: OPT IN+Role Setup | N64: Y | O64: Pragyan Dash | P64: Requisition Line
A65: 64 | B65: Procurement | C65: Responsive Self Service Procurement | D65: Refine Requisition Search Using Filters | F65: 24B | G65: 25D | H65: Wave2 - Modarate Pages | I65: 25C | J65: Requisition Self Service Responsive Application User Duty (ORA_POR_REQUISITION_SELF_SERVICE_PWA_USER_DUTY) | M65: OPT IN+Role Setup | N65: Y | O65: Pragyan Dash | P65: My Requisition Search
A66: 65 | B66: Product Hub | C66: Product Hub | D66: Search Product Management Content Using the Redwood User Experience | F66: 24B | G66: 26C | H66: Wave1 - Simple Pages | I66: 26C | J66: View Product Management Search (EGP_VIEW_PRODUCT_MGT_SEARCH_PRIV) Get Search View Rest (EGP_GET_SEARCH_VIEW_REST_PRIV) GET Product Management Index REST (EGP_GET_PM_INDEX_REST_PRIV) | L66: Mandate version is not specified hence considering the mandate version as per Roadmap for PLM module which is 26B. | M66: OPT IN+Role Setup | N66: Y | O66: Karthik Gopal | P66: Product Management Search
A67: 66 | B67: Product Hub | C67: Product Hub | D67: Manage Spoke Systems Using the Redwood User Experience | F67: 24B | G67: 26C | H67: Wave1 - Simple Pages | I67: 26C | J67: Manage Item Source System (EGI_MANAGE_ITEM_SOURCE_SYSTEM_PRIV) | K67: ORA_EGI_SPOKE_SYSTEM_REDWOOD_PAGES_ENABLED | L67: Mandate version is not specified hence considering the mandate version as per Roadmap for PLM module which is 26B. | M67: Role Setup+Profile option | N67: Y | O67: Karthik Gopal | P67: Manage Spoke Systems
A68: 67 | B68: Product Hub | C68: Product Hub | D68: Manage Delete Groups Using the Redwood User Experience | F68: 24B | G68: 26C | H68: Wave1 - Simple Pages | I68: 26C | J68: Manage Item Delete Group (EGP_MANAGE_ITEM_DELETE_GROUP_PRIV) Access Item Structure Data Using a REST Service (EGP_GET_ITEM_STRUCTURE_REST_PRIV) Access Change Order Using a REST Service (ACA_GET_CHANGE_REST_PRIV) Manage Delete Group Rest (EGP_DG_REST_PRIV) GET Product Management Index REST (EGP_GET_PM_INDEX_REST_PRIV) Get Search View REST (EGP_GET_SEARCH_VIEW_REST_PRIV) Grant Search Framework Manager Permissions (FND_SEARCH_FWK_MGR_PRIV) View Product Management Search (EGP_VIEW_PRODUCT_MGT_SEARCH_PRIV) | K68: ORA_EGP_DELETE_GROUPS_REDWOOD_PAGES_ENABLED | L68: Mandate version is not specified hence considering the mandate version as per Roadmap for PLM module which is 26B. | M68: Role Setup+Profile option | N68: Y | O68: Karthik Gopal | P68: Manage Delete Groups
A69: 68 | B69: Inventory Management | C69: Inventory Management | D69: Manage Lots and Serial Numbers Using a Redwood Page | F69: 24C | G69: 26B | H69: Wave2 - Modarate Pages | I69: 26A | J69: Manage Lots and Serial Numbers Using Responsive Inventory Duty (ORA_INV_MANAGE_LOT_SERIAL_PWA_DUTY) | K69: ORA_INV_LOTS_AND_SERIAL_NUMBERS_REDWOOD_ENABLED | M69: Role Setup+Profile option | N69: Y | O69: Pragyan Dash | P69: Inventory Management work area
A70: 69 | B70: Inventory Management | C70: Inventory Management | D70: Create Multiple New Subinventories and Locators Simultaneously | F70: 24C | G70: 26B | H70: Wave2 - Modarate Pages | I70: 26A | J70: Configure Subinventory Using Responsive Inventory (ORA_INV_CONFIGURE_SUBINVENTORY_PWA_DUTY) | M70: OPT IN | N70: Y | O70: Pragyan Dash | P70: Subinventories page
A71: 70 | B71: Inventory Management | C71: Inventory Management | D71: Approve Count Sequences Using a Redwood Page | F71: 24C | G71: 26B | H71: Wave1 - Simple Pages | I71: 26A | J71: Approve Cycle Count Using Responsive Inventory Duty (ORA_INV_APPROVE_CYCLE_COUNT_PWA_DUTY) | K71: ORA_INV_CYCLE_COUNT_REDWOOD_ENABLED | M71: Role Setup+Profile option | N71: Y | O71: Pragyan Dash | P71: Cycle count Approvals
A72: 71 | B72: Inventory Management | C72: Inventory Management | D72: Create Outbound Shipment Requests Using a Redwood Page | F72: 24C | G72: 26B | H72: Wave2 - Modarate Pages | I72: 26A | J72: Create Outbound Shipment Request Using Responsive Shipping (ORA_WSH_CREATE_OUTBOUND_SHIPMENT_REQUEST_PWA_DUTY) | K72: ORA_WSH_PICK_WAVE_SHIPMENT_REQUEST_REDWOOD_PAGES_ENABLED | M72: Role Setup+Profile option | N72: Y | O72: Mukesh Panwar | P72: Outbound Shipment Request
A73: 72 | B73: Inventory Management | C73: Inventory Management | D73: Create Pick Waves Using a Redwood Page | F73: 24C | G73: 26B | H73: Wave2 - Modarate Pages | I73: 26A | J73: Create Pick Wave Using Responsive Shipping (ORA_WSH_CREATE_PICK_WAVE_PWA_DUTY) | K73: ORA_WSH_PICK_WAVE_SHIPMENT_REQUEST_REDWOOD_PAGES_ENABLED | M73: Role Setup+Profile option | N73: Y | O73: Mukesh Panwar | P73: New Pick Wave
A74: 1194 | B74: Product Lifecycle Management | C74: Product Development & Product Hub Common | D74: Analyze Structure Details in Level Structure View | E74: =VLOOKUP(D74,Sheet12!$A$2:$A$37,1,FALSE) -> #N/A | F74: 24C | H74: Wave3 - Complex Pages | J74: Users who are assigned a configured job role that contains these privileges can access this feature. To view the item structure in Redwood: View Product Management Search (EGP_VIEW_PRODUCT_MGT_SEARCH) View Item (EGP_VIEW_ITEM) Create Item Structure (EGP_CREATE_ITEM_STRUCTURE_PRIV) Get Search View REST(EGP_GET_SEARCH_VIEW_REST_PRIV) Data Security: View Item Basic Access Item Structure Data Using a REST Service (EGP_GET_ITEM_STRUCTURE_REST_PRIV) Access Structure Attributes for Indexing Using REST (EGP_GET_PM_STRUCTURE_AVAIL_REST_PRIV) To configure the index: Manage Product Management Index (EGP_MANAGE_PM_INDEXES) Manage Scheduled Job Definition (FND_MANAGE_SCHEDULED_JOB_DEFINITION_PRIV) Grant Search Framework Manager Permissions (FND_SEARCH_FWK_MGR_PRIV) Access Item Structure Data Using a REST Service (EGP_GET_ITEM_STRUCTURE_REST_PRIV) Access Structure Attributes for Indexing Using REST (EGP_GET_PM_STRUCTURE_AVAIL_REST_PRIV) GET Product Management Index REST (EGP_GET_PM_INDEX_REST_PRIV) Manage Product Management Index REST (EGP_MANAGE_PM_INDEX_REST_PRIV) To rebuild the index: Rebuild Product Management Indexes (EGO_REBUILD_PRODUCT_MGT_INDEXES) To create the structure view: Manage Product Management View (EGP_MANAGE_PM_VIEWS) Manage Scheduled Job Definition (FND_MANAGE_SCHEDULED_JOB_DEFINITION_PRIV) Grant Search Framework Manager Permissions (FND_SEARCH_FWK_MGR_PRIV) Access Product Development Configurations Using a REST Service (ACA_GET_PD_CONFIGURATIONS_REST_PRIV) Manage Search View REST(EGP_MANAGE_SEARCH_VIEW_REST_PRIV) Access Structure Attributes for Indexing Using REST (EGP_GET_PM_STRUCTURE_AVAIL_REST_PRIV) GET Product Management Index REST (EGP_GET_PM_INDEX_REST_PRIV) Get View Available Attribute REST (EGP_VIEW_AVAIL_ATTR_REST_PRIV) To view the quality issues, quality actions, problem reports, and corrective actions in the side panel: Manage Problem Report (ACA_MANAGE_PROBLEM_REPORT_PRIV) Manage Corrective Action (ACA_MANAGE_CORRECTIVE_ACTION_PRIV) Manage Quality Issue (ENQ_MANAGE_QUALITY_ISSUE_PRIV) Manage Quality Action (ENQ_MANAGE_QUALITY_ACTION_PRIV) | L74: Use Enterprise Scheduler Service job: Upgrade Product Management Data to run on-demand manufacturer upgrade and presence indicator scripts: Upgrade Process = Execution Functional Area = Item Child Presence Indicator Feature = Start the job for each of these entries in the Features list one at a time. Wait till one job completes before you start the next. Item has Pending Changes Indicators Item has Quality Indicators Item has AML Indicators Item has Revision level Attachment indicators Item has Structure Indicators
A75: 74 | B75: Inventory Management | C75: Cost Management | D75: Redwood: Create and Edit Cost Analysis Groups Using a New User Experience | F75: 25B | G75: 26B | H75: Wave2 - Modarate Pages | I75: 26A | J75: Manage Workflow Notifications (FUN_MANAGE_WORKFLOW_NOTIFICATIONS_PRIV) to view approvers. 2) Manage Requisition with the Responsive Self Service Procurement Application (POR_MANAGE_REQ_WITH_PWA_PRIV) to access the responsive application. | K75: No profile | L75: No profile | M75: Auto Enabled | N75: Yes | O75: Rekha Bhoopathy | P75: Cost Analysis Groups Page
A76: 75 | B76: Procurement | C76: Responsive Self Service Procurement | D76: View Requisitions Created by Other Preparers | F76: 24C | G76: 26B | H76: Wave1 - Simple Pages | I76: 26A | J76: Manage Requisition with the Responsive Self Service Procurement Application (POR_MANAGE_REQ_WITH_PWA_PRIV) to access the responsive application. 2) View Requisition - All (POR_VIEW_REQUISITION_ALL_PRIV) to view all requisitions in accessible requisitioning BUs | M76: OPT IN+Role Setup | N76: Y | O76: Pragyan Dash | P76: My Requisition Search
A77: 76 | B77: Procurement | C77: Responsive Self Service Procurement | D77: Manage Approvers on Requisitions during Shopping Checkout | F77: 24C | G77: 26B | H77: Wave1 - Simple Pages | I77: 26A | J77: Manage Workflow Notifications (FUN_MANAGE_WORKFLOW_NOTIFICATIONS_PRIV) to view approvers. 2) Manage Requisition with the Responsive Self Service Procurement Application (POR_MANAGE_REQ_WITH_PWA_PRIV) to access the responsive application. | M77: OPT IN+Role Setup | N77: Y | O77: Ashoka Veerabhadrappa | P77: PR Approval notification
A78: 77 | B78: Procurement | C78: Responsive Self Service Procurement | D78: Modify Requisitions as an Approver | F78: 24C | G78: 26B | H78: Wave1 - Simple Pages | I78: 26A | J78: Manage Requisition with the Responsive Self Service Procurement Application (POR_MANAGE_REQ_WITH_PWA_PRIV). 2) Edit Requisition as Approver (POR_CREATE_REQUISITION_ALLOW_APPROVER_MODIFICATION_PRIV) | M78: OPT IN+Role Setup | N78: Y | O78: Pragyan Dash | P78: Workflow approval
A79: 78 | B79: Procurement | C79: Responsive Self Service Procurement | D79: Create Urgent Requisitions | F79: 24C | G79: 26B | H79: Wave1 - Simple Pages | I79: 26A | J79: Manage Requisition with the Responsive Self Service Procurement Application (POR_MANAGE_REQ_WITH_PWA_PRIV) | M79: OPT IN+Role Setup | N79: Y | O79: Pragyan Dash | P79: Requisition Line
A80: 79 | B80: Procurement | C80: Responsive Self Service Procurement | D80: Update the Preparer and Requester on Requisitions | F80: 24C | G80: 26B | H80: Wave1 - Simple Pages | I80: 26A | J80: Manage Requisition with the Responsive Self Service Procurement Application (POR_MANAGE_REQ_WITH_PWA_PRIV) | K80: ORA_POR_USE_SUPP_SITE_INVOICE_CURR) | M80: OPT IN+Profile option+Role Setup | N80: Y | O80: Pragyan Dash | P80: Requisition dashboard
A81: 80 | B81: Procurement | C81: Responsive Self Service Procurement | D81: Create Requisitions as an Advanced User | F81: 24C | G81: 26B | H81: Wave1 - Simple Pages | I81: 26A | J81: Manage Requisition with the Responsive Self Service Procurement Application (POR_MANAGE_REQ_WITH_PWA_PRIV). Create Requisition with Quick Entry (POR_CREATE_REQUISITION_ALLOW_QUICK_ENTRY_PRIV). View Total On Hand Quantity in Supply Source (DOS_VIEW_AVAILABLE_ONHAND_QTY_PRIV) to view available quantity in a source organization. View Subinventory List of Values by Web Service for Self Service Procurement User (INV_VIEW_SUBINVENTORY_LOV_PRC_WEB_SERVICE_PRIV) to view subinventory list of values. | M81: OPT IN+Role Setup | N81: Y | O81: Mukesh Panwar | P81: Requisition Line UI
A82: 81 | B82: Procurement | C82: Responsive Self Service Procurement | D82: Populate Currency on Requisition Lines Automatically from the Supplier Site’s Invoice Currency | F82: 24C | G82: 26B | H82: Wave1 - Simple Pages | I82: 26A | J82: Manage Requisition with the Responsive Self Service Procurement Application (POR_MANAGE_REQ_WITH_PWA_PRIV). | K82: ORA_POR_USE_SUPP_SITE_INVOICE_CURR) | M82: OPT IN+Role Setup | N82: Y | O82: Mukesh Panwar | P82: Requisition Line UI
A83: 82 | B83: Supply Chain Orchestration | C83: Supply Chain Orchestration | D83: Use Redesigned Pages to View Supply Request Lines | F83: 24C | G83: 26B | H83: Wave1 - Simple Pages | I83: 26C | M83: Auto Enabled | N83: Y | O83: Venkat | P83: View Supply Request Line Details
A84: 83 | B84: Product Hub | C84: Product Development | D84: Enhance Manufacturer Management | F84: 24C | G84: 26B | H84: Wave2 - Modarate Pages | I84: 26C | J84: To search for manufacturers using a Redwood page: Get Search View REST(EGP_GET_SEARCH_VIEW_REST_PRIV) To view only manufacturers: View Manufacturer (EGP_VIEW_MANUFACTURER_PRIV) To edit manufacturers: Manage Manufacturer (EGP_MANAGE_MANUFACTURER_PRIV) To create manufacturers: Create Manufacturer (EGP_CREATE_MANUFACTURER_PRIV) Manage Manufacturer (EGP_MANAGE_MANUFACTURER_PRIV) | L84: Mandate version is not specified hence considering the mandate version as per Roadmap for PLM module which is 26B. | M84: Role Setup+Profile option | N84: Y | O84: Karthik Gopal | P84: New Manufacturer and Edit Manufacturer pages
A85: 84 | B85: Manufacturing | C85: Manufacturing | D85: Search for, Create, and Edit Work Definition Names Using the Redwood User Experience | F85: 24B | G85: 26A | H85: Wave1 - Simple Pages | I85: 26A | K85: ORA_WIS_WORK_DEFINITION_NAMES_REDWOOD_ENABLED | M85: Role Setup+Profile option | P85: Work Definition UI
A86: 85 | B86: Manufacturing | C86: Manufacturing | D86: Search for, Create, and Edit Work Areas Using the Redwood User Experience | F86: 24B | G86: 26A | H86: Wave1 - Simple Pages | I86: 26A | K86: ORA_WIS_WORK_AREAS_REDWOOD_ENABLED | M86: Role Setup+Profile option | P86: Manufacturing Work Areas UI
A87: 86 | B87: Manufacturing | C87: Smart Operations | D87: Create, Edit, and Search for Workstations | F87: 24C | G87: 26A | H87: Wave2 - Modarate Pages | I87: 26B | M87: OPT IN | N87: Y | O87: Yoga Gopalakrishnan | P87: Workstations under Plant Setup
A88: 87 | B88: Manufacturing | C88: Smart Operations | D88: Execute Production at a Workstation and Automate Resource Transactions | F88: 24C | G88: 26A | H88: Wave2 - Modarate Pages | I88: 26B | M88: OPT IN | N88: Y | O88: Yoga Gopalakrishnan | P88: Execute Production at a Workstation page
A89: 88 | B89: Manufacturing | C89: Smart Operations | D89: Create Shift Notes During Work Execution at a Workstation for Operator Handoff | F89: 24C | G89: 26A | H89: Wave2 - Modarate Pages | I89: 26B | M89: OPT IN+Setup | N89: Y | O89: Yoga Gopalakrishnan | P89: Workstation page
A90: 89 | B90: Manufacturing | C90: Manufacturing | D90: Search for, Create, and Edit Work Order Statuses Using the Redwood User Experience | F90: 24C | G90: 26A | H90: Wave2 - Modarate Pages | I90: 26B | K90: ORA_WIE_WO_STATUSES_REDWOOD_ENABLED | M90: Role Setup+Profile option | N90: Y | O90: Veeranarayana Swamy | P90: Manage Work Order Statuses
A91: 90 | B91: Manufacturing | C91: Manufacturing | D91: Search for, Create, and Edit Work Centers Using the Redwood User Experience | F91: 24C | G91: 26A | H91: Wave2 - Modarate Pages | I91: 26B | K91: ORA_WIS_WORK_CENTERS_REDWOOD_ENABLED | M91: Role Setup+Profile option | N91: Y | O91: Veeranarayana Swamy | P91: Work Center
A92: 91 | B92: Manufacturing | C92: Manufacturing | D92: Search for, Create, and Edit Standard Operations Using a Redwood User Experience | F92: 24C | G92: 26A | H92: Wave2 - Modarate Pages | I92: 26B | K92: ORA_WIS_STANDARD_OPERATIONS_REDWOOD_ENABLED | M92: Role Setup+Profile option | N92: Y | O92: Veeranarayana Swamy | P92: Manage Standard Operations
A93: 92 | B93: Manufacturing | C93: Manufacturing | D93: Manage Work Definition Productivity Improvements Using the Redwood User Experience | F93: 24C | G93: 26A | H93: Wave2 - Modarate Pages | I93: 26B | K93: ORA_WIS_WORK_DEFINITIONS_REDWOOD_ENABLED | M93: Role Setup+Profile option | N93: Y | O93: Yoga Gopalakrishnan | P93: Work Definitions page
A94: 93 | B94: Inventory Management | C94: Inventory Management | D94: Redwood: Create Cycle Counts Using a Redwood Page | F94: 24D | G94: 26A | H94: Wave2 - Modarate Pages | I94: 26A | K94: ORA_INV_CREATE_CYCLE_COUNT_REDWOOD_ENABLED | M94: OPT IN | N94: Y | O94: Pragyan Dash | P94: Create Cycle count
A95: 94 | B95: Inventory Management | C95: Inventory Management | D95: Redwood: View Item Quantities Using a Redwood Page | F95: 24D | G95: 25B | H95: Wave2 - Modarate Pages | I95: 26A | M95: OPT IN | N95: Y | O95: Karthik Gopal | P95: Item Quantities
A96: 95 | B96: Inventory Management | C96: Receiving | D96: Redwood: Inspect Receipts Using a Redwood Page | F96: 24D | G96: 25B | H96: Wave2 - Modarate Pages | I96: 26A | K96: Manage Administrator Profile Values > ORA_RCV_INSPECT_RECEIPT_LINES_REDWOOD_ENABLED = Yes | L96: 1. Activate Sandbox to enable the Inventory Management (New) 2. Run the "ESS job to create index definition and perform Initial Ingest to OSCS" Refer: https://docs.oracle.com/en/cloud/saas/readiness/scm/24b/inv24b/24B-inventory-wn-f31373.htm | M96: Profile Option | N96: Y | O96: Karthik Gopal | P96: Inspect Receipt Line
A97: 96 | B97: Inventory Management | C97: Receiving | D97: Redwood: Create Receipt Returns Using a Redwood Page | F97: 24D | G97: 25B | H97: Wave2 - Modarate Pages | I97: 26A | K97: Manage Receiving Profile Options > ORA_RCV_RECEIVING_RETURNS_REDWOOD_ENABLED = Yes | M97: Profile Option | N97: Y | O97: Karthik Gopal | P97: Receipt Returns
A98: 97 | B98: Inventory Management | C98: Receiving | D98: Redwood: Create Unordered Receipts Using a Redwood Page | F98: 24D | G98: 26A | H98: Wave2 - Modarate Pages | I98: 26A | K98: Manage Inventory Profile Options > ORA_RCV_UNORDERED_RECEIPTS_REDWOOD_ENABLED = Yes | M98: Profile Option | N98: Y | O98: Karthik Gopal | P98: Create Unordered Receipts
A99: 98 | B99: Inventory Management | C99: Receiving | D99: Redwood: Correct Receipts Using a Redwood Page | F99: 24D | G99: 26A | H99: Wave2 - Modarate Pages | I99: 26A | K99: Manage Administrator Profile Values > ORA_RCV_CORRECT_RECEIPTS_REDWOOD_ENABLED = Yes | M99: Profile Option | N99: Y | O99: Karthik Gopal | P99: Correct Receipt Line
A100: 99 | B100: Order Management | C100: Order Management | D100: Redwood: Create and Manage Sales Orders | F100: 24D | G100: 26A | H100: Wave2 - Modarate Pages | I100: 26B | J100: View Orders (FOM_VIEW_ORDERS_PRIV) Revise Order (FOM_REVISE_ORDER_PRIV) Cancel Order (FOM_CANCEL_ORDER_PRIV) Prepare Sales Orders for Redesigned Pages (FOM_PREPARE_SALES_ORDERS_FOR_REDESIGNED_PAGES_PRIV) Modify Orchestration Order Fulfillment Line Schedule Date (DOO_MODIFY_ORCHESTRATION_ORDER_FULFILLMENT_LINE_SCHEDULE_DATE_PRIV) View Purchase Order (PO_VIEW_PURCHASE_ORDER_PRIV) View Receipt Summary and Transaction History using Responsive Receiving (RCV_VIEW_RECEIPT_SUMMARY_TXN_HISTORY_PWA_PRIV) View Shipment Using Responsive Shipping (WSH_VIEW_SHIPMENT_USING_RESPONSIVE_SHIPPING_PWA) View Supply Orders (DOS_VIEW_SUPPLY_ORDERS_PRIV) | L100: Redwood: Manage Configured Items on Sales Orders | M100: OPT IN+Role Setup | N100: Y | O100: Ashoka Veerabhadrappa | P100: Order Management
...

Sheet Sheet4
A1: S.no | B1: Product | C1: Module | D1: Redwood Features | E1: Update Version | F1: Mandate Version | H1: Privilage Name | I1: Profile Options Value | J1: Additional Info | K1: Action Required | L1: Availability of PPT | M1: SME | N1: UI Page Name
A2: 1 | B2: Inventory Management | C2: Mobile Inventory | D2: Redwood: Create an Interorganization Transfer Using a Mobile Device | E2: 24D | F2: 25B | H2: Create Interorganization Transfer Using Responsive Inventory Duty (ORA_INV_CREATE_INTERORG_TRANSFER_PWA_DUTY). | K2: Role Setup | L2: Y | M2: Pragyan Dash | N2: Inventory Management (Mobile)
A3: 2 | B3: Inventory Management | C3: Mobile Inventory | D3: Redwood: View the Inventory Management (New) Tile as Inventory Management (Mobile) | E3: 24D | F3: 25B | K3: Auto Enabled | N3: Inventory Management (Mobile)
A4: 3 | B4: Inventory Management | C4: Mobile Inventory | D4: Redwood: Inspect Received Goods Using a Mobile Device | E4: 24D | F4: 25B | H4: New: Inspect goods using the responsive receiving application (ORA_RCV_INSPECT_GOODS_PWA_DUTY) | I4: Manage Inventory Profile Options > ORA_INV_MOBILE_INVENTORY_MANAGEMENT_REDWOOD_ENABLED = Yes | J4: 1. Activate Sandbox to enable the Inventory Management (New) 2. Run the "ESS job to create index definition and perform Initial Ingest to OSCS" Refer: https://docs.oracle.com/en/cloud/saas/readiness/scm/24b/inv24b/24B-inventory-wn-f31373.htm | K4: Profile Option | N4: Inventory Management (Mobile)
A5: 4 | B5: Inventory Management | C5: Mobile Inventory | D5: Redwood: View Lot Attributes in Mobile Inventory Transactions | E5: 24D | F5: 25B | K5: Auto Enabled | N5: Inventory Management (Mobile)
A6: 5 | B6: Inventory Management | C6: Cost Management | D6: Redwood: View Rollup Costs Using a New User Experience | E6: 25A | F6: 25B | H6: Users who are assigned a configured job role that contains the following privilege can access this feature: View Rolled Up Costs (CST_REVIEW_ROLLEDUP_COSTS) | I6: On the Manage Administrator Profile Values page, search for and select the ORA_CST_VIEW_ROLLEDUP_COSTS_REDWOOD_ENABLED profile option code. In the Profile Values section, set the Site level to Yes. The default value is No. Click Save and Close. Changes in the profile value will affect users the next time they sign in. Yes = enables the feature No = disables the feature | K6: Role Setup+Profile option | L6: Y | M6: Miriam Chandni | N6: Cost Accounting Work Area
A7: 6 | B7: Inventory Management | C7: Cost Management | D7: Redwood: Create and Update Cost Scenarios Using a New User Experience | E7: 25A | F7: 25B | H7: Users who are assigned a configured job role that contains the following privilege can access this feature: Manage Cost Planning Scenario Definition (CST_MANAGE_SCENARIO) | I7: On the Manage Administrator Profile Values page, search for and select the ORA_CST_PLANNING_SCENARIOS_REDWOOD_ENABLED profile option code. In the Profile Values section, set the Site level to Yes. The default value is No. Click Save and Close. Changes in the profile value will affect users the next time they sign in. Yes = enables the feature No = disables the feature | K7: Role Setup+Profile option | L7: Y | M7: Miriam Chandni | N7: Cost Accounting Work Area
A8: 7 | B8: Inventory Management | C8: Cost Management | D8: Redwood: Review Standard Costs Import Exceptions Using a New User Experience | E8: 25A | F8: 25B | H8: Users who are assigned a configured job role that contains the following privilege can access this feature: Estimate Costs (CST_ESTIMATE_COSTS) | I8: On the Manage Administrator Profile Values page, search for and select the ORA_CST_STD_COST_IMPORT_EXCEPTIONS_REDWOOD_ENABLED profile option code. In the Profile Values section, set the Site level to Yes. The default value is No. Click Save and Close. Changes in the profile value will affect users the next time they sign in. Yes = enables the feature No = disables the feature | K8: Role Setup+Profile option | L8: Y | M8: Miriam Chandni | N8: Cost Accounting Work Area
A9: 8 | B9: Inventory Management | C9: Receiving | D9: Redwood: Manage Inbound Shipments and Create ASN or ASBN Using a Redwood Page | E9: 24D | F9: 25C | H9: 1. Manage Inbound Shipment Using Responsive Receiving (RCV_MANAGE_INBOUND_SHIPMENT_PWA) 2. Manage Inbound Shipment as Supplier Using Responsive Receiving (RCV_MANAGE_INBOUND_SHIPMENT_AS_SUPPLIER_PWA) 3. Create Advance Shipment Notice Using Responsive Receiving (RCV_CREATE_ADVANCE_SHIPMENT_NOTICE_PWA) 4. Create Advance Shipment Notice as Supplier Using Responsive Receiving (RCV_CREATE_ADVANCE_SHIPMENT_NOTICE_AS_SUPPLIER_PWA) | I9: Manage Receiving Profile Options > 1. ORA_RCV_INBOUND_SHIPMENTS_REDWOOD_ENABLED = Yes 2. ORA_RCV_ADVANCE_SHIPMENT_NOTICE_REDWOOD_ENABLED = Yes 3. ORA_RCV_INBOUND_SHIPMENTS_SUPPLIER_PORTAL_REDWOOD_ENABLED = Yes 4. ORA_RCV_ADVANCE_SHIPMENT_NOTICE_SUPPLIER_PORTAL_REDWOOD_ENABLED = Yes | J9: 1. Activate Sandbox to enable the Inventory Management (New) 2. Run the "ESS job to create index definition and perform Initial Ingest to OSCS" Refer: https://docs.oracle.com/en/cloud/saas/readiness/scm/24b/inv24b/24B-inventory-wn-f31373.htm | K9: Profile Option | L9: Y | M9: Mukesh Panwar | N9: Receipts
A10: 9 | B10: Inventory Management | C10: Receiving | D10: Redwood: View Receipts and Receipt Returns in Supplier Portal Using a Redwood Page | E10: 24D | F10: 25C | H10: View Receiving Receipt and Receipt Return as Supplier (RCV_VIEW_RECEIVING_RECEIPT_AND_RECEIPT_RETURN_AS_SUPPLIER_PRIV) | I10: Manage Receiving Profile Options task > ORA_RCV_RECEIPTS_RETURNS_SUPPLIER_PORTAL_REDWOOD_ENABLED = Yes | K10: Profile Option | L10: Y | M10: Pragyan Dash | N10: Supplier Portal
A11: 10 | B11: Inventory Management | C11: Cost Management | D11: Create and Edit Overhead Rates Using Redwood Pages | E11: 24C | F11: 26B | H11: Users who are assigned a configured job role that contains the following privilege can access this feature: Manage Resource and Overhead Rate Plans (CST_MANAGE_RATE_PLANS) | I11: On the Manage Administrator Profile Values page, search for and select the ORA_CST_RESOURCE_RATES_REDWOOD_ENABLED profile option code. In the Profile Values section, set the Site level to Yes. The default value is No. Yes = enables the feature No = disables the feature | J11: Part of the standard setups | K11: Role Setup+Profile option | M11: Rekha Bhoopathy | N11: Overhead Rates
A12: 11 | B12: Inventory Management | C12: Fiscal Document Capture | D12: Manage Tolerances Using the Redwood Experience | E12: 24C | F12: 26B | H12: Set Up Fiscal Document Tolerances (CMF_FISCAL_DOC_TOLERANCES) Manage Fiscal Document Tolerances by Web Service (CMF_FISCAL_DOC_TOLERANCE_WEB_SERVICE) | I12: On the Manage Administrator Profile Values page, enable the new ORA_CMF_TOLERANCE_RULES_REDWOOD_ENABLED profile option at Site or Product or User level. Select Yes for the Redwood page for Fiscal Document Tolerance Rules Enabled option. | J12: Part of the standard setups | K12: Role Setup+Profile option | M12: Rekha Boopathy | N12: Fiscal Document Tolerance Rules
A13: 12 | B13: Inventory Management | C13: Supply Chain Orchestration | D13: Manage Documentation and Accounting Rule in Redwood Pages | E13: 24C | F13: 26B | H13: Maintain Documentation and Accounting Rules (FOS_MAINTAIN_TRADE_AND_ACCOUNTING_RULES) Manage Documentation and Accounting Rules (FOS_MANAGE_TRADE_AND_ACCOUNTING_RULES) View Documentation and Accounting Rules (FOS_VIEW_TRADE_AND_ACCOUNTING_RULES) | I13: ORA_FOS_TRADE_ACCOUNTING_RULES_REDWOOD_ENABLED | K13: Role Setup+Profile option | L13: Y | M13: Veeranarayana Swamy | N13: Documentation and Accounting Rules
A14: 13 | B14: Inventory Management | C14: Supply Chain Orchestration | D14: Manage Transfer Pricing Rule in Redwood Pages | E14: 24C | F14: 26B | H14: Maintain Transfer Pricing Rules (FOS_MAINTAIN_TRANSFER_PRICING_RULES) Manage Transfer Pricing Rules (FOS_MANAGE_TRANSFER_PRICING_RULES) View Transfer Pricing Rules (FOS_VIEW_TRANSFER_PRICING_RULES) | I14: ORA_FOS_TRANSFER_PRICING_RULES_REDWOOD_ENABLED | K14: Role Setup+Profile option | L14: Y | M14: Miriam Chandni | N14: Financial Orchestration Work Area
A15: 14 | B15: Inventory Management | C15: Cost Management | D15: Create and Update Resource Rates Using Redwood Pages | E15: 24B | F15: 26B | H15: Users who are assigned a configured job role that contains the following privilege can access this feature: Manage Resource and Overhead Rate Plans (CST_MANAGE_RATE_PLANS) | I15: On the Manage Administrator Profile Values page, search for and select the ORA_CST_RESOURCE_RATES_REDWOOD_ENABLED profile option code. In the Profile Values section, set the Site level to Yes. The default value is No. Yes = enables the feature No = disables the feature | J15: Part of the standard setups | K15: Role Setup+Profile option | M15: Rekha Bhoopathy | N15: Resource Rates
A16: 15 | B16: Inventory Management | C16: Cost Management | D16: Redwood: View Scenario Exceptions Using a New User Experience | E16: 25A | F16: 25B | H16: Users who are assigned a configured job role that contains the following privilege can access this feature: View Scenario Exceptions (CST_MANAGE_SCENRIO_EXCEPTIONS) | I16: On the Manage Administrator Profile Values page, search for and select the ORA_CST_SCENARIO_EXCEPTIONS_REDWOOD_ENABLED profile option code. In the Profile Values section, set the Site level to Yes. The default value is No. Click Save and Close. Changes in the profile value will affect users the next time they sign in. Yes = enables the feature No = disables the feature | K16: Role Setup+Profile option | L16: Y | M16: Miriam Chandni | N16: Cost Accounting Work Area
A17: 16 | B17: Manufacturing | C17: Manufacturing | D17: Search for, Create, and Edit a Standard Item Work Definition Using the Redwood User Experience | E17: 24B | F17: 26B | I17: ORA_WIS_WORK_DEFINITIONS_REDWOOD_ENABLED | K17: Role Setup+Profile option | L17: Y | M17: Yoga Gopalakrishnan | N17: Manage Work Definitions Page
A18: 17 | B18: Order Management | C18: Channel Revenue Management | D18: Redwood: Define Product Eligibility Based on Item Categories for Customer Rebate Programs | E18: 24D | F18: 25A | H18: Manage Customer Programs (CJM_MANAGE_CUSTOMER_PROGRAMS_PRIV) | J18: Use the Opt In UI to enable this feature. | K18: OPT IN+Role Setup | M18: TBD | N18: Customer Rebate Work Area
A19: 18 | B19: Order Management | C19: Channel Revenue Management | D19: Redwood: Exclude Multiple Items or Item Categories in Product Eligibility Rules | E19: 24D | F19: 25C | H19: Manage Customer Programs (CJM_MANAGE_CUSTOMER_PROGRAMS_PRIV) | J19: Use the Opt In UI to enable this feature. | K19: OPT IN+Role Setup | M19: TBD | N19: Customer Rebate Work Area
A20: 19 | B20: Order Management | C20: Channel Revenue Management | D20: Redwood: Manage Manual Accrual Adjustments for Customer Rebate Programs | E20: 24D | F20: 26B | H20: Manage Customer Manual Adjustments (CJM_MANAGE_CUSTOMER_MANUAL_ADJUSTMENTS_PRIV), View Customer Manual Adjustments (CJM_VIEW_CUSTOMER_MANUAL_ADJUSTMENTS_PRIV) | J20: Use the Opt In UI to enable this feature. | K20: OPT IN+Role Setup | M20: TBD | N20: Customer Rebate Work Area
A21: 20 | B21: Order Management | C21: Pricing | D21: Redwood: Apply Pricing Promotions According to Pricing Strategies and Payment Terms | E21: 24D | F21: 26B | H21: Manage Draft Pricing Promotions (QP_MANAGE_DRAFT_PRICING_PROMOTIONS) Manage Pricing Promotions (QP_MANAGE_PRICING_PROMOTIONS) View Pricing Promotions (QP_VIEW_PRICING_PROMOTIONS) Activate Pricing Promotions (QP_ APPROVE_PRICING_PROMOTIONS) Manage Dynamic Rules (QP_MANAGE_DYNAMIC_RULES) | J21: This is a new feature not available on classic UI | K21: OPT IN | L21: Y | M21: Mukesh Panwar | N21: Pricing Promotions
A22: 21 | B22: Order Management | C22: Pricing | D22: Redwood: Copy and Delete Pricing Promotions | E22: 24D | F22: 26B | H22: Manage Promotions (QP_MANAGE_PROMOTIONS) | J22: This is a new feature not available on classic UI | K22: OPT IN | L22: Y | M22: Mukesh Panwar | N22: Pricing Promotions
A23: 22 | B23: Order Management | C23: Pricing | D23: Redwood: Define Tiered Adjustments on Rate Plan Charges | E23: 24D | F23: 26B | H23: Manage Price Lists (QP_MANAGE_PRICE_LISTS) Manage In-Progress Price Lists (QP_MANAGE_IN_PROGRESS_PRICE_LISTS) View Price Lists (QP_VIEW_PRICE_LISTS) Approve Price Lists QP_APPROVE_PRICE_LISTS | J23: This is a new feature not available on classic UI | K23: OPT IN+Role Setup | L23: Y | M23: Mukesh Panwar | N23: Price List
A24: 23 | B24: Order Management | C24: Pricing | D24: Create Pricing Promotions for Sales Orders Using Redwood Pages | E24: 24C | F24: 26A | H24: Manage Draft Pricing Promotions (QP_MANAGE_DRAFT_PRICING_PROMOTIONS) Manage Pricing Promotions (QP_MANAGE_PRICING_PROMOTIONS) View Pricing Promotions (QP_VIEW_PRICING_PROMOTIONS) Activate Pricing Promotions (QP_ APPROVE_PRICING_PROMOTIONS) Manage Dynamic Rules (QP_MANAGE_DYNAMIC_RULES) | J24: This is a new feature not available on classic UI | K24: OPT IN+Role Setup | L24: Y | M24: Mukesh Panwar | N24: Pricing Promotions
A25: 24 | B25: Order Management | C25: Channel Revenue Management | D25: Add Notes for Customer Programs and Claims in Redwood Pages | E25: 23C | F25: 25B | H25: Manage Customer Programs (CJM_MANAGE_CUSTOMER_PROGRAMS_PRIV) Manage Customer Claims (CJM_MANAGE_CUSTOMER_CLAIMS_PRIV) View Only Activity (ZMM_VIEW_ONLY_ACTIVITY_PRIV) | J25: Use the Opt In UI to enable this feature. | K25: OPT IN+Role Setup | M25: TBD | N25: Customer Rebate Work Area
A26: 25 | B26: Order Management | C26: Channel Revenue Management | D26: Improve Usability of Claim Pages in Redwood | E26: 23C | F26: 25B | H26: Manage Customer Claims (CJM_MANAGE_CUSTOMER_CLAIMS_PRIV) Create Customer Claims (CJM_CREATE_CUSTOMER_CLAIMS_PRIV) View Customer Claims (CJM_VIEW_CUSTOMER_CLAIMS_PRIV) | J26: Use the Opt In UI to enable this feature. | K26: OPT IN+Role Setup | M26: TBD | N26: Customer Claims Work Area
A27: 26 | B27: Order Management | C27: Channel Revenue Management | D27: Update and Settle Multiple Claims Using Redwood Pages | E27: 23C | F27: 25B | H27: Manage Customer Claims (CJM_MANAGE_CUSTOMER_CLAIMS_PRIV) View Only Activity (ZMM_VIEW_ONLY_ACTIVITY_PRIV) | J27: Use the Opt In UI to enable this feature. | K27: OPT IN+Role Setup | M27: TBD | N27: Customer Claims Work Area
A28: 27 | B28: Order Management | C28: Channel Revenue Management | D28: Manage Deduction Claims Using Redwood Pages | E28: 23B | F28: 26A | H28: No additional roles needed to access redwood pages if you already have access to Deductions and Settlement in 23B. Add reference data set access to existing Channel Claim Manager users, in addition to their existing business unit data access. | J28: Use the Opt In UI to enable this feature. | K28: OPT IN+Role Setup | M28: TBD | N28: Customer Claims Work Area
A29: 28 | B29: Procurement | C29: Sourcing | D29: Redwood: Respond to Simple Negotiations in Supplier Portal | E29: 24D | F29: 26A | H29: Create Supplier Negotiation Response (PON_CREATE_SUPPLIER_NEGOTIATION_RESPONSE_PRIV) Edit Supplier Negotiation Response (PON_EDIT_SUPPLIER_NEGOTIATION_RESPONSE_PRIV) | K29: Log Service Request | L29: Y | M29: Karthik Gopal | N29: Requirements
A30: 29 | B30: Procurement | C30: Sourcing | D30: Redwood: Use Enhanced Negotiation Search in Supplier Portal | E30: 24D | F30: 26A | H30: View Supplier Negotiation as Supplier (PON_VIEW_SUPPLIER_NEGOTIATION_SUPPLIER_FACING_PRIV) | K30: OPT IN | L30: Y | M30: Ashoka Veerabhadrappa | N30: negotiation in supplier portal
A31: 30 | B31: Procurement | C31: Sourcing | D31: Redwood: Use New Buyer Experience for Negotiation Messages | E31: 24D | F31: 25C | H31: View Supplier Negotiation Online Message (PON_VIEW_ONLINE_MESSAGE_PRIV) Create Supplier Negotiation Online Message (PON_CREATE_ONLINE_MESSAGE_PRIV) Reply Supplier Negotiation Online Message (PON_REPLY_ONLINE_MESSAGE_PRIV) | K31: OPT IN+ Profile Option | L31: Y | M31: Ashoka Veerabhadrappa | N31: negotiation Messages
A32: 31 | B32: Procurement | C32: Sourcing | D32: Redwood: Use New Supplier Experience for Negotiation Messages | E32: 24D | F32: 26A | H32: View Supplier Negotiation Online Message as Supplier (PON_VIEW_ONLINE_MESSAGE_SUPPLIER_FACING_PRIV) Create Supplier Negotiation Online Message as Supplier (PON_CREATE_ONLINE_MESSAGE_SUPPLIER_FACING_PRIV) Reply Supplier Negotiation Online Message as Supplier (PON_REPLY_ONLINE_MESSAGE_SUPPLIER_FACING_PRIV) | K32: OPT IN | L32: Y | M32: Ashoka Veerabhadrappa | N32: negotiation Messages
A33: 32 | B33: Procurement | C33: Supplier Model | D33: Redwood: Next Generation User Experience for Supplier Registration | E33: 24D | F33: 25C | K33: OPT IN | L33: Y | M33: Ashoka Veerabhadrappa | N33: Supplier Registration UI
A34: 33 | B34: Procurement | C34: Supplier Qualification Management | D34: Redwood: Use Questionnaires in Internal Supplier Registration | E34: 24D | F34: 25C | H34: POZ_SUBMIT_SUPPLIER_REGISTRATION_PRIV | J34: Opt in : Redwood: Next Generation User Experience for Supplier Registration | K34: OPT IN+Role Setup | L34: Y | M34: Ashoka Veerabhadrappa | N34: Supplier Registration UI
A35: 34 | B35: Procurement | C35: Common Procurement | D35: Extend Procurement Redwood Application Pages Using Visual Builder Studio | E35: 24C | F35: 25C | K35: Visual Builder | M35: Pravalika G | N35: Vishual Builder
A36: 35 | B36: Product Hub | C36: Product Development | D36: Redwood: Secure Manufacturers Using Access Control Lists | E36: 24D | F36: 26A | H36: To configure manufacturer conditions using a filtered list: Use REST Service - Identity Integration (ASE_REST_SERVICE_ACCESS_IDENTITY_INTEGRATION_PRIV) Use Atom Feed - Employees Workspace (PER_ATOM_WORKSPACE_ACCESS_EMPLOYEES_PRIV) Manage HCM Lists (HRC_MANAGE_HCM_LISTS_PRIV) Human Capital Management Application Administrator (ORA_HRC_HUMAN_CAPITAL_MANAGEMENT_APPLICATION_ADMINISTRATOR_JOB) To configure teams, permission sets, and conditions: Monitor Product Development (ACA_MONITOR_PRODUCT_DEVELOPMENT_PRIV) Configure Access Control Teams, Permission Sets, and Conditions (EGP_ACCESS_CONTROL_TEAMS_PRIV) Use REST Service - Identity Integration (ASE_REST_SERVICE_ACCESS_IDENTITY_INTEGRATION_PRIV) Use Atom Feed - Employees Workspace (PER_ATOM_WORKSPACE_ACCESS_EMPLOYEES_PRIV) Manage HCM Lists (HRC_MANAGE_HCM_LISTS_PRIV) Manage HCM Rules (HRC_MANAGE_HCM_RULES_PRIV) Run Scheduled Processes (HEY_RUN_SCHEDULED_PROCESSES_PRIV) Manage Scheduled Processes(FND_MANAGE_SCHEDULED_PROCESSES_PRIV) To access the secured manufacturer data: Create Manufacturer (EGP_CREATE_MANUFACTURER_PRIV) View Manufacturers (EGP_VIEW_MANUFACTURER_PRIV) Manage Manufacturers (EGP_MANAGE_MANUFACTURER_PRIV) To access journeys setup and configure the roles in role hierarchy: Manage Journey (ORA_PER_MANAGE_JOURNEY_TEMPLATE) Manage Guided Journeys (ORA_PER_MANAGE_GUIDED_JOURNEYS) Use REST Service - Guided Journeys Read Only (ORA_PER_REST_SERVICE_ACCESS_GUIDED_JOURNEYS_RO) Use REST Service - Journey Categories List of Values (ORA_PER_REST_SERVICE_ACCESS_JOURNEY_CATEGORIES_LOV) To access business rules: Administer Sandbox (FND_ADMINISTER_SANDBOX_PRIV) | J36: Mandate version is not specified hence considering the mandate version as per Roadmap for PLM module which is 26B. | K36: OPT IN | L36: Y | M36: Miriam Chandni | N36: Product Management Work Area
A37: 36 | B37: Product Hub | C37: Product Lifecycle Management | D37: Redwood: Create and Manage Personalized Views in Product Management Search | E37: 24D | F37: 26A | H37: View Product Management Search (EGP_VIEW_PRODUCT_MGT_SEARCH_PRIV) Get Search View REST (EGP_GET_SEARCH_VIEW_REST_PRIV) GET Product Management Index REST (EGP_GET_PM_INDEX_REST_PRIV) Manage Search View REST (EGP_MANAGE_SEARCH_VIEW_REST_PRIV) | J37: Mandate version is not specified hence considering the mandate version as per Roadmap for PLM module which is 26B. | K37: Role Setup+Profile option | L37: Y | M37: Miriam Chandni | N37: Product Information Management Work Area
A38: 37 | B38: Product Hub | C38: Product Lifecycle Management | D38: Redwood: Search Workflow Approvals | E38: 24D | F38: 25C | H38: Users with view only access to changes require the following privileges: Access Product Management Change Search (EGO_VIEW_PRODUCT_MANAGEMENT_CHANGE_SEARCH) Get Search View REST (EGP_GET_SEARCH_VIEW_REST_PRIV) GET Product Management Index REST (EGP_GET_PM_INDEX_REST_PRIV) You should have Monitor Product Management Workflow Objects (ACA_MONITOR_PRODUCT_MANAGEMENT_WORFLOW_OBJECTS_PRIV) and one of the following privileges: For change orders: View Change Order (ACA_VIEW_CHANGE_ORDERS_PRIV) or Manage Change Orders (ACA_MANAGE_CHANGE_ORDERS_PRIV) For change requests: View Change Request (ACA_VIEW_CHANGE_REQUESTS_PRIV) Manage Change Requests (ACA_MANAGE_CHANGE_REQUESTS_PRIV) For problem reports: View Problem Report (ACA_VIEW_PROBLEM_REPORTS_PRIV) Manage Problem Report (ACA_MANAGE_PROBLEM_REPORT_PRIV) For corrective and preventive actions: View Corrective Action (ACA_VIEW_CORRECTIVE_ACTIONS_PRIV) Manage Corrective Action (ACA_MANAGE_CORRECTIVE_ACTION_PRIV) To configure the index: Manage Product Management Index (EGP_MANAGE_PM_INDEXES_PRIV) Manage Scheduled Job Definition (FND_MANAGE_SCHEDULED_JOB_DEFINITION_PRIV) Grant Search Framework Manager Permissions (FND_SEARCH_FWK_MGR_PRIV) To rebuild the index: Rebuild Product Management Indexes (EGO_REBUILD_PRODUCT_MGT_INDEXES_PRIV) To create search views: Manage Product Management View (EGP_MANAGE_PM_VIEWS_PRIV) Manage Scheduled Job Definition (FND_MANAGE_SCHEDULED_JOB_DEFINITION_PRIV) Grant Search Framework Manager Permissions (FND_SEARCH_FWK_MGR_PRIV) Access Product Development Configurations Using a REST Service (ACA_GET_PD_CONFIGURATIONS_REST_PRIV) Manage Search View REST (EGP_MANAGE_SEARCH_VIEW_REST_PRIV) Get View Available Attribute REST (EGP_VIEW_AVAIL_ATTR_REST_PRIV) | J38: Mandate version is not specified hence considering the mandate version as per Roadmap for PLM module which is 26B. | K38: Role Setup+Profile option | L38: Y | M38: Miriam Chandni | N38: Product Management Experience
A39: 38 | B39: Product Hub | C39: Product Lifecycle Management | D39: Redwood: Search Workflow History | E39: 24D | F39: 25C | H39: Users with view only access to changes require the following privileges: Access Product Management Change Search (EGO_VIEW_PRODUCT_MANAGEMENT_CHANGE_SEARCH) View Change History (EGO_VIEW_CHANGE_HISTORY_PRIV) Get Search View REST (EGP_GET_SEARCH_VIEW_REST_PRIV) GET Product Management Index REST (EGP_GET_PM_INDEX_REST_PRIV) You should have Monitor Product Management Workflow Objects (ACA_MONITOR_PRODUCT_MANAGEMENT_WORFLOW_OBJECTS_PRIV) and one of the following privileges: For change orders: View Change Order (ACA_VIEW_CHANGE_ORDERS_PRIV) or Manage Change Orders (ACA_MANAGE_CHANGE_ORDERS_PRIV) For change requests: View Change Request (ACA_VIEW_CHANGE_REQUESTS_PRIV) Manage Change Requests (ACA_MANAGE_CHANGE_REQUESTS_PRIV) For problem reports: View Problem Report (ACA_VIEW_PROBLEM_REPORTS_PRIV) Manage Problem Report (ACA_MANAGE_PROBLEM_REPORT_PRIV) For corrective and preventive actions: View Corrective Action (ACA_VIEW_CORRECTIVE_ACTIONS_PRIV) Manage Corrective Action (ACA_MANAGE_CORRECTIVE_ACTION_PRIV) To configure the index: Manage Product Management Index (EGP_MANAGE_PM_INDEXES_PRIV) Manage Scheduled Job Definition (FND_MANAGE_SCHEDULED_JOB_DEFINITION_PRIV) Grant Search Framework Manager Permissions (FND_SEARCH_FWK_MGR_PRIV) To rebuild the index: Rebuild Product Management Indexes (EGO_REBUILD_PRODUCT_MGT_INDEXES_PRIV) To create search views: Manage Product Management View (EGP_MANAGE_PM_VIEWS_PRIV) Manage Scheduled Job Definition (FND_MANAGE_SCHEDULED_JOB_DEFINITION_PRIV) Grant Search Framework Manager Permissions (FND_SEARCH_FWK_MGR_PRIV) Access Product Development Configurations Using a REST Service (ACA_GET_PD_CONFIGURATIONS_REST_PRIV) Manage Search View REST (EGP_MANAGE_SEARCH_VIEW_REST_PRIV) Get View Available Attribute REST (EGP_VIEW_AVAIL_ATTR_REST_PRIV) | J39: Mandate version is not specified hence considering the mandate version as per Roadmap for PLM module which is 26B. | K39: Role Setup+Profile option | L39: Y | M39: Miriam Chandni | N39: Product Management Experience
A40: 39 | B40: Product Hub | C40: Product Development | D40: Create, Edit, and Extend Manufacturers Using a Redwood Page | E40: 24B | F40: 25B | H40: To search for manufacturers using a Redwood page: Get Search View REST(EGP_GET_SEARCH_VIEW_REST_PRIV) To view only manufacturers: View Manufacturer (EGP_VIEW_MANUFACTURER_PRIV) To edit manufacturers: Manage Manufacturer (EGP_MANAGE_MANUFACTURER_PRIV) To create manufacturers: Create Manufacturer (EGP_CREATE_MANUFACTURER_PRIV) Manage Manufacturer (EGP_MANAGE_MANUFACTURER_PRIV) | I40: EGP_MANUFACTURER_REDWOOD_ENABLED | J40: Mandate version is not specified hence considering the mandate version as per Roadmap for PLM module which is 26B. | K40: Role Setup+Profile option | L40: Y | M40: Miriam Chandni | N40: Product Management Search
A41: 40 | B41: Product Hub | C41: Product Development & Product Hub Common | D41: Access Side Panel View of Item Data from Search Results Using a Redwood Page | E41: 24B | F41: 25D | H41: To view the item search: View Product Management Search (EGP_VIEW_PRODUCT_MGT_SEARCH) View Item (EGP_VIEW_ITEM) Get Search View REST (EGP_GET_SEARCH_VIEW_REST_PRIV) Data Security: View Item Basic To view the item AML in Redwood: Manage Trading Partner Item (EGP_MANAGE_TRADING_PARTNER_ITEM_PRIV) View Trading Partner Item (EGP_VIEW_TRANDING_PARTNER_ITEM_PRIV) View Manufacturers (EGP_VIEW_MANUFACTURER_PRIV) Get Trading Partner Item Relationship Rest (EGI_GET_TPI_REL_REST_PRIV) To view the item pending changes in Redwood: Manage Change Orders (ACA_MANAGE_CHANGE_ORDERS_PRIV) Manage Change Requests (ACA_MANAGE_CHANGE_REQUESTS_PRIV) View Change Order (ACA_VIEW_CHANGE_ORDERS_PRIV) View Change Request (ACA_VIEW_CHANGE_REQUESTS_PRIV) Data Security: View Item Change Order (EGO_ENGINEERING_CHANGES_B) To view the quality issues, quality actions, problem reports and corrective actions: Manage Problem Report (ACA_MANAGE_PROBLEM_REPORT_PRIV) View Problem Report (ACA_VIEW_PROBLEM_REPORTS_PRIV) Manage Corrective Action (ACA_MANAGE_CORRECTIVE_ACTION_PRIV) View Corrective Action (ACA_VIEW_CORRECTIVE_ACTIONS_PRIV) Manage Quality Issue (ENQ_MANAGE_QUALITY_ISSUE_PRIV) View Quality Issue (ENQ_VIEW_QUALITY_ISSUE_PRIV) Manage Quality Action (ENQ_MANAGE_QUALITY_ACTION_PRIV) View Quality Action (ENQ_VIEW_QUALITY_ACTION_PRIV) | J41: Mandate version is not specified hence considering the mandate version as per Roadmap for PLM module which is 26B. | K41: Role Setup+Profile option | L41: Y | M41: Miriam Chandni | N41: Product Management Search
A42: 41 | B42: Product Hub | C42: Product Development & Product Hub Common | D42: Access Side Panel View of Structure Component Data Using a Redwood Page | E42: 24B | F42: 25D | H42: To view the item structure in Redwood: View Product Management Search (EGP_VIEW_PRODUCT_MGT_SEARCH) View Item (EGP_VIEW_ITEM) Create Item Structure (EGP_CREATE_ITEM_STRUCTURE_PRIV) Get Search View REST (EGP_GET_SEARCH_VIEW_REST_PRIV) Data Security: View Item Basic To configure the index: Manage Product Management Index (EGP_MANAGE_PM_INDEXES) Manage Scheduled Job Definition (FND_MANAGE_SCHEDULED_JOB_DEFINITION_PRIV) Grant Search Framework Manager Permissions (FND_SEARCH_FWK_MGR_PRIV) Get Item Index Available Attributes REST (EGP_GET_PM_ITEM_AVAIL_REST_PRIV) To rebuild the index: Rebuild Product Management Indexes (EGO_REBUILD_PRODUCT_MGT_INDEXES) To create the structure view: Manage Product Management View (EGP_MANAGE_PM_VIEWS) Manage Scheduled Job Definition (FND_MANAGE_SCHEDULED_JOB_DEFINITION_PRIV) Grant Search Framework Manager Permissions (FND_SEARCH_FWK_MGR_PRIV) Access Product Development Configurations Using a REST Service (ACA_GET_PD_CONFIGURATIONS_REST_PRIV) Manage Search View REST (EGP_MANAGE_SEARCH_VIEW_REST_PRIV) Get View Available Attribute REST (EGP_VIEW_AVAIL_ATTR_REST_PRIV) To view the quality issues, quality actions, problem report, and corrective action in the side panel: Manage Problem Report (ACA_MANAGE_PROBLEM_REPORT_PRIV) Manage Corrective Action (ACA_MANAGE_CORRECTIVE_ACTION_PRIV) Manage Quality Issue (ENQ_MANAGE_QUALITY_ISSUE_PRIV) Manage Quality Action (ENQ_MANAGE_QUALITY_ACTION_PRIV) | J42: Mandate version is not specified hence considering the mandate version as per Roadmap for PLM module which is 26B. | K42: Role Setup+Profile option | L42: Y | M42: Miriam Chandni | N42: Product Management Search
A43: 42 | B43: Quality Management | C43: Quality Inspection Management | D43: Manage Inspection Levels using the Redwood Experience | E43: 24C | F43: 26A | H43: View Product Management Search (EGP_VIEW_PRODUCT_MGT_SEARCH_PRIV) Get Search View Rest (EGP_GET_SEARCH_VIEW_REST_PRIV) GET Product Management Index REST (EGP_GET_PM_INDEX_REST_PRIV) | I43: ORA_QA_INSPECTION_LEVEL_REDWOOD_ENABLED | K43: Role Setup+Profile option | L43: Y | M43: Ashoka Veerabhadrappa | N43: Quality Management Landing Page | P43: Manufacturing and Product Life Cylce Management
A44: 43 | B44: Quality Management | C44: Quality Inspection Management | D44: Manage Inspection Plans using the Redwood Experience | E44: 24C | F44: 26A | H44: Manage Item Source System (EGI_MANAGE_ITEM_SOURCE_SYSTEM_PRIV) | I44: ORA_QA_INSPECTION_PLAN_REDWOOD_ENABLED | K44: Role Setup+Profile option | L44: Y | M44: Ashoka Veerabhadrappa | N44: Quality Management Landing Page | P44: Manufacturing and Product Life Cylce Management
A45: 44 | B45: Quality Management | C45: Quality Inspection Management | D45: Perform Quality Inspections using the Redwood Experience | E45: 24C | F45: 25B | H45: Manage Item Delete Group (EGP_MANAGE_ITEM_DELETE_GROUP_PRIV) Access Item Structure Data Using a REST Service (EGP_GET_ITEM_STRUCTURE_REST_PRIV) Access Change Order Using a REST Service (ACA_GET_CHANGE_REST_PRIV) Manage Delete Group Rest (EGP_DG_REST_PRIV) GET Product Management Index REST (EGP_GET_PM_INDEX_REST_PRIV) Get Search View REST (EGP_GET_SEARCH_VIEW_REST_PRIV) Grant Search Framework Manager Permissions (FND_SEARCH_FWK_MGR_PRIV) View Product Management Search (EGP_VIEW_PRODUCT_MGT_SEARCH_PRIV) | I45: ORA_QA_INSPECTIONS_REDWOOD_ENABLED | K45: Role Setup+Profile option | L45: Y | M45: Yoga Gopalakrishnan | N45: Quality Inspections Landing page | P45: Manufacturing and Product Life Cylce Management
A46: 45 | B46: Quality Management | C46: Quality Inspection Management | D46: Manage Inspection Characteristics in Redwood Pages | E46: 24B | F46: 26B | H46: To search for manufacturers using a Redwood page: Get Search View REST(EGP_GET_SEARCH_VIEW_REST_PRIV) To view only manufacturers: View Manufacturer (EGP_VIEW_MANUFACTURER_PRIV) To edit manufacturers: Manage Manufacturer (EGP_MANAGE_MANUFACTURER_PRIV) To create manufacturers: Create Manufacturer (EGP_CREATE_MANUFACTURER_PRIV) Manage Manufacturer (EGP_MANAGE_MANUFACTURER_PRIV) | I46: ORA_QA_CHARACTERISTIC_REDWOOD_ENABLED | K46: Role Setup+Profile option | L46: Y | M46: Yoga Gopalakrishnan | N46: Quality Inspections Landing page | P46: Manufacturing and Product Life Cylce Management
A47: 46 | B47: SCM Common Components | C47: SCM Common Components | D47: Create Guided Journeys for Redwood Pages | E47: 24C | F47: 26A | H47: Manage Publication Maps (EGI_MANAGE_PUBLICATION_MAPS_PRIV) Manage Publishable Attributes REST (EGI_MANAGE_PUBLISHABLE_ATTR_REST_PRIV) Manage Publication Maps REST (EGI_MANAGE_PUBLICATION_MAPS_REST_PRIV) | K47: Visual Builder | M47: Pravalika G | N47: Visual Builder
A48: 47 | B48: Inventory Management | C48: Cost Management | D48: Redwood: Create and Update Standard Costs Using a New User Experience | E48: 25A | F48: 25B | H48: To search for manufacturers using a Redwood page: Get Search View REST(EGP_GET_SEARCH_VIEW_REST_PRIV) To view manufacturers: View Manufacturer (EGP_VIEW_MANUFACTURER_PRIV) To edit manufacturers: Manage Manufacturer (EGP_MANAGE_MANUFACTURER_PRIV) To create manufacturers: Create Manufacturer (EGP_CREATE_MANUFACTURER_PRIV) Manage Manufacturer (EGP_MANAGE_MANUFACTURER_PRIV) | I48: On the Manage Administrator Profile Values page, search for and select the ORA_CST_STANDARD_COSTS_REDWOOD_ENABLED profile option code. In the Profile Values section, set the Site level to Yes. The default value is No. Click Save and Close. Changes in the profile value will affect users the next time they sign in. Yes = enables the feature No = disables the feature | K48: Role Setup+Profile option | L48: Y | M48: Miriam Chandni | N48: Cost Accounting Work Area
A49: 48 | B49: Inventory Management | C49: Cost Management | D49: Redwood: Compare Standard Costs Using a New User Experience | E49: 25A | F49: 25B | H49: Access Clipboard (ACA_ACCESS_CLIPBOARD_PRIV) | I49: On the Manage Administrator Profile Values page, search for and select the ORA_CST_COMPARE_STD_COSTS_REDWOOD_ENABLED profile option code. In the Profile Values section, set the Site level to Yes. The default value is No. Click Save and Close. Changes in the profile value will affect users the next time they sign in. Yes = enables the feature No = disables the feature | K49: Role Setup+Profile option | L49: Y | M49: Miriam Chandni | N49: Cost Accounting Work Area
A50: 49 | B50: Supply Chain Collaboration | C50: Supply Chain Collaboration | D50: Manage Supplier On-Hand Quantities Using a Redwood Page | E50: 24C | F50: 26A | H50: To view the item structure on the Redwood page: View Product Management Search (EGP_VIEW_PRODUCT_MGT_SEARCH) View Item (EGP_VIEW_ITEM) Create Item Structure (EGP_CREATE_ITEM_STRUCTURE_PRIV) Get Search View REST (EGP_GET_SEARCH_VIEW_REST_PRIV) Data Security: View Item Basic Access Item Structure Data Using a REST Service (EGP_GET_ITEM_STRUCTURE_REST_PRIV) Access Structure Attributes for Indexing Using REST (EGP_GET_PM_STRUCTURE_AVAIL_REST_PRIV) | K50: OPT IN+Role Setup | L50: Y | M50: Veeranarayana Swamy | N50: Supplier On-Hand Quantities
A51: 50 | B51: Supply Chain Collaboration | C51: Supply Chain Collaboration | D51: Manage Supply Collaboration Network Using a Redwood Page | E51: 24C | F51: 25D | H51: You should have Monitor Product Management Workflow Objects (ACA_MONITOR_PRODUCT_MANAGEMENT_WORFLOW_OBJECTS_PRIV) and one of the following privileges: For change orders: View Change Order (ACA_VIEW_CHANGE_ORDERS_PRIV) or Manage Change Orders (ACA_MANAGE_CHANGE_ORDERS_PRIV) For change requests: View Change Request (ACA_VIEW_CHANGE_REQUESTS_PRIV) or Manage Change Requests (ACA_MANAGE_CHANGE_REQUESTS_PRIV) For problem reports: View Problem Report (ACA_VIEW_PROBLEM_REPORTS_PRIV) or Manage Problem Report (ACA_MANAGE_PROBLEM_REPORT_PRIV) For corrective and preventive actions: View Corrective Action (ACA_VIEW_CORRECTIVE_ACTIONS_PRIV) or Manage Corrective Action (ACA_MANAGE_CORRECTIVE_ACTION_PRIV) | K51: OPT IN+Role Setup | M51: Venkat | N51: Supply Collaboration Network
A52: 51 | B52: Supply Chain Collaboration | C52: Supply Chain Collaboration | D52: Manage Upload Supply Data Using a Redwood Page | E52: 24C | F52: 26A | H52: You should have Monitor Product Management Workflow Objects (ACA_MONITOR_PRODUCT_MANAGEMENT_WORFLOW_OBJECTS_PRIV) and one of the following privileges: For change orders: View Change Order (ACA_VIEW_CHANGE_ORDERS_PRIV) or Manage Change Orders (ACA_MANAGE_CHANGE_ORDERS_PRIV) For change requests: View Change Request (ACA_VIEW_CHANGE_REQUESTS_PRIV) or Manage Change Requests (ACA_MANAGE_CHANGE_REQUESTS_PRIV) For problem reports: View Problem Report (ACA_VIEW_PROBLEM_REPORTS_PRIV) or Manage Problem Report (ACA_MANAGE_PROBLEM_REPORT_PRIV) For corrective and preventive actions: View Corrective Action (ACA_VIEW_CORRECTIVE_ACTIONS_PRIV) or Manage Corrective Action (ACA_MANAGE_CORRECTIVE_ACTION_PRIV) Users who are assigned a configured job role that contains these privileges can access assigned notifications: For Item Change Orders: EGO_VIEW_ITEM_CHANGE_ORDER_PRIV For New Item Request: EGO_VIEW_NEW_ITEM_REQUEST_PRIV | K52: OPT IN+Role Setup | M52: Venkat | N52: Upload Supply Data
A53: 52 | B53: Supply Chain Collaboration | C53: Supply Chain Collaboration | D53: Manage Collaboration Planners Using a Redwood Page | E53: 24B | F53: 25B | H53: Landing Page (ORA_EGP_LANDING_PAGE_DUTY) contains: View Item Redwood (ORA_EGP_REDWOOD_VIEW_ITEM_DUTY) Product Search (ORA_EGI_PRODUCT_SEARCH_DUTY) Access Object Tag Set Repository (ACA_ACCESS_OBJECT_TAG_SETS_PRIV) Access Object Tags Repository (ACA_ACCESS_OBJECT_TAGS_PRIV) Access Product Management Landing Page (EGP_ACCESS_LANDING_PAGE_PRIV) Manage Landing Page Layout (EGP_MANAGE_LANDING_PAGE_LAYOUT_PRIV) Access Clipboard (ACA_ACCESS_CLIPBOARD_PRIV) Access HCM Common Components (HRC_ACCESS_HCM_COMMON_COMPONENTS_PRIV) Manage Search Consumer Applications Rest (EGP_MANAGE_SEARCH_CONS_REST_PRIV) | K53: OPT IN+Role Setup | M53: Venkat | N53: Collaboration Planners
A54: 53 | B54: Supply Chain Collaboration | C54: Supply Chain Collaboration | D54: Manage Collaboration Plans Using a Redwood Page | E54: 24B | F54: 25B | K54: OPT IN+Role Setup | M54: Venkat | N54: Collaboration Plans
A55: 54 | B55: Supply Chain Collaboration | C55: Supply Chain Collaboration | D55: Manage VMI Analysts Using a Redwood Page | E55: 24B | F55: 25B | H55: View Item Redwood Items (EGP_VIEW_REDWOOD_ITEM_PRIV) View Item Redwood Attachments (EGP_VIEW_REDWOOD_ITEM_ATTACHMENT_PRIV) View Item Redwood Associations (EGP_VIEW_REDWOOD_ITEM_ASSOCIATION_PRIV) View Item Redwood Structures (EGP_VIEW_REDWOOD_ITEM_STRUCTURE_PRIV) View Item Redwood Changes (EGP_VIEW_REDWOOD_ITEM_CHANGE_PRIV) View Item Redwood Item Categories (EGP_VIEW_REDWOOD_ITEM_CATEGORIES_PRIV) View Item Redwood Relationships (EGP_VIEW_REDWOOD_ITEM_RELATIONSHIP_PRIV) View Item Redwood Quality (EGP_VIEW_REDWOOD_ITEM_QUALITY_PRIV) Supply Chain Common View Web Service (ORA_RCS_SCM_COMMON_VIEW_WEB_SERVICE_DUTY) Enter Trading Community Organization Information (HZ_ENTER_TRADING_COMMUNITY_ORGANIZATION_INFORMATION_PRIV) Get Failure Condition Event Codes (MNT_GET_FAILURE_CONDITION_EVENT_CODE_BY_SERVICE_PRIV) Get Item Attribute Control REST (EGP_ITEM_ATTRIBUTE_CONTROL_READ_PRIV) Get Item Lifecycle Phases Read Rest (EGP_ITEM_LIFECYCLE_PHASES_READ_REST_PRIV) Get Item Status REST (EGP_ITEM_STATUSES_READ_PRIV) Get New Item Request Rest (EGI_NEW_ITEM_REQUEST_REST_PRIV) Get Template REST (EGP_TEMPLATE_READ_PRIV) Manage Material Planner (MSP_MANAGE_MATERIAL_PLANNER_PRIV) Manage Subscription Setup (OSS_MANAGE_SUBSCRIPTION_SETUP_PRIV) Remove Trading Community Organization (HZ_REMOVE_TRADING_COMMUNITY_ORGANIZATION_PRIV) Set Up Receivables Payment Terms (AR_SET_UP_RECEIVABLES_PAYMENT_TERM_PRIV) Update Trading Community Organization (HZ_UPDATE_TRADING_COMMUNITY_ORGANIZATION_PRIV) Verify Tax Configuration (ZX_VERIFY_TAX_CONFIGURATION_PRIV) View Procurement Buyers List of Values using REST Service (PO_VIEW_BUYER_LOV_REST_SERVICE_PRIV) View Purchasing Hazard Classes List of Values using REST Service (PO_VIEW_HAZARD_CLASSES_LOV_REST_SERVICE_PRIV) View Purchasing UN Numbers List of Values using REST Service (PO_VIEW_UNNUMBER_LOV_REST_SERVICE_PRIV) View Trading Community Organization (HZ_VIEW_TRADING_COMMUNITY_ORGANIZATION_PRIV) View Trading Community Person (HZ_VIEW_TRADING_COMMUNITY_PERSON_PRIV) Manage Item Redwood Items (EGP_MANAGE_REDWOOD_ITEM_PRIV) Manage Item Redwood Attachments (EGP_MANAGE_REDWOOD_ITEM_ATTACHMENT_PRIV) Manage Item Redwood Associations (EGP_MANAGE_REDWOOD_ITEM_ASSOCIATION_PRIV) Manage Item Redwood Item Categories (EGP_MANAGE_REDWOOD_ITEM_CATEGORY_PRIV) Manage Item Redwood Relationships (EGP_MANAGE_REDWOOD_ITEM_RELATIONSHIP_PRIV) Manage Item Redwood Structures (EGP_MANAGE_REDWOOD_ITEM_STRUCTURE_PRIV) Get New Item Request Rest (EGI_NEW_ITEM_REQUEST_REST_PRIV) Manage Item Status REST (EGP_ITEM_STATUSES_PRIV) | K55: OPT IN+Role Setup | M55: Venkat | N55: VMI Analytics
A56: 55 | B56: Supply Chain Collaboration | C56: Supply Chain Collaboration | D56: Specify Aggregation Schedule Using a Redwood Page | E56: 24B | F56: 26A | H56: To access the item on Redwood page: View Item Redwood Items (EGP_VIEW_REDWOOD_ITEM_PRIV) Manage Item Redwood Items (EGP_MANAGE_REDWOOD_ITEM_PRIV) To create, manage, or view the item structure on the Redwood page: Create Item Structure (EGP_CREATE_ITEM_STRUCTURE_PRIV) Manage Item Redwood Structures (EGP_MANAGE_REDWOOD_ITEM_STRUCTURE_PRIV) View Item Redwood Structures (EGP_VIEW_REDWOOD_ITEM_STRUCTURE_PRIV To manage change order on Redwood page: Manage Change Orders (ACA_MANAGE_CHANGE_ORDERS_PRIV) | K56: OPT IN+Role Setup | M56: Venkat | N56: Select Aggregation Schedule
A57: 56 | B57: Inventory Management | C57: Inventory Management | D57: Manage Subinventories and Locators on Redesigned Pages | E57: 24A | F57: 26A | I57: Get Item Rest (EGP_GET_ITEM_REST_PRIV) Manage Inventory Status (INV_MANAGE_INVENTORY_STATUS_PRIV) Manage Subinventory and Locator (INV_MANAGE_SUBINVENTORY_AND_LOCATOR_PRIV) Manage Unit of Measure Usage (INV_MANAGE_UNIT_OF_MEASURE_USAGE_PRIV) View Inventory On-Hand Balance Web Service (INV_VIEW_INVENTORY_ONHAND_BALANCE_WEB_SERVICE_PRIV) View Subinventory and Locator List of Values by Web Service (INV_VIEW_SUBINVENTORY_LOCATOR_LOV_WEB_SERVICE_PRIV) View Inventory Organizations List of Values by Web Service (RCS_VIEW_INV_ORG_LOV_WEB_SERVICE_PRIV) View Units of Measure List of Values by Web Service (RCS_VIEW_UNITS_OF_MEASURE_LOV_WEB_SERVICE_PRIV) | K57: OPT IN | L57: Y | M57: Miriam Chandni | N57: Inventory Management work area
A58: 57 | B58: Inventory Management | C58: Inventory Management | D58: Manage Item Transaction Defaults on a Redesigned Page | E58: 24B | F58: 26A | H58: View Item Redwood Items (EGP_VIEW_REDWOOD_ITEM_PRIV) Manage Item Supplier Associations (EGP_MANAGE_REDWOOD_ITEM_SUPPLIER_ASSOCIATION_PRIV) | K58: Role Setup+Profile option | L58: Y | M58: Miriam Chandni | N58: Inventory Management work area
A59: 58 | B59: Procurement | C59: Purchasing | D59: Search for Purchase Agreements Using a Redwood Page | E59: 24B | F59: 26A | H59: View Item Redwood Items (EGP_VIEW_REDWOOD_ITEM_PRIV) Manage Item Redwood Items (EGP_MANAGE_REDWOOD_ITEM_PRIV) | I59: Manage Administrator Profile Values > ORA_PO_MANAGE_AGREEMENTS_REDWOOD_ENABLED = Y | J59: 1. Submit the ESS job to create index definition and perform initial ingest to OSCS scheduled process with this index name: Purchase Agreements: fa-prc-pa 2. We can Confiure Guided Journey 3. We can use VBCS to hide or show field | K59: OPT IN+ Profile Option | L59: Y | M59: Karthik Gopal | N59: Purchase Agreements
A60: 59 | B60: Procurement | C60: Responsive Self Service Procurement | D60: Create Multiple Distributions on Requisitions | E60: 24B | F60: 26A | H60: For items: View Item Redwood (ORA_EGP_REDWOOD_VIEW_ITEM_DUTY) For landing page: Access Product Management Landing Page (EGP_ACCESS_LANDING_PAGE_PRIV) Access Clipboard (ACA_ACCESS_CLIPBOARD_PRIV) Access HCM Common Components (HRC_ACCESS_HCM_COMMON_COMPONENTS_PRIV) For manufacturers: View Manufacturer (EGP_VIEW_MANUFACTURER_PRIV) For change orders: View Change Order (ACA_VIEW_CHANGE_ORDERS_PRIV) or Manage Change Orders (ACA_MANAGE_CHANGE_ORDERS_PRIV) | K60: Role Setup+Profile option | L60: Y | M60: Pragyan Dash | N60: Requisition Line
A61: 60 | B61: Procurement | C61: Responsive Self Service Procurement | D61: View Requisition Lifecycle Information | E61: 24B | F61: 25D | H61: Product Management Search Page Product Search (ORA_EGI_PRODUCT_SEARCH_DUTY) and Product Search (ORA_EGI_PRODUCT_SEARCH_HCM_DUTY) duty roles contain the following privileges: Access Product Development Configurations Using a REST Service (ACA_GET_PD_CONFIGURATIONS_REST_PRIV) GET Product Management Index REST (EGP_GET_PM_INDEX_REST_PRIV) Get Item Index Available Attributes REST (EGP_GET_PM_ITEM_AVAIL_REST_PRIV) Get Search View REST (EGP_GET_SEARCH_VIEW_REST_PRIV) Manage Search View REST (EGP_MANAGE_SEARCH_VIEW_REST_PRIV) Manage System Searches (HRC_MANAGE_SYSTEM_SEARCHES_PRIV) Use REST Service - Saved Searches (HRC_REST_SERVICE_ACCESS_SAVED_SEARCHES_PRIV) View Product Management Search (EGP_VIEW_PRODUCT_MGT_SEARCH_PRIV) Access HCM Common Components (HRC_ACCESS_HCM_COMMON_COMPONENTS_PRIV) Manage Search Consumer Applications Rest (EGP_MANAGE_SEARCH_CONS_REST_PRIV) | K61: OPT IN | L61: Y | M61: Karthik Gopal | N61: Requisition Line
A62: 61 | B62: Procurement | C62: Responsive Self Service Procurement | D62: View Requisition Document History | E62: 24B | F62: 25D | H62: To search for manufacturers using a Redwood page: Access Product Development Configurations Using a REST Service(ACA_GET_PD_CONFIGURATIONS_REST_PRIV) Access Product Management Landing Page(EGP_ACCESS_LANDING_PAGE_PRIV) Get Search View REST(EGP_GET_SEARCH_VIEW_REST_PRIV) Manage Product Management Data Security EGO_MGT_PRODUCT_MGT_DATA_SECURITY_PRIV) View Feature States Value by Web Service(RCS_VIEW_FEATURE_STATES_WEB_SERVICE_PRIV) Get View Available Attribute REST (EGP_VIEW_AVAIL_ATTR_REST_PRIV) Grant Search Framework Manager Permissions (FND_SEARCH_FWK_MGR_PRIV) To view only manufacturers: View Manufacturer (EGP_VIEW_MANUFACTURER_PRIV) To edit manufacturers: Manage Item Manufacturer (EGP_MANAGE_ITEM_MANUFACTURER_PRIV) Manage Manufacturers (EGP_MANAGE_MANUFACTURER_PRIV) To create manufacturers: Create Manufacturer (EGP_CREATE_MANUFACTURER_PRIV) Manage Manufacturer (EGP_MANAGE_MANUFACTURER_PRIV) | K62: Role Setup+Profile option | L62: Y | M62: Pragyan Dash | N62: Requisition Header
A63: 62 | B63: Procurement | C63: Responsive Self Service Procurement | D63: Assign Additional Supplier Contact Emails for Catalog Item-Based Requisitions | E63: 24B | F63: 25D | H63: Manage Requisition with the Responsive Self Service Procurement Application (POR_MANAGE_REQ_WITH_PWA_PRIV). | I63: ORA_POR_RESP_DISABLE_CONTACT_AUTOSOURCING | K63: OPT IN+Profile option+Role Setup | L63: Y | M63: Karthik Gopal | N63: Requisition Line
A64: 63 | B64: Procurement | C64: Responsive Self Service Procurement | D64: Change Description for Agreement Based Items During Shopping | E64: 24B | F64: 25D | H64: Manage Requisition with the Responsive Self Service Procurement Application (POR_MANAGE_REQ_WITH_PWA_PRIV) | K64: OPT IN+Role Setup | L64: Y | M64: Pragyan Dash | N64: Requisition Line
A65: 64 | B65: Procurement | C65: Responsive Self Service Procurement | D65: Refine Requisition Search Using Filters | E65: 24B | F65: 25D | H65: Requisition Self Service Responsive Application User Duty (ORA_POR_REQUISITION_SELF_SERVICE_PWA_USER_DUTY) | K65: OPT IN+Role Setup | L65: Y | M65: Pragyan Dash | N65: My Requisition Search
A66: 65 | B66: Product Hub | C66: Product Hub | D66: Search Product Management Content Using the Redwood User Experience | E66: 24B | F66: 26C | H66: View Product Management Search (EGP_VIEW_PRODUCT_MGT_SEARCH_PRIV) Get Search View Rest (EGP_GET_SEARCH_VIEW_REST_PRIV) GET Product Management Index REST (EGP_GET_PM_INDEX_REST_PRIV) | J66: Mandate version is not specified hence considering the mandate version as per Roadmap for PLM module which is 26B. | K66: OPT IN+Role Setup | L66: Y | M66: Karthik Gopal | N66: Product Management Search
A67: 66 | B67: Product Hub | C67: Product Hub | D67: Manage Spoke Systems Using the Redwood User Experience | E67: 24B | F67: 26C | H67: Manage Item Source System (EGI_MANAGE_ITEM_SOURCE_SYSTEM_PRIV) | I67: ORA_EGI_SPOKE_SYSTEM_REDWOOD_PAGES_ENABLED | J67: Mandate version is not specified hence considering the mandate version as per Roadmap for PLM module which is 26B. | K67: Role Setup+Profile option | L67: Y | M67: Karthik Gopal | N67: Manage Spoke Systems
A68: 67 | B68: Product Hub | C68: Product Hub | D68: Manage Delete Groups Using the Redwood User Experience | E68: 24B | F68: 26C | H68: Manage Item Delete Group (EGP_MANAGE_ITEM_DELETE_GROUP_PRIV) Access Item Structure Data Using a REST Service (EGP_GET_ITEM_STRUCTURE_REST_PRIV) Access Change Order Using a REST Service (ACA_GET_CHANGE_REST_PRIV) Manage Delete Group Rest (EGP_DG_REST_PRIV) GET Product Management Index REST (EGP_GET_PM_INDEX_REST_PRIV) Get Search View REST (EGP_GET_SEARCH_VIEW_REST_PRIV) Grant Search Framework Manager Permissions (FND_SEARCH_FWK_MGR_PRIV) View Product Management Search (EGP_VIEW_PRODUCT_MGT_SEARCH_PRIV) | I68: ORA_EGP_DELETE_GROUPS_REDWOOD_PAGES_ENABLED | J68: Mandate version is not specified hence considering the mandate version as per Roadmap for PLM module which is 26B. | K68: Role Setup+Profile option | L68: Y | M68: Karthik Gopal | N68: Manage Delete Groups
A69: 68 | B69: Inventory Management | C69: Inventory Management | D69: Manage Lots and Serial Numbers Using a Redwood Page | E69: 24C | F69: 26B | H69: Manage Lots and Serial Numbers Using Responsive Inventory Duty (ORA_INV_MANAGE_LOT_SERIAL_PWA_DUTY) | I69: ORA_INV_LOTS_AND_SERIAL_NUMBERS_REDWOOD_ENABLED | K69: Role Setup+Profile option | L69: Y | M69: Pragyan Dash | N69: Inventory Management work area
A70: 69 | B70: Inventory Management | C70: Inventory Management | D70: Create Multiple New Subinventories and Locators Simultaneously | E70: 24C | F70: 26B | H70: Configure Subinventory Using Responsive Inventory (ORA_INV_CONFIGURE_SUBINVENTORY_PWA_DUTY) | K70: OPT IN | L70: Y | M70: Pragyan Dash | N70: Subinventories page
A71: 70 | B71: Inventory Management | C71: Inventory Management | D71: Approve Count Sequences Using a Redwood Page | E71: 24C | F71: 26B | H71: Approve Cycle Count Using Responsive Inventory Duty (ORA_INV_APPROVE_CYCLE_COUNT_PWA_DUTY) | I71: ORA_INV_CYCLE_COUNT_REDWOOD_ENABLED | K71: Role Setup+Profile option | L71: Y | M71: Pragyan Dash | N71: Cycle count Approvals
A72: 71 | B72: Inventory Management | C72: Inventory Management | D72: Create Outbound Shipment Requests Using a Redwood Page | E72: 24C | F72: 26B | H72: Create Outbound Shipment Request Using Responsive Shipping (ORA_WSH_CREATE_OUTBOUND_SHIPMENT_REQUEST_PWA_DUTY) | I72: ORA_WSH_PICK_WAVE_SHIPMENT_REQUEST_REDWOOD_PAGES_ENABLED | K72: Role Setup+Profile option | L72: Y | M72: Mukesh Panwar | N72: Outbound Shipment Request
A73: 72 | B73: Inventory Management | C73: Inventory Management | D73: Create Pick Waves Using a Redwood Page | E73: 24C | F73: 26B | H73: Create Pick Wave Using Responsive Shipping (ORA_WSH_CREATE_PICK_WAVE_PWA_DUTY) | I73: ORA_WSH_PICK_WAVE_SHIPMENT_REQUEST_REDWOOD_PAGES_ENABLED | K73: Role Setup+Profile option | L73: Y | M73: Mukesh Panwar | N73: New Pick Wave
A74: 73 | B74: Order Management | C74: Global Order Promising | D74: Review Calendar Associations Using a Redwood Page | E74: 24C | F74: 26B | H74: NR | I74: NR | J74: Dependent on Review Planning Calendars Using a Redwood Page | K74: OPT IN | L74: Y | M74: Ashoka Veerabhadrappa | N74: Supply Chain Planning
A75: 74 | B75: Inventory Management | C75: Cost Management | D75: Redwood: Create and Edit Cost Analysis Groups Using a New User Experience | E75: 25B | F75: 26B | H75: Manage Workflow Notifications (FUN_MANAGE_WORKFLOW_NOTIFICATIONS_PRIV) to view approvers. 2) Manage Requisition with the Responsive Self Service Procurement Application (POR_MANAGE_REQ_WITH_PWA_PRIV) to access the responsive application. | I75: No profile | J75: No profile | K75: Auto Enabled | L75: Yes | M75: Rekha Bhoopathy | N75: Cost Analysis Groups Page
A76: 75 | B76: Procurement | C76: Responsive Self Service Procurement | D76: View Requisitions Created by Other Preparers | E76: 24C | F76: 26B | H76: Manage Requisition with the Responsive Self Service Procurement Application (POR_MANAGE_REQ_WITH_PWA_PRIV) to access the responsive application. 2) View Requisition - All (POR_VIEW_REQUISITION_ALL_PRIV) to view all requisitions in accessible requisitioning BUs | K76: OPT IN+Role Setup | L76: Y | M76: Pragyan Dash | N76: My Requisition Search
A77: 76 | B77: Procurement | C77: Responsive Self Service Procurement | D77: Manage Approvers on Requisitions during Shopping Checkout | E77: 24C | F77: 26B | H77: Manage Workflow Notifications (FUN_MANAGE_WORKFLOW_NOTIFICATIONS_PRIV) to view approvers. 2) Manage Requisition with the Responsive Self Service Procurement Application (POR_MANAGE_REQ_WITH_PWA_PRIV) to access the responsive application. | K77: OPT IN+Role Setup | L77: Y | M77: Ashoka Veerabhadrappa | N77: PR Approval notification
A78: 77 | B78: Procurement | C78: Responsive Self Service Procurement | D78: Modify Requisitions as an Approver | E78: 24C | F78: 26B | H78: Manage Requisition with the Responsive Self Service Procurement Application (POR_MANAGE_REQ_WITH_PWA_PRIV). 2) Edit Requisition as Approver (POR_CREATE_REQUISITION_ALLOW_APPROVER_MODIFICATION_PRIV) | K78: OPT IN+Role Setup | L78: Y | M78: Pragyan Dash | N78: Workflow approval
A79: 78 | B79: Procurement | C79: Responsive Self Service Procurement | D79: Create Urgent Requisitions | E79: 24C | F79: 26B | H79: Manage Requisition with the Responsive Self Service Procurement Application (POR_MANAGE_REQ_WITH_PWA_PRIV) | K79: OPT IN+Role Setup | L79: Y | M79: Pragyan Dash | N79: Requisition Line
A80: 79 | B80: Procurement | C80: Responsive Self Service Procurement | D80: Update the Preparer and Requester on Requisitions | E80: 24C | F80: 26B | H80: Manage Requisition with the Responsive Self Service Procurement Application (POR_MANAGE_REQ_WITH_PWA_PRIV) | I80: ORA_POR_USE_SUPP_SITE_INVOICE_CURR) | K80: OPT IN+Profile option+Role Setup | L80: Y | M80: Pragyan Dash | N80: Requisition dashboard
A81: 80 | B81: Procurement | C81: Responsive Self Service Procurement | D81: Create Requisitions as an Advanced User | E81: 24C | F81: 26B | H81: Manage Requisition with the Responsive Self Service Procurement Application (POR_MANAGE_REQ_WITH_PWA_PRIV). Create Requisition with Quick Entry (POR_CREATE_REQUISITION_ALLOW_QUICK_ENTRY_PRIV). View Total On Hand Quantity in Supply Source (DOS_VIEW_AVAILABLE_ONHAND_QTY_PRIV) to view available quantity in a source organization. View Subinventory List of Values by Web Service for Self Service Procurement User (INV_VIEW_SUBINVENTORY_LOV_PRC_WEB_SERVICE_PRIV) to view subinventory list of values. | K81: OPT IN+Role Setup | L81: Y | M81: Mukesh Panwar | N81: Requisition Line UI
A82: 81 | B82: Procurement | C82: Responsive Self Service Procurement | D82: Populate Currency on Requisition Lines Automatically from the Supplier Site’s Invoice Currency | E82: 24C | F82: 26B | H82: Manage Requisition with the Responsive Self Service Procurement Application (POR_MANAGE_REQ_WITH_PWA_PRIV). | I82: ORA_POR_USE_SUPP_SITE_INVOICE_CURR) | K82: OPT IN+Role Setup | L82: Y | M82: Mukesh Panwar | N82: Requisition Line UI
A83: 82 | B83: Supply Chain Execution | C83: Supply Chain Orchestration | D83: Use Redesigned Pages to View Supply Request Lines | E83: 24C | F83: 26B | K83: Auto Enabled | L83: Y | M83: Venkat | N83: View Supply Request Line Details
A84: 83 | B84: Product Hub | C84: Product Development | D84: Enhance Manufacturer Management | E84: 24C | F84: 26B | H84: To search for manufacturers using a Redwood page: Get Search View REST(EGP_GET_SEARCH_VIEW_REST_PRIV) To view only manufacturers: View Manufacturer (EGP_VIEW_MANUFACTURER_PRIV) To edit manufacturers: Manage Manufacturer (EGP_MANAGE_MANUFACTURER_PRIV) To create manufacturers: Create Manufacturer (EGP_CREATE_MANUFACTURER_PRIV) Manage Manufacturer (EGP_MANAGE_MANUFACTURER_PRIV) | J84: Mandate version is not specified hence considering the mandate version as per Roadmap for PLM module which is 26B. | K84: Role Setup+Profile option | L84: Y | M84: Karthik Gopal | N84: New Manufacturer and Edit Manufacturer pages
A85: 84 | B85: Manufacturing | C85: Manufacturing | D85: Search for, Create, and Edit Work Definition Names Using the Redwood User Experience | E85: 24B | F85: 26A | I85: ORA_WIS_WORK_DEFINITION_NAMES_REDWOOD_ENABLED | K85: Role Setup+Profile option | N85: Work Definition UI
A86: 85 | B86: Manufacturing | C86: Manufacturing | D86: Search for, Create, and Edit Work Areas Using the Redwood User Experience | E86: 24B | F86: 26A | I86: ORA_WIS_WORK_AREAS_REDWOOD_ENABLED | K86: Role Setup+Profile option | N86: Manufacturing Work Areas UI
A87: 86 | B87: Manufacturing | C87: Smart Operations | D87: Create, Edit, and Search for Workstations | E87: 24C | F87: 26A | K87: OPT IN | L87: Y | M87: Yoga Gopalakrishnan | N87: Workstations under Plant Setup
A88: 87 | B88: Manufacturing | C88: Smart Operations | D88: Execute Production at a Workstation and Automate Resource Transactions | E88: 24C | F88: 26A | K88: OPT IN | L88: Y | M88: Yoga Gopalakrishnan | N88: Execute Production at a Workstation page
A89: 88 | B89: Manufacturing | C89: Smart Operations | D89: Create Shift Notes During Work Execution at a Workstation for Operator Handoff | E89: 24C | F89: 26A | K89: OPT IN+Setup | L89: Y | M89: Yoga Gopalakrishnan | N89: Workstation page
A90: 89 | B90: Manufacturing | C90: Manufacturing | D90: Search for, Create, and Edit Work Order Statuses Using the Redwood User Experience | E90: 24C | F90: 26A | I90: ORA_WIE_WO_STATUSES_REDWOOD_ENABLED | K90: Role Setup+Profile option | L90: Y | M90: Veeranarayana Swamy | N90: Manage Work Order Statuses
A91: 90 | B91: Manufacturing | C91: Manufacturing | D91: Search for, Create, and Edit Work Centers Using the Redwood User Experience | E91: 24C | F91: 26A | I91: ORA_WIS_WORK_CENTERS_REDWOOD_ENABLED | K91: Role Setup+Profile option | L91: Y | M91: Veeranarayana Swamy | N91: Work Center
A92: 91 | B92: Manufacturing | C92: Manufacturing | D92: Search for, Create, and Edit Standard Operations Using a Redwood User Experience | E92: 24C | F92: 26A | I92: ORA_WIS_STANDARD_OPERATIONS_REDWOOD_ENABLED | K92: Role Setup+Profile option | L92: Y | M92: Veeranarayana Swamy | N92: Manage Standard Operations
A93: 92 | B93: Manufacturing | C93: Manufacturing | D93: Manage Work Definition Productivity Improvements Using the Redwood User Experience | E93: 24C | F93: 26A | I93: ORA_WIS_WORK_DEFINITIONS_REDWOOD_ENABLED | K93: Role Setup+Profile option | L93: Y | M93: Yoga Gopalakrishnan | N93: Work Definitions page
A94: 93 | B94: Inventory Management | C94: Inventory Management | D94: Redwood: Create Cycle Counts Using a Redwood Page | E94: 24D | F94: 26A | I94: ORA_INV_CREATE_CYCLE_COUNT_REDWOOD_ENABLED | K94: OPT IN | L94: Y | M94: Pragyan Dash | N94: Create Cycle count
A95: 94 | B95: Inventory Management | C95: Inventory Management | D95: Redwood: View Item Quantities Using a Redwood Page | E95: 24D | F95: 25B | K95: OPT IN | L95: Y | M95: Karthik Gopal | N95: Item Quantities
A96: 95 | B96: Inventory Management | C96: Receiving | D96: Redwood: Inspect Receipts Using a Redwood Page | E96: 24D | F96: 25B | I96: Manage Administrator Profile Values > ORA_RCV_INSPECT_RECEIPT_LINES_REDWOOD_ENABLED = Yes | J96: 1. Activate Sandbox to enable the Inventory Management (New) 2. Run the "ESS job to create index definition and perform Initial Ingest to OSCS" Refer: https://docs.oracle.com/en/cloud/saas/readiness/scm/24b/inv24b/24B-inventory-wn-f31373.htm | K96: Profile Option | L96: Y | M96: Karthik Gopal | N96: Inspect Receipt Line
A97: 96 | B97: Inventory Management | C97: Receiving | D97: Redwood: Create Receipt Returns Using a Redwood Page | E97: 24D | F97: 25B | I97: Manage Receiving Profile Options > ORA_RCV_RECEIVING_RETURNS_REDWOOD_ENABLED = Yes | K97: Profile Option | L97: Y | M97: Karthik Gopal | N97: Receipt Returns
